HW/RTL/06PCM-AUDIO-MICROFONO/Version_01/02 verilog/Prueba fifo/div_freq.v
module div_freq #(
              parameter   fi     = 100000000,           
              parameter   fs	 = 2000000        //flckout=((2.48*fs)/500000)KHZ
  )(input clk, output reg clkout,input reset, output reg led);



initial led=0;

reg [31:0] count;

always @(posedge  clk)
begin
	if (reset) begin
	led=1;
		count <=count-1;
		if (count==0)begin
			clkout <=~clkout;
			count <= fi/fs;
		end	
	end
	else begin
	led=0;
		count <= fi/fs;
		clkout <=0;
		
	end	
end


endmodule

HW/RTL/06PCM-AUDIO-MICROFONO/Version_01/02 verilog/Prueba fifo/microfono.v
module microfono
(
	output reg	ledlr,
	output 		ledres,
	input		clk,
	output		mclk,
	input		lr,
	output	reg	ws,
	input		dataint,
	input		reset,
	output reg [5:0] sregt//sregtl
	//output reg [5:0] sregtr


);
reg [0:5] count1;
//reg [0:5] count=0;
initial ws=0;
initial ledlr=0;
initial count1=0;
div_freq df(.clk(clk), .reset(reset),.clkout(mclk),.led(ledres));

always @(posedge  mclk)
begin

	//if (reset)
	//begin
	
	//end
	 
	//else
	//begin
	
	if(lr)
	begin
		
		if (count1<=5)  /* guarda 5 bits */
		begin
		
		ledlr=1;
		sregt<= {sregt[4:0],dataint};
		count1<=count1+1;
		end
		
		else 
		begin
		count1<=0;
		end
	end
	//end
	
end
 
//always @(negedge  mclk, negedge lr)
//begin

	//if (reset)
	//begin
	
	//end
	 
	//else
	//begin
	//count<=0;
	
		//if (count<=5)  /* guarda 5 bits */
		//begin
		//ledlr=0;
		//sregtl<= {sregtl[4:0],dataint};
		//count<=count+1;
		//end
	
	//end

	
//end


endmodule

HW/RTL/06PCM-AUDIO-MICROFONO/Version_01/02 verilog/Prueba fifo/fifo.v
// diseño de una fifo ciclica, para implementar en cada  bloque de proyecto
// ferney alberto beltran 2016 electrónica digital 1 universidad Nacional

module fifo
   #(
  	parameter adr_width = 12,
	parameter dat_width = 6
   )
   (
    input  clk, reset, mclk,
    input  rd, wr,
    input  [dat_width-1:0] data_in,
    output [dat_width-1:0] data_out,
    output empty, 
    output full,
    input dataint,
    input lr
   );

microfono mic(.clk(clk), .reset(reset),.sregt(data_in),.dataint,.lr(lr),.mclk(mclk));
  
  parameter depth = (1 << adr_width);

   //declaración de registros 
 
   reg [dat_width-1:0] array_reg [depth-1:0];// register array FIFO

   reg [adr_width-1:0] w_ptr_reg;
   reg [adr_width-1:0] w_ptr_next;
   reg [adr_width-1:0] r_ptr_reg, r_ptr_next;
   reg full_reg, empty_reg, full_next, empty_next;
   wire wr_en;
   wire rw;
  
   assign data_out = array_reg[r_ptr_reg];
   assign wr_en = wr & ~full_reg;

   assign full = full_reg;
   assign empty = empty_reg;
   assign rw = rd | wr;
   always @(posedge mclk) begin
      if (wr_en)
         array_reg[w_ptr_reg] <= data_in;
   end

   // fifo control logic
   // register for read and write pointers
   always @(posedge mclk) begin
      if (reset)
         begin
            w_ptr_reg = 0;
            r_ptr_reg = 0;
            full_reg = 1'b0;
            empty_reg = 1'b1;
         end
      else
         begin
            w_ptr_reg = w_ptr_next;
            r_ptr_reg = r_ptr_next;
            full_reg = full_next;
            empty_reg = empty_next;
         end
   end


   
   always @(posedge rw)
   begin
      if (reset) begin
	w_ptr_next =  0;
        r_ptr_next =  0;       
      end else begin
	      full_next = full_reg;
	      empty_next = empty_reg;
	      case ({wr, rd})
		 2'b01: // read
		    if (~empty_reg) // not empty
		       begin
		          r_ptr_next = r_ptr_reg + 1;
		          full_next = 1'b0;
		          if (r_ptr_next==w_ptr_reg)
		             empty_next = 1'b1;
		       end
		 2'b10: // write
		    if (~full_reg) // not full
		       begin
		          w_ptr_next = w_ptr_reg + 1;
		          empty_next = 1'b0;
		          if (w_ptr_next==r_ptr_reg)
		             full_next = 1'b1;
		       end
		 2'b11: // write and read
		    begin
		       w_ptr_next =  w_ptr_reg + 1;
		       r_ptr_next = r_ptr_reg + 1;
		    end
	      endcase
	end
   end


  
endmodule

HW/RTL/06PCM-AUDIO-MICROFONO/Version_01/02 verilog/Prueba fifo/controlador_TB.v

module controlador_TB;

reg dataint;
reg clk;
reg mclk;
reg ws;
reg reset;
reg lr;
reg rd;
reg wr;


microfono uut(.clk(clk),.reset(reset),.dataint(dataint),.lr(lr));
fifo uttf(.rd(rd),.wr(wr),.clk(clk),.reset(reset),.dataint(dataint),.lr(lr));
always
begin
clk =1'b1;
#2;
clk=1'b0;
#2;
end

initial
begin
reset =1'b0;
#10;
reset =1'b1;

end
initial
begin
wr=1'b1;
rd =1'b0;
end

initial
begin
lr =1'b0;
#10;
lr =1'b1;
#2000;
lr =1'b0;
#2000;
lr =1'b1;
end

initial begin
#100 dataint = 1'b1;
#150 dataint = 1'b0;
#150 dataint = 1'b1;
#150 dataint = 1'b0;
#150 dataint = 1'b0;
#150 dataint = 1'b1;
#150 dataint = 1'b0;
#150 dataint = 1'b1;
#100 dataint = 1'b1;
#150 dataint = 1'b0;
#150 dataint = 1'b1;
#150 dataint = 1'b0;
#150 dataint = 1'b0;
#150 dataint = 1'b1;
#150 dataint = 1'b0;
#150 dataint = 1'b1;
end
	
initial begin: TEST_CASE
     $dumpfile("controlador_TB.vcd");
     $dumpvars(-1, uut,uttf);

     #(10000) $finish;
   end

endmodule //

HW/RTL/06PCM-AUDIO-MICROFONO/Version_01/02 verilog/Prueba fifo/simulation/controlador_TB.vcd
$date
	Mon Oct 30 07:58:47 2017
$end
$version
	Icarus Verilog
$end
$timescale
	1s
$end
$scope module controlador_TB $end
$scope module uut $end
$var wire 1 ! clk $end
$var wire 1 " dataint $end
$var wire 1 # lr $end
$var wire 1 $ reset $end
$var wire 1 % mclk $end
$var wire 1 & ledres $end
$var reg 6 ' count1 [0:5] $end
$var reg 1 ( ledlr $end
$var reg 6 ) sregt [5:0] $end
$var reg 1 * ws $end
$scope module df $end
$var wire 1 ! clk $end
$var wire 1 $ reset $end
$var reg 1 % clkout $end
$var reg 32 + count [31:0] $end
$var reg 1 & led $end
$upscope $end
$upscope $end
$upscope $end
$scope module controlador_TB $end
$scope module uttf $end
$var wire 1 ! clk $end
$var wire 6 , data_out [5:0] $end
$var wire 1 " dataint $end
$var wire 1 - empty $end
$var wire 1 . full $end
$var wire 1 # lr $end
$var wire 1 / rd $end
$var wire 1 $ reset $end
$var wire 1 0 rw $end
$var wire 1 1 wr $end
$var wire 1 2 wr_en $end
$var wire 1 3 mclk $end
$var wire 6 4 data_in [5:0] $end
$var reg 1 5 empty_next $end
$var reg 1 6 empty_reg $end
$var reg 1 7 full_next $end
$var reg 1 8 full_reg $end
$var reg 12 9 r_ptr_next [11:0] $end
$var reg 12 : r_ptr_reg [11:0] $end
$var reg 12 ; w_ptr_next [11:0] $end
$var reg 12 < w_ptr_reg [11:0] $end
$scope module mic $end
$var wire 1 ! clk $end
$var wire 1 " dataint $end
$var wire 1 # lr $end
$var wire 1 $ reset $end
$var wire 1 3 mclk $end
$var wire 1 = ledres $end
$var reg 6 > count1 [0:5] $end
$var reg 1 ? ledlr $end
$var reg 6 @ sregt [5:0] $end
$var reg 1 A ws $end
$scope module df $end
$var wire 1 ! clk $end
$var wire 1 $ reset $end
$var reg 1 3 clkout $end
$var reg 32 B count [31:0] $end
$var reg 1 = led $end
$upscope $end
$upscope $end
$upscope $end
$upscope $end
$enddefinitions $end
#0
$dumpvars
b110010 B
0A
bx @
0?
b0 >
0=
bx <
bx ;
bx :
bx 9
x8
x7
x6
x5
bx 4
03
x2
11
10
0/
x.
x-
bx ,
b110010 +
0*
bx )
0(
b0 '
0&
0%
0$
0#
x"
1!
$end
#2
0!
#4
1!
#6
0!
#8
1!
#10
0!
1#
1$
#12
b110001 B
b110001 +
1=
1&
1!
#14
0!
#16
b110000 +
b110000 B
1!
#18
0!
#20
b101111 B
b101111 +
1!
#22
0!
#24
b101110 +
b101110 B
1!
#26
0!
#28
b101101 B
b101101 +
1!
#30
0!
#32
b101100 +
b101100 B
1!
#34
0!
#36
b101011 B
b101011 +
1!
#38
0!
#40
b101010 +
b101010 B
1!
#42
0!
#44
b101001 B
b101001 +
1!
#46
0!
#48
b101000 +
b101000 B
1!
#50
0!
#52
b100111 B
b100111 +
1!
#54
0!
#56
b100110 +
b100110 B
1!
#58
0!
#60
b100101 B
b100101 +
1!
#62
0!
#64
b100100 +
b100100 B
1!
#66
0!
#68
b100011 B
b100011 +
1!
#70
0!
#72
b100010 +
b100010 B
1!
#74
0!
#76
b100001 B
b100001 +
1!
#78
0!
#80
b100000 +
b100000 B
1!
#82
0!
#84
b11111 B
b11111 +
1!
#86
0!
#88
b11110 +
b11110 B
1!
#90
0!
#92
b11101 B
b11101 +
1!
#94
0!
#96
b11100 +
b11100 B
1!
#98
0!
#100
b11011 B
b11011 +
1!
1"
#102
0!
#104
b11010 +
b11010 B
1!
#106
0!
#108
b11001 B
b11001 +
1!
#110
0!
#112
b11000 +
b11000 B
1!
#114
0!
#116
b10111 B
b10111 +
1!
#118
0!
#120
b10110 +
b10110 B
1!
#122
0!
#124
b10101 B
b10101 +
1!
#126
0!
#128
b10100 +
b10100 B
1!
#130
0!
#132
b10011 B
b10011 +
1!
#134
0!
#136
b10010 +
b10010 B
1!
#138
0!
#140
b10001 B
b10001 +
1!
#142
0!
#144
b10000 +
b10000 B
1!
#146
0!
#148
b1111 B
b1111 +
1!
#150
0!
#152
b1110 +
b1110 B
1!
#154
0!
#156
b1101 B
b1101 +
1!
#158
0!
#160
b1100 +
b1100 B
1!
#162
0!
#164
b1011 B
b1011 +
1!
#166
0!
#168
b1010 +
b1010 B
1!
#170
0!
#172
b1001 B
b1001 +
1!
#174
0!
#176
b1000 +
b1000 B
1!
#178
0!
#180
b111 B
b111 +
1!
#182
0!
#184
b110 +
b110 B
1!
#186
0!
#188
b101 B
b101 +
1!
#190
0!
#192
b100 +
b100 B
1!
#194
0!
#196
b11 B
b11 +
1!
#198
0!
#200
b10 +
b10 B
1!
#202
0!
#204
b1 B
b1 +
1!
#206
0!
#208
b0 +
b0 B
1!
#210
0!
#212
b1 >
bx1 4
bx1 @
b1 '
bx1 )
12
1?
1-
16
0.
08
b0 :
b0 <
1(
13
b110010 B
1%
b110010 +
1!
#214
0!
#216
b110001 +
b110001 B
1!
#218
0!
#220
b110000 B
b110000 +
1!
#222
0!
#224
b101111 +
b101111 B
1!
#226
0!
#228
b101110 B
b101110 +
1!
#230
0!
#232
b101101 +
b101101 B
1!
#234
0!
#236
b101100 B
b101100 +
1!
#238
0!
#240
b101011 +
b101011 B
1!
#242
0!
#244
b101010 B
b101010 +
1!
#246
0!
#248
b101001 +
b101001 B
1!
#250
0!
0"
#252
b101000 B
b101000 +
1!
#254
0!
#256
b100111 +
b100111 B
1!
#258
0!
#260
b100110 B
b100110 +
1!
#262
0!
#264
b100101 +
b100101 B
1!
#266
0!
#268
b100100 B
b100100 +
1!
#270
0!
#272
b100011 +
b100011 B
1!
#274
0!
#276
b100010 B
b100010 +
1!
#278
0!
#280
b100001 +
b100001 B
1!
#282
0!
#284
b100000 B
b100000 +
1!
#286
0!
#288
b11111 +
b11111 B
1!
#290
0!
#292
b11110 B
b11110 +
1!
#294
0!
#296
b11101 +
b11101 B
1!
#298
0!
#300
b11100 B
b11100 +
1!
#302
0!
#304
b11011 +
b11011 B
1!
#306
0!
#308
b11010 B
b11010 +
1!
#310
0!
#312
b11001 +
b11001 B
1!
#314
0!
#316
b11000 B
b11000 +
1!
#318
0!
#320
b10111 +
b10111 B
1!
#322
0!
#324
b10110 B
b10110 +
1!
#326
0!
#328
b10101 +
b10101 B
1!
#330
0!
#332
b10100 B
b10100 +
1!
#334
0!
#336
b10011 +
b10011 B
1!
#338
0!
#340
b10010 B
b10010 +
1!
#342
0!
#344
b10001 +
b10001 B
1!
#346
0!
#348
b10000 B
b10000 +
1!
#350
0!
#352
b1111 +
b1111 B
1!
#354
0!
#356
b1110 B
b1110 +
1!
#358
0!
#360
b1101 +
b1101 B
1!
#362
0!
#364
b1100 B
b1100 +
1!
#366
0!
#368
b1011 +
b1011 B
1!
#370
0!
#372
b1010 B
b1010 +
1!
#374
0!
#376
b1001 +
b1001 B
1!
#378
0!
#380
b1000 B
b1000 +
1!
#382
0!
#384
b111 +
b111 B
1!
#386
0!
#388
b110 B
b110 +
1!
#390
0!
#392
b101 +
b101 B
1!
#394
0!
#396
b100 B
b100 +
1!
#398
0!
#400
b11 +
b11 B
1!
1"
#402
0!
#404
b10 B
b10 +
1!
#406
0!
#408
b1 +
b1 B
1!
#410
0!
#412
b0 B
b0 +
1!
#414
0!
#416
0%
b110010 +
03
b110010 B
1!
#418
0!
#420
b110001 B
b110001 +
1!
#422
0!
#424
b110000 +
b110000 B
1!
#426
0!
#428
b101111 B
b101111 +
1!
#430
0!
#432
b101110 +
b101110 B
1!
#434
0!
#436
b101101 B
b101101 +
1!
#438
0!
#440
b101100 +
b101100 B
1!
#442
0!
#444
b101011 B
b101011 +
1!
#446
0!
#448
b101010 +
b101010 B
1!
#450
0!
#452
b101001 B
b101001 +
1!
#454
0!
#456
b101000 +
b101000 B
1!
#458
0!
#460
b100111 B
b100111 +
1!
#462
0!
#464
b100110 +
b100110 B
1!
#466
0!
#468
b100101 B
b100101 +
1!
#470
0!
#472
b100100 +
b100100 B
1!
#474
0!
#476
b100011 B
b100011 +
1!
#478
0!
#480
b100010 +
b100010 B
1!
#482
0!
#484
b100001 B
b100001 +
1!
#486
0!
#488
b100000 +
b100000 B
1!
#490
0!
#492
b11111 B
b11111 +
1!
#494
0!
#496
b11110 +
b11110 B
1!
#498
0!
#500
b11101 B
b11101 +
1!
#502
0!
#504
b11100 +
b11100 B
1!
#506
0!
#508
b11011 B
b11011 +
1!
#510
0!
#512
b11010 +
b11010 B
1!
#514
0!
#516
b11001 B
b11001 +
1!
#518
0!
#520
b11000 +
b11000 B
1!
#522
0!
#524
b10111 B
b10111 +
1!
#526
0!
#528
b10110 +
b10110 B
1!
#530
0!
#532
b10101 B
b10101 +
1!
#534
0!
#536
b10100 +
b10100 B
1!
#538
0!
#540
b10011 B
b10011 +
1!
#542
0!
#544
b10010 +
b10010 B
1!
#546
0!
#548
b10001 B
b10001 +
1!
#550
0!
0"
#552
b10000 +
b10000 B
1!
#554
0!
#556
b1111 B
b1111 +
1!
#558
0!
#560
b1110 +
b1110 B
1!
#562
0!
#564
b1101 B
b1101 +
1!
#566
0!
#568
b1100 +
b1100 B
1!
#570
0!
#572
b1011 B
b1011 +
1!
#574
0!
#576
b1010 +
b1010 B
1!
#578
0!
#580
b1001 B
b1001 +
1!
#582
0!
#584
b1000 +
b1000 B
1!
#586
0!
#588
b111 B
b111 +
1!
#590
0!
#592
b110 +
b110 B
1!
#594
0!
#596
b101 B
b101 +
1!
#598
0!
#600
b100 +
b100 B
1!
#602
0!
#604
b11 B
b11 +
1!
#606
0!
#608
b10 +
b10 B
1!
#610
0!
#612
b1 B
b1 +
1!
#614
0!
#616
b0 +
b0 B
1!
#618
0!
#620
bx1 ,
b10 >
bx10 4
bx10 @
b10 '
bx10 )
13
b110010 B
1%
b110010 +
1!
#622
0!
#624
b110001 +
b110001 B
1!
#626
0!
#628
b110000 B
b110000 +
1!
#630
0!
#632
b101111 +
b101111 B
1!
#634
0!
#636
b101110 B
b101110 +
1!
#638
0!
#640
b101101 +
b101101 B
1!
#642
0!
#644
b101100 B
b101100 +
1!
#646
0!
#648
b101011 +
b101011 B
1!
#650
0!
#652
b101010 B
b101010 +
1!
#654
0!
#656
b101001 +
b101001 B
1!
#658
0!
#660
b101000 B
b101000 +
1!
#662
0!
#664
b100111 +
b100111 B
1!
#666
0!
#668
b100110 B
b100110 +
1!
#670
0!
#672
b100101 +
b100101 B
1!
#674
0!
#676
b100100 B
b100100 +
1!
#678
0!
#680
b100011 +
b100011 B
1!
#682
0!
#684
b100010 B
b100010 +
1!
#686
0!
#688
b100001 +
b100001 B
1!
#690
0!
#692
b100000 B
b100000 +
1!
#694
0!
#696
b11111 +
b11111 B
1!
#698
0!
#700
b11110 B
b11110 +
1!
#702
0!
#704
b11101 +
b11101 B
1!
#706
0!
#708
b11100 B
b11100 +
1!
#710
0!
#712
b11011 +
b11011 B
1!
#714
0!
#716
b11010 B
b11010 +
1!
#718
0!
#720
b11001 +
b11001 B
1!
#722
0!
#724
b11000 B
b11000 +
1!
#726
0!
#728
b10111 +
b10111 B
1!
#730
0!
#732
b10110 B
b10110 +
1!
#734
0!
#736
b10101 +
b10101 B
1!
#738
0!
#740
b10100 B
b10100 +
1!
#742
0!
#744
b10011 +
b10011 B
1!
#746
0!
#748
b10010 B
b10010 +
1!
#750
0!
#752
b10001 +
b10001 B
1!
#754
0!
#756
b10000 B
b10000 +
1!
#758
0!
#760
b1111 +
b1111 B
1!
#762
0!
#764
b1110 B
b1110 +
1!
#766
0!
#768
b1101 +
b1101 B
1!
#770
0!
#772
b1100 B
b1100 +
1!
#774
0!
#776
b1011 +
b1011 B
1!
#778
0!
#780
b1010 B
b1010 +
1!
#782
0!
#784
b1001 +
b1001 B
1!
#786
0!
#788
b1000 B
b1000 +
1!
#790
0!
#792
b111 +
b111 B
1!
#794
0!
#796
b110 B
b110 +
1!
#798
0!
#800
b101 +
b101 B
1!
#802
0!
#804
b100 B
b100 +
1!
#806
0!
#808
b11 +
b11 B
1!
#810
0!
#812
b10 B
b10 +
1!
#814
0!
#816
b1 +
b1 B
1!
#818
0!
#820
b0 B
b0 +
1!
#822
0!
#824
0%
b110010 +
03
b110010 B
1!
#826
0!
#828
b110001 B
b110001 +
1!
#830
0!
#832
b110000 +
b110000 B
1!
#834
0!
#836
b101111 B
b101111 +
1!
#838
0!
#840
b101110 +
b101110 B
1!
#842
0!
#844
b101101 B
b101101 +
1!
#846
0!
#848
b101100 +
b101100 B
1!
#850
0!
1"
#852
b101011 B
b101011 +
1!
#854
0!
#856
b101010 +
b101010 B
1!
#858
0!
#860
b101001 B
b101001 +
1!
#862
0!
#864
b101000 +
b101000 B
1!
#866
0!
#868
b100111 B
b100111 +
1!
#870
0!
#872
b100110 +
b100110 B
1!
#874
0!
#876
b100101 B
b100101 +
1!
#878
0!
#880
b100100 +
b100100 B
1!
#882
0!
#884
b100011 B
b100011 +
1!
#886
0!
#888
b100010 +
b100010 B
1!
#890
0!
#892
b100001 B
b100001 +
1!
#894
0!
#896
b100000 +
b100000 B
1!
#898
0!
#900
b11111 B
b11111 +
1!
#902
0!
#904
b11110 +
b11110 B
1!
#906
0!
#908
b11101 B
b11101 +
1!
#910
0!
#912
b11100 +
b11100 B
1!
#914
0!
#916
b11011 B
b11011 +
1!
#918
0!
#920
b11010 +
b11010 B
1!
#922
0!
#924
b11001 B
b11001 +
1!
#926
0!
#928
b11000 +
b11000 B
1!
#930
0!
#932
b10111 B
b10111 +
1!
#934
0!
#936
b10110 +
b10110 B
1!
#938
0!
#940
b10101 B
b10101 +
1!
#942
0!
#944
b10100 +
b10100 B
1!
#946
0!
#948
b10011 B
b10011 +
1!
#950
0!
#952
b10010 +
b10010 B
1!
#954
0!
#956
b10001 B
b10001 +
1!
#958
0!
#960
b10000 +
b10000 B
1!
#962
0!
#964
b1111 B
b1111 +
1!
#966
0!
#968
b1110 +
b1110 B
1!
#970
0!
#972
b1101 B
b1101 +
1!
#974
0!
#976
b1100 +
b1100 B
1!
#978
0!
#980
b1011 B
b1011 +
1!
#982
0!
#984
b1010 +
b1010 B
1!
#986
0!
#988
b1001 B
b1001 +
1!
#990
0!
#992
b1000 +
b1000 B
1!
#994
0!
#996
b111 B
b111 +
1!
#998
0!
#1000
b110 +
b110 B
1!
0"
#1002
0!
#1004
b101 B
b101 +
1!
#1006
0!
#1008
b100 +
b100 B
1!
#1010
0!
#1012
b11 B
b11 +
1!
#1014
0!
#1016
b10 +
b10 B
1!
#1018
0!
#1020
b1 B
b1 +
1!
#1022
0!
#1024
b0 +
b0 B
1!
#1026
0!
#1028
b11 >
bx100 4
bx100 @
bx10 ,
b11 '
bx100 )
13
b110010 B
1%
b110010 +
1!
#1030
0!
#1032
b110001 +
b110001 B
1!
#1034
0!
#1036
b110000 B
b110000 +
1!
#1038
0!
#1040
b101111 +
b101111 B
1!
#1042
0!
#1044
b101110 B
b101110 +
1!
#1046
0!
#1048
b101101 +
b101101 B
1!
#1050
0!
#1052
b101100 B
b101100 +
1!
#1054
0!
#1056
b101011 +
b101011 B
1!
#1058
0!
#1060
b101010 B
b101010 +
1!
#1062
0!
#1064
b101001 +
b101001 B
1!
#1066
0!
#1068
b101000 B
b101000 +
1!
#1070
0!
#1072
b100111 +
b100111 B
1!
#1074
0!
#1076
b100110 B
b100110 +
1!
#1078
0!
#1080
b100101 +
b100101 B
1!
#1082
0!
#1084
b100100 B
b100100 +
1!
#1086
0!
#1088
b100011 +
b100011 B
1!
#1090
0!
#1092
b100010 B
b100010 +
1!
#1094
0!
#1096
b100001 +
b100001 B
1!
#1098
0!
#1100
b100000 B
b100000 +
1!
#1102
0!
#1104
b11111 +
b11111 B
1!
#1106
0!
#1108
b11110 B
b11110 +
1!
#1110
0!
#1112
b11101 +
b11101 B
1!
#1114
0!
#1116
b11100 B
b11100 +
1!
#1118
0!
#1120
b11011 +
b11011 B
1!
#1122
0!
#1124
b11010 B
b11010 +
1!
#1126
0!
#1128
b11001 +
b11001 B
1!
#1130
0!
#1132
b11000 B
b11000 +
1!
#1134
0!
#1136
b10111 +
b10111 B
1!
#1138
0!
#1140
b10110 B
b10110 +
1!
#1142
0!
#1144
b10101 +
b10101 B
1!
#1146
0!
#1148
b10100 B
b10100 +
1!
#1150
0!
1"
#1152
b10011 +
b10011 B
1!
#1154
0!
#1156
b10010 B
b10010 +
1!
#1158
0!
#1160
b10001 +
b10001 B
1!
#1162
0!
#1164
b10000 B
b10000 +
1!
#1166
0!
#1168
b1111 +
b1111 B
1!
#1170
0!
#1172
b1110 B
b1110 +
1!
#1174
0!
#1176
b1101 +
b1101 B
1!
#1178
0!
#1180
b1100 B
b1100 +
1!
#1182
0!
#1184
b1011 +
b1011 B
1!
#1186
0!
#1188
b1010 B
b1010 +
1!
#1190
0!
#1192
b1001 +
b1001 B
1!
#1194
0!
#1196
b1000 B
b1000 +
1!
#1198
0!
#1200
b111 +
b111 B
1!
#1202
0!
#1204
b110 B
b110 +
1!
#1206
0!
#1208
b101 +
b101 B
1!
#1210
0!
#1212
b100 B
b100 +
1!
#1214
0!
#1216
b11 +
b11 B
1!
#1218
0!
#1220
b10 B
b10 +
1!
#1222
0!
#1224
b1 +
b1 B
1!
#1226
0!
#1228
b0 B
b0 +
1!
#1230
0!
#1232
0%
b110010 +
03
b110010 B
1!
#1234
0!
#1236
b110001 B
b110001 +
1!
#1238
0!
#1240
b110000 +
b110000 B
1!
#1242
0!
#1244
b101111 B
b101111 +
1!
#1246
0!
#1248
b101110 +
b101110 B
1!
#1250
0!
#1252
b101101 B
b101101 +
1!
#1254
0!
#1256
b101100 +
b101100 B
1!
#1258
0!
#1260
b101011 B
b101011 +
1!
#1262
0!
#1264
b101010 +
b101010 B
1!
#1266
0!
#1268
b101001 B
b101001 +
1!
#1270
0!
#1272
b101000 +
b101000 B
1!
#1274
0!
#1276
b100111 B
b100111 +
1!
#1278
0!
#1280
b100110 +
b100110 B
1!
#1282
0!
#1284
b100101 B
b100101 +
1!
#1286
0!
#1288
b100100 +
b100100 B
1!
#1290
0!
#1292
b100011 B
b100011 +
1!
#1294
0!
#1296
b100010 +
b100010 B
1!
#1298
0!
#1300
b100001 B
b100001 +
1!
#1302
0!
#1304
b100000 +
b100000 B
1!
#1306
0!
#1308
b11111 B
b11111 +
1!
#1310
0!
#1312
b11110 +
b11110 B
1!
#1314
0!
#1316
b11101 B
b11101 +
1!
#1318
0!
#1320
b11100 +
b11100 B
1!
#1322
0!
#1324
b11011 B
b11011 +
1!
#1326
0!
#1328
b11010 +
b11010 B
1!
#1330
0!
#1332
b11001 B
b11001 +
1!
#1334
0!
#1336
b11000 +
b11000 B
1!
#1338
0!
#1340
b10111 B
b10111 +
1!
#1342
0!
#1344
b10110 +
b10110 B
1!
#1346
0!
#1348
b10101 B
b10101 +
1!
#1350
0!
#1352
b10100 +
b10100 B
1!
#1354
0!
#1356
b10011 B
b10011 +
1!
#1358
0!
#1360
b10010 +
b10010 B
1!
#1362
0!
#1364
b10001 B
b10001 +
1!
#1366
0!
#1368
b10000 +
b10000 B
1!
#1370
0!
#1372
b1111 B
b1111 +
1!
#1374
0!
#1376
b1110 +
b1110 B
1!
#1378
0!
#1380
b1101 B
b1101 +
1!
#1382
0!
#1384
b1100 +
b1100 B
1!
#1386
0!
#1388
b1011 B
b1011 +
1!
#1390
0!
#1392
b1010 +
b1010 B
1!
#1394
0!
#1396
b1001 B
b1001 +
1!
#1398
0!
#1400
b1000 +
b1000 B
1!
0"
#1402
0!
#1404
b111 B
b111 +
1!
#1406
0!
#1408
b110 +
b110 B
1!
#1410
0!
#1412
b101 B
b101 +
1!
#1414
0!
#1416
b100 +
b100 B
1!
#1418
0!
#1420
b11 B
b11 +
1!
#1422
0!
#1424
b10 +
b10 B
1!
#1426
0!
#1428
b1 B
b1 +
1!
#1430
0!
#1432
b0 +
b0 B
1!
#1434
0!
#1436
bx100 ,
b100 >
bx1000 4
bx1000 @
b100 '
bx1000 )
13
b110010 B
1%
b110010 +
1!
#1438
0!
#1440
b110001 +
b110001 B
1!
#1442
0!
#1444
b110000 B
b110000 +
1!
#1446
0!
#1448
b101111 +
b101111 B
1!
#1450
0!
#1452
b101110 B
b101110 +
1!
#1454
0!
#1456
b101101 +
b101101 B
1!
#1458
0!
#1460
b101100 B
b101100 +
1!
#1462
0!
#1464
b101011 +
b101011 B
1!
#1466
0!
#1468
b101010 B
b101010 +
1!
#1470
0!
#1472
b101001 +
b101001 B
1!
#1474
0!
#1476
b101000 B
b101000 +
1!
#1478
0!
#1480
b100111 +
b100111 B
1!
#1482
0!
#1484
b100110 B
b100110 +
1!
#1486
0!
#1488
b100101 +
b100101 B
1!
#1490
0!
#1492
b100100 B
b100100 +
1!
#1494
0!
#1496
b100011 +
b100011 B
1!
#1498
0!
#1500
b100010 B
b100010 +
1!
#1502
0!
#1504
b100001 +
b100001 B
1!
#1506
0!
#1508
b100000 B
b100000 +
1!
#1510
0!
#1512
b11111 +
b11111 B
1!
#1514
0!
#1516
b11110 B
b11110 +
1!
#1518
0!
#1520
b11101 +
b11101 B
1!
#1522
0!
#1524
b11100 B
b11100 +
1!
#1526
0!
#1528
b11011 +
b11011 B
1!
#1530
0!
#1532
b11010 B
b11010 +
1!
#1534
0!
#1536
b11001 +
b11001 B
1!
#1538
0!
#1540
b11000 B
b11000 +
1!
#1542
0!
#1544
b10111 +
b10111 B
1!
#1546
0!
#1548
b10110 B
b10110 +
1!
#1550
0!
1"
#1552
b10101 +
b10101 B
1!
#1554
0!
#1556
b10100 B
b10100 +
1!
#1558
0!
#1560
b10011 +
b10011 B
1!
#1562
0!
#1564
b10010 B
b10010 +
1!
#1566
0!
#1568
b10001 +
b10001 B
1!
#1570
0!
#1572
b10000 B
b10000 +
1!
#1574
0!
#1576
b1111 +
b1111 B
1!
#1578
0!
#1580
b1110 B
b1110 +
1!
#1582
0!
#1584
b1101 +
b1101 B
1!
#1586
0!
#1588
b1100 B
b1100 +
1!
#1590
0!
#1592
b1011 +
b1011 B
1!
#1594
0!
#1596
b1010 B
b1010 +
1!
#1598
0!
#1600
b1001 +
b1001 B
1!
#1602
0!
#1604
b1000 B
b1000 +
1!
#1606
0!
#1608
b111 +
b111 B
1!
#1610
0!
#1612
b110 B
b110 +
1!
#1614
0!
#1616
b101 +
b101 B
1!
#1618
0!
#1620
b100 B
b100 +
1!
#1622
0!
#1624
b11 +
b11 B
1!
#1626
0!
#1628
b10 B
b10 +
1!
#1630
0!
#1632
b1 +
b1 B
1!
#1634
0!
#1636
b0 B
b0 +
1!
#1638
0!
#1640
0%
b110010 +
03
b110010 B
1!
#1642
0!
#1644
b110001 B
b110001 +
1!
#1646
0!
#1648
b110000 +
b110000 B
1!
#1650
0!
#1652
b101111 B
b101111 +
1!
#1654
0!
#1656
b101110 +
b101110 B
1!
#1658
0!
#1660
b101101 B
b101101 +
1!
#1662
0!
#1664
b101100 +
b101100 B
1!
#1666
0!
#1668
b101011 B
b101011 +
1!
#1670
0!
#1672
b101010 +
b101010 B
1!
#1674
0!
#1676
b101001 B
b101001 +
1!
#1678
0!
#1680
b101000 +
b101000 B
1!
#1682
0!
#1684
b100111 B
b100111 +
1!
#1686
0!
#1688
b100110 +
b100110 B
1!
#1690
0!
#1692
b100101 B
b100101 +
1!
#1694
0!
#1696
b100100 +
b100100 B
1!
#1698
0!
#1700
b100011 B
b100011 +
1!
0"
#1702
0!
#1704
b100010 +
b100010 B
1!
#1706
0!
#1708
b100001 B
b100001 +
1!
#1710
0!
#1712
b100000 +
b100000 B
1!
#1714
0!
#1716
b11111 B
b11111 +
1!
#1718
0!
#1720
b11110 +
b11110 B
1!
#1722
0!
#1724
b11101 B
b11101 +
1!
#1726
0!
#1728
b11100 +
b11100 B
1!
#1730
0!
#1732
b11011 B
b11011 +
1!
#1734
0!
#1736
b11010 +
b11010 B
1!
#1738
0!
#1740
b11001 B
b11001 +
1!
#1742
0!
#1744
b11000 +
b11000 B
1!
#1746
0!
#1748
b10111 B
b10111 +
1!
#1750
0!
#1752
b10110 +
b10110 B
1!
#1754
0!
#1756
b10101 B
b10101 +
1!
#1758
0!
#1760
b10100 +
b10100 B
1!
#1762
0!
#1764
b10011 B
b10011 +
1!
#1766
0!
#1768
b10010 +
b10010 B
1!
#1770
0!
#1772
b10001 B
b10001 +
1!
#1774
0!
#1776
b10000 +
b10000 B
1!
#1778
0!
