HW/RTL/06PCM-AUDIO-MICROFONO/Version_01/02 verilog/Prueba fifo/fifo.v
module fifo # (parameter abits = 4, dbits = 8)(
    input  reset, clock,
    input  rd, wr,
    input  [dbits-1:0] din,
    output [dbits-1:0] dout,
    output empty,
    output full,
    output reg ledres
    );



wire db_wr;
wire db_rd;
reg dffw1, dffr1;
reg [dbits-1:0] out;
initial ledres = 0;
reg [1:0] count;
reg [1:0] count1;
//always @ (posedge clock) dffw1 <= ~wr; 
//always @ (posedge clock) dffw2 <= rd;
 
assign db_wr = dffw1; //monostable multivibrator to detect only one pulse of the button

//always @ (posedge clock) dffr1 <= rd;
//always @ (posedge clock) dffr2 <= dffr1;
 
assign db_rd = dffr1; //monostable multivibrator to detect only one pulse of the button
 
 
reg [dbits-1:0] regarray[2**abits-1:0]; //number of words in fifo = 2^(number of address bits)
reg [abits-1:0] wr_reg, wr_next, wr_succ; //points to the register that needs to be written to
reg [abits-1:0] rd_reg, rd_next, rd_succ; //points to the register that needs to be read from
reg full_reg, empty_reg, full_next, empty_next;

assign wr_en = db_wr & ~full; //only write if write signal is high and fifo is not full

always @ (posedge clock)
begin

	if(wr && ~rd)
	begin
		if(count)
		begin
		//dffr1<=0;
		dffw1<=0;
		count<=count+1;
		end		
		else 
		begin	
		//dffr1<=0;	
		dffw1<=1;
		count<=0;
		end
	end
	else dffw1<=0;
   
 
end
always @ (posedge clock)
begin

	if(rd && ~wr)
	begin
		if(count1)
		begin
		//dffw1<=0;
		dffr1<=0;
		count1<=count1+1;
		end		
		else 
		begin
		//dffw1<=0;		
		dffr1<=1;
		count1<=0;
		end
	end
	else dffr1<=0;
   
 
end

//always block for write operation
always @ (posedge clock)
 begin
  if(wr_en)
   regarray[wr_reg] <= din;  //at wr_reg location of regarray store what is given at din
 
 end
  
//always block for read operation
always @ (posedge clock)
 begin
  if(db_rd)
   out <= regarray[rd_reg];
 end

always @ (posedge clock or posedge reset)
 begin
  if (reset)
   begin
   
   wr_reg <= 0;
   rd_reg <= 0;
   full_reg <= 1'b0;
   empty_reg <= 1'b1;
   ledres=0;
   end
   
  else
   begin
   wr_reg <= wr_next; //created the next registers to avoid the error of mixing blocking and non blocking assignment to the same signal
   rd_reg <= rd_next;
   full_reg <= full_next;
   empty_reg <= empty_next;
   ledres=1;
   end
 end
  
always @(clock)
 begin
  wr_succ = wr_reg + 1; //assigned to new value as wr_next cannot be tested for in same always block
  rd_succ = rd_reg + 1; //assigned to new value as rd_next cannot be tested for in same always block
  wr_next = wr_reg;  //defaults state stays the same
  rd_next = rd_reg;  //defaults state stays the same
  full_next = full_reg;  //defaults state stays the same
  empty_next = empty_reg;  //defaults state stays the same
   
   case({db_wr,db_rd})
    //2'b00: do nothing LOL..
     
    2'b01: //read
     begin
      if(~empty) //if fifo is not empty continue
       begin
        rd_next = rd_succ;
        full_next = 1'b0;
       if(rd_succ == wr_reg) //all data has been read
         empty_next = 1'b1;  //its empty again
       end
     end
2'b10: //write
     begin
       
      if(~full) //if fifo is not full continue
       begin
        wr_next = wr_succ;
        empty_next = 1'b0;
        if(wr_succ == (2**abits-1)) //all registers have been written to
         full_next = 1'b1;   //its full now
       end
     end
      
    2'b11: //read and write
     begin
      wr_next = wr_succ;
      rd_next = rd_succ;
     end
     //no empty or full flag will be checked for or asserted in this state since data is being written to and read from together it can  not get full in this state.
    endcase
    
 
 end
 
assign full = full_reg;
assign empty = empty_reg;
assign dout = out;
endmodule

HW/RTL/06PCM-AUDIO-MICROFONO/Version_01/02 verilog/Prueba fifo/fifo_TB.v
module fifo_TB;

reg clk;
reg reset;
reg rd;
reg wr;
reg dataint;


fifo uttf(.rd(rd),.wr(wr),.din(dataint),.clock(clk),.reset(reset));


always
begin
clk =1'b1;
#10;
clk=1'b0;
#10;
end

initial
begin
reset = 1'b1;
#4 reset = 1'b0;
end

initial
begin
wr = 1'b1;
#3430;
wr=1'b0;
#3430;
wr = 1'b1;
#3430;
wr=1'b0;
#3430;
wr = 1'b1;
#3430;
wr=1'b0;
#3430;
wr = 1'b1;
#3430;
wr=1'b0;
#3430;
wr = 1'b1;
#3430;
wr=1'b0;
#3430;
wr = 1'b1;
#3430;
wr=1'b0;
#3430;
wr = 1'b1;
#3430;
wr=1'b0;
#3430;
wr = 1'b1;
#3430;
wr=1'b0;
#3430;
wr = 1'b1;
#3430;
wr=1'b0;
#3430;
wr = 1'b1;
#3430;
wr=1'b0;
#3430;
wr = 1'b1;
#3430;
wr=1'b0;
end
initial
begin

rd=1'b0;
#64300;
rd=1'b1;
#3430;
rd=1'b0;
#3430;
rd=1'b1;
#3430;
rd=1'b0;
#3430;
rd=1'b1;
#3430;
rd=1'b0;
#3430;
rd=1'b1;
#3430;
rd=1'b0;
#3430;
rd=1'b1;
#3430;
rd=1'b0;
#3430;
rd=1'b1;
#3430;
rd=1'b0;
#3430;
rd=1'b1;
#3430;
rd=1'b0;
#3430;
rd=1'b1;
#3430;
rd=1'b0;
#3430;
rd=1'b1;
#3430;
rd=1'b0;
#3430;
rd=1'b1;
#3430;
rd=1'b0;
#3430;
rd=1'b1;
#3430;
rd=1'b0;
#3430;
rd=1'b1;
#3430;
rd=1'b0;
#3430;
rd=1'b1;
#3430;
rd=1'b0;
#3430;
rd=1'b1;
#3430;
rd=1'b0;
#3430;
rd=1'b1;
#3430;
rd=1'b0;
#3430;
rd=1'b1;
#3430;
rd=1'b0;
end


initial begin

#3430 dataint = 1'b0;
#3430 dataint = 1'b1;
#3430 dataint = 1'b0;
#3430 dataint = 1'b1;
#3430 dataint = 1'b0;
#3430 dataint = 1'b1;
#3430 dataint = 1'b0;
#3430 dataint = 1'b1;
#3430 dataint = 1'b0;

#3430 dataint = 1'b0;
#3430 dataint = 1'b1;
#3430 dataint = 1'b0;
#3430 dataint = 1'b1;
#3430 dataint = 1'b0;
#3430 dataint = 1'b1;
#3430 dataint = 1'b0;
#3430 dataint = 1'b1;
#3430 dataint = 1'b0;

#3430 dataint = 1'b0;
#3430 dataint = 1'b1;
#3430 dataint = 1'b0;
#3430 dataint = 1'b1;
#3430 dataint = 1'b0;
#3430 dataint = 1'b1;
#3430 dataint = 1'b0;
#3430 dataint = 1'b1;
#3430 dataint = 1'b0;
end
	
initial begin: TEST_CASE
     $dumpfile("fifo_TB.vcd");
     $dumpvars(-1, uttf);

     #(1000000) $finish;
   end

endmodule //

HW/RTL/06PCM-AUDIO-MICROFONO/Version_01/02 verilog/Prueba fifo/simulation/fifo_TB.vcd
$date
	Sun Nov 26 21:04:18 2017
$end
$version
	Icarus Verilog
$end
$timescale
	1s
$end
$scope module fifo_TB $end
$scope module uttf $end
$var wire 1 ! clock $end
$var wire 1 " db_rd $end
$var wire 8 # din [7:0] $end
$var wire 8 $ dout [7:0] $end
$var wire 1 % empty $end
$var wire 1 & rd $end
$var wire 1 ' reset $end
$var wire 1 ( wr $end
$var wire 1 ) wr_en $end
$var wire 1 * full $end
$var wire 1 + db_wr $end
$var reg 2 , count [1:0] $end
$var reg 2 - count1 [1:0] $end
$var reg 1 . dffr1 $end
$var reg 1 + dffw1 $end
$var reg 1 / empty_next $end
$var reg 1 0 empty_reg $end
$var reg 1 1 full_next $end
$var reg 1 * full_reg $end
$var reg 1 2 ledres $end
$var reg 8 3 out [7:0] $end
$var reg 4 4 rd_next [3:0] $end
$var reg 4 5 rd_reg [3:0] $end
$var reg 4 6 rd_succ [3:0] $end
$var reg 4 7 wr_next [3:0] $end
$var reg 4 8 wr_reg [3:0] $end
$var reg 4 9 wr_succ [3:0] $end
$upscope $end
$upscope $end
$enddefinitions $end
#0
$dumpvars
bx 9
b0 8
bx 7
bx 6
b0 5
bx 4
bx 3
02
x1
10
x/
0.
bx -
bx ,
0+
0*
0)
0(
1'
0&
1%
bx $
bx #
0"
1!
$end
#4
0'
#10
1/
01
b0 4
b0 7
b1 6
b1 9
0!
#20
12
1!
#30
0!
#40
1!
#50
0!
#60
1!
#70
0!
#80
1!
#90
0!
#100
1!
#110
0!
#120
1!
#130
0!
#140
1!
#150
0!
#160
1!
#170
0!
#180
1!
#190
0!
#200
1!
#210
0!
#220
1!
#230
0!
#240
1!
#250
0!
#260
1!
#270
0!
#280
1!
#290
0!
#300
1!
#310
0!
#320
1!
#330
0!
#340
1!
#350
0!
#360
1!
#370
0!
#380
1!
#390
0!
#400
1!
#410
0!
#420
1!
#430
0!
#440
1!
#450
0!
#460
1!
#470
0!
#480
1!
#490
0!
#500
1!
#510
0!
#520
1!
#530
0!
#540
1!
#550
0!
#560
1!
#570
0!
#580
1!
#590
0!
#600
1!
#610
0!
#620
1!
#630
0!
#640
1!
#650
0!
#660
1!
#670
0!
#680
1!
#690
0!
#700
1!
#710
0!
#720
1!
#730
0!
#740
1!
#750
0!
#760
1!
#770
0!
#780
1!
#790
0!
#800
1!
#810
0!
#820
1!
#830
0!
#840
1!
#850
0!
#860
1!
#870
0!
#880
1!
#890
0!
#900
1!
#910
0!
#920
1!
#930
0!
#940
1!
#950
0!
#960
1!
#970
0!
#980
1!
#990
0!
#1000
1!
#1010
0!
#1020
1!
#1030
0!
#1040
1!
#1050
0!
#1060
1!
#1070
0!
#1080
1!
#1090
0!
#1100
1!
#1110
0!
#1120
1!
#1130
0!
#1140
1!
#1150
0!
#1160
1!
#1170
0!
#1180
1!
#1190
0!
#1200
1!
#1210
0!
#1220
1!
#1230
0!
#1240
1!
#1250
0!
#1260
1!
#1270
0!
#1280
1!
#1290
0!
#1300
1!
#1310
0!
#1320
1!
#1330
0!
#1340
1!
#1350
0!
#1360
1!
#1370
0!
#1380
1!
#1390
0!
#1400
1!
#1410
0!
#1420
1!
#1430
0!
#1440
1!
#1450
0!
#1460
1!
#1470
0!
#1480
1!
#1490
0!
#1500
1!
#1510
0!
#1520
1!
#1530
0!
#1540
1!
#1550
0!
#1560
1!
#1570
0!
#1580
1!
#1590
0!
#1600
1!
#1610
0!
#1620
1!
#1630
0!
#1640
1!
#1650
0!
#1660
1!
#1670
0!
#1680
1!
#1690
0!
#1700
1!
#1710
0!
#1720
1!
#1730
0!
#1740
1!
#1750
0!
#1760
1!
#1770
0!
#1780
1!
#1790
0!
#1800
1!
#1810
0!
#1820
1!
#1830
0!
#1840
1!
#1850
0!
#1860
1!
#1870
0!
#1880
1!
#1890
0!
#1900
1!
#1910
0!
#1920
1!
#1930
0!
#1940
1!
#1950
0!
#1960
1!
#1970
0!
#1980
1!
#1990
0!
#2000
1!
#2010
0!
#2020
1!
#2030
0!
#2040
1!
#2050
0!
#2060
1!
#2070
0!
#2080
1!
#2090
0!
#2100
1!
#2110
0!
#2120
1!
#2130
0!
#2140
1!
#2150
0!
#2160
1!
#2170
0!
#2180
1!
#2190
0!
#2200
1!
#2210
0!
#2220
1!
#2230
0!
#2240
1!
#2250
0!
#2260
1!
#2270
0!
#2280
1!
#2290
0!
#2300
1!
#2310
0!
#2320
1!
#2330
0!
#2340
1!
#2350
0!
#2360
1!
#2370
0!
#2380
1!
#2390
0!
#2400
1!
#2410
0!
#2420
1!
#2430
0!
#2440
1!
#2450
0!
#2460
1!
#2470
0!
#2480
1!
#2490
0!
#2500
1!
#2510
0!
#2520
1!
#2530
0!
#2540
1!
#2550
0!
#2560
1!
#2570
0!
#2580
1!
#2590
0!
#2600
1!
#2610
0!
#2620
1!
#2630
0!
#2640
1!
#2650
0!
#2660
1!
#2670
0!
#2680
1!
#2690
0!
#2700
1!
#2710
0!
#2720
1!
#2730
0!
#2740
1!
#2750
0!
#2760
1!
#2770
0!
#2780
1!
#2790
0!
#2800
1!
#2810
0!
#2820
1!
#2830
0!
#2840
1!
#2850
0!
#2860
1!
#2870
0!
#2880
1!
#2890
0!
#2900
1!
#2910
0!
#2920
1!
#2930
0!
#2940
1!
#2950
0!
#2960
1!
#2970
0!
#2980
1!
#2990
0!
#3000
1!
#3010
0!
#3020
1!
#3030
0!
#3040
1!
#3050
0!
#3060
1!
#3070
0!
#3080
1!
#3090
0!
#3100
1!
#3110
0!
#3120
1!
#3130
0!
#3140
1!
#3150
0!
#3160
1!
#3170
0!
#3180
1!
#3190
0!
#3200
1!
#3210
0!
#3220
1!
#3230
0!
#3240
1!
#3250
0!
#3260
1!
#3270
0!
#3280
1!
#3290
0!
#3300
1!
#3310
0!
#3320
1!
#3330
0!
#3340
1!
#3350
0!
#3360
1!
#3370
0!
#3380
1!
#3390
0!
#3400
1!
#3410
0!
#3420
1!
#3430
0!
b1 #
1(
#3440
1)
b0 ,
1+
1!
#3450
0/
b1 7
0!
#3460
0%
00
b1 8
0/
b1 7
1!
#3464
b0 #
#3470
b10 7
b10 9
0!
#3480
b10 8
b10 7
1!
#3490
b11 7
b11 9
0!
#3498
b1010 #
#3500
b11 8
b11 7
1!
#3510
b100 7
b100 9
0!
#3520
b100 8
b100 7
1!
#3530
b101 7
b101 9
0!
#3532
b11 #
#3540
b101 8
b101 7
1!
#3550
b110 7
b110 9
0!
#3560
b110 8
b110 7
1!
#3570
b111 7
b111 9
0!
#3580
b111 8
b111 7
1!
#3590
b1000 7
b1000 9
0!
#3600
b1000 8
b1000 7
1!
#3610
b1001 7
b1001 9
0!
#3620
b1001 8
b1001 7
1!
#3630
b1010 7
b1010 9
0!
#3640
b1010 8
b1010 7
1!
#3650
b1011 7
b1011 9
0!
#3660
b1011 8
b1011 7
1!
#3670
b1100 7
b1100 9
0!
#3680
b1100 8
b1100 7
1!
#3690
b1101 7
b1101 9
0!
#3700
b1101 8
b1101 7
1!
#3710
b1110 7
b1110 9
0!
#3720
b1110 8
b1110 7
1!
#3730
11
b1111 7
b1111 9
0!
#3740
0)
1*
b1111 8
11
b1111 7
1!
#3750
b0 9
0!
