HW/RTL/06PCM-AUDIO-MICROFONO/Version_01/02 verilog/Prueba fifo/fifo.v
module fifo # (parameter abits = 3, dbits = 8)(
    input  reset, clock,
    input  rd, wr,
    input  [dbits-1:0] din,
    output [dbits-1:0] dout,
    output empty,
    output full,
    output reg ledres
    );



wire db_wr, db_rd;
reg dffw1, dffw2, dffr1, dffr2;
reg [dbits-1:0] out;
initial ledres = 0;

always @ (posedge clock) dffw1 <= wr; 
always @ (posedge clock) dffw2 <= dffw1;
 
assign db_wr = ~dffw1 & dffw2; //monostable multivibrator to detect only one pulse of the button
 
always @ (posedge clock) dffr1 <= rd;
always @ (posedge clock) dffr2 <= dffr1;
 
assign db_rd = ~dffr1 & dffr2; //monostable multivibrator to detect only one pulse of the button
 
 
reg [dbits-1:0] regarray[2**abits-1:0]; //number of words in fifo = 2^(number of address bits)
reg [abits-1:0] wr_reg, wr_next, wr_succ; //points to the register that needs to be written to
reg [abits-1:0] rd_reg, rd_next, rd_succ; //points to the register that needs to be read from
reg full_reg, empty_reg, full_next, empty_next;
 
assign wr_en = db_wr & ~full; //only write if write signal is high and fifo is not full
 
//always block for write operation
always @ (posedge clock)
 begin
  if(wr_en)
   regarray[wr_reg] <= din;  //at wr_reg location of regarray store what is given at din
 
 end
  
//always block for read operation
always @ (posedge clock)
 begin
  if(db_rd)
   out <= regarray[rd_reg];
 end

always @ (posedge clock or posedge reset)
 begin
  if (reset)
   begin
   wr_reg <= 0;
   rd_reg <= 0;
   full_reg <= 1'b0;
   empty_reg <= 1'b1;
   end
   
  else
   begin
   wr_reg <= wr_next; //created the next registers to avoid the error of mixing blocking and non blocking assignment to the same signal
   rd_reg <= rd_next;
   full_reg <= full_next;
   empty_reg <= empty_next;
   ledres=1;
   end
 end
  
always @(*)
 begin
  wr_succ = wr_reg + 1; //assigned to new value as wr_next cannot be tested for in same always block
  rd_succ = rd_reg + 1; //assigned to new value as rd_next cannot be tested for in same always block
  wr_next = wr_reg;  //defaults state stays the same
  rd_next = rd_reg;  //defaults state stays the same
  full_next = full_reg;  //defaults state stays the same
  empty_next = empty_reg;  //defaults state stays the same
   
   case({db_wr,db_rd})
    //2'b00: do nothing LOL..
     
    2'b01: //read
     begin
      if(~empty) //if fifo is not empty continue
       begin
        rd_next = rd_succ;
        full_next = 1'b0;
       if(rd_succ == wr_reg) //all data has been read
         empty_next = 1'b1;  //its empty again
       end
     end
2'b10: //write
     begin
       
      if(~full) //if fifo is not full continue
       begin
        wr_next = wr_succ;
        empty_next = 1'b0;
        if(wr_succ == (2**abits-1)) //all registers have been written to
         full_next = 1'b1;   //its full now
       end
     end
      
    2'b11: //read and write
     begin
      wr_next = wr_succ;
      rd_next = rd_succ;
     end
     //no empty or full flag will be checked for or asserted in this state since data is being written to and read from together it can  not get full in this state.
    endcase
    
 
 end
 
assign full = full_reg;
assign empty = empty_reg;
assign dout = out;
endmodule

HW/RTL/06PCM-AUDIO-MICROFONO/Version_01/02 verilog/Prueba fifo/fifo_TB.v
module fifo_TB;

reg clk;
reg reset;
reg rd;
reg wr;
reg dataint;


fifo uttf(.rd(rd),.wr(wr),.din(dataint),.clock(clk),.reset(reset));


always
begin
clk =1'b1;
#10;
clk=1'b0;
#10;
end

initial
begin
reset = 1'b1;
#4 reset = 1'b0;
end

initial
begin
wr = 1'b1;
#3430;
wr=1'b0;
#3430;
wr = 1'b1;
#3430;
wr=1'b0;
#3430;
wr = 1'b1;
#3430;
wr=1'b0;
#3430;
wr = 1'b1;
#3430;
wr=1'b0;
#3430;
wr = 1'b1;
#3430;
wr=1'b0;
#3430;
wr = 1'b1;
#3430;
wr=1'b0;
#3430;
wr = 1'b1;
#3430;
wr=1'b0;
#3430;
wr = 1'b1;
#3430;
wr=1'b0;
#3430;
wr = 1'b1;
#3430;
wr=1'b0;
#3430;
wr = 1'b1;
#3430;
wr=1'b0;
#3430;
wr = 1'b1;
#3430;
wr=1'b0;
end
initial
begin

rd=1'b0;
#64300;
rd=1'b1;
#3430;
rd=1'b0;
#3430;
rd=1'b1;
#3430;
rd=1'b0;
#3430;
rd=1'b1;
#3430;
rd=1'b0;
#3430;
rd=1'b1;
#3430;
rd=1'b0;
#3430;
rd=1'b1;
#3430;
rd=1'b0;
#3430;
rd=1'b1;
#3430;
rd=1'b0;
#3430;
rd=1'b1;
#3430;
rd=1'b0;
#3430;
rd=1'b1;
#3430;
rd=1'b0;
#3430;
rd=1'b1;
#3430;
rd=1'b0;
#3430;
rd=1'b1;
#3430;
rd=1'b0;
#3430;
rd=1'b1;
#3430;
rd=1'b0;
#3430;
rd=1'b1;
#3430;
rd=1'b0;
#3430;
rd=1'b1;
#3430;
rd=1'b0;
#3430;
rd=1'b1;
#3430;
rd=1'b0;
#3430;
rd=1'b1;
#3430;
rd=1'b0;
#3430;
rd=1'b1;
#3430;
rd=1'b0;
end


initial begin

#3430 dataint = 1'b0;
#3430 dataint = 1'b1;
#3430 dataint = 1'b0;
#3430 dataint = 1'b1;
#3430 dataint = 1'b0;
#3430 dataint = 1'b1;
#3430 dataint = 1'b0;
#3430 dataint = 1'b1;
#3430 dataint = 1'b0;

#3430 dataint = 1'b0;
#3430 dataint = 1'b1;
#3430 dataint = 1'b0;
#3430 dataint = 1'b1;
#3430 dataint = 1'b0;
#3430 dataint = 1'b1;
#3430 dataint = 1'b0;
#3430 dataint = 1'b1;
#3430 dataint = 1'b0;

#3430 dataint = 1'b0;
#3430 dataint = 1'b1;
#3430 dataint = 1'b0;
#3430 dataint = 1'b1;
#3430 dataint = 1'b0;
#3430 dataint = 1'b1;
#3430 dataint = 1'b0;
#3430 dataint = 1'b1;
#3430 dataint = 1'b0;
end
	
initial begin: TEST_CASE
     $dumpfile("fifo_TB.vcd");
     $dumpvars(-1, uttf);

     #(1000000) $finish;
   end

endmodule //

HW/RTL/06PCM-AUDIO-MICROFONO/Version_01/02 verilog/Prueba fifo/simulation/fifo_TB.vcd
$date
	Wed Nov 22 02:04:06 2017
$end
$version
	Icarus Verilog
$end
$timescale
	1s
$end
$scope module fifo_TB $end
$scope module uttf $end
$var wire 1 ! clock $end
$var wire 1 " db_rd $end
$var wire 1 # db_wr $end
$var wire 7 $ din [6:0] $end
$var wire 7 % dout [6:0] $end
$var wire 1 & empty $end
$var wire 1 ' rd $end
$var wire 1 ( reset $end
$var wire 1 ) wr $end
$var wire 1 * wr_en $end
$var wire 1 + full $end
$var reg 1 , dffr1 $end
$var reg 1 - dffr2 $end
$var reg 1 . dffw1 $end
$var reg 1 / dffw2 $end
$var reg 1 0 empty_next $end
$var reg 1 1 empty_reg $end
$var reg 1 2 full_next $end
$var reg 1 + full_reg $end
$var reg 1 3 ledres $end
$var reg 7 4 out [6:0] $end
$var reg 2 5 rd_next [1:0] $end
$var reg 2 6 rd_reg [1:0] $end
$var reg 2 7 rd_succ [1:0] $end
$var reg 2 8 wr_next [1:0] $end
$var reg 2 9 wr_reg [1:0] $end
$var reg 2 : wr_succ [1:0] $end
$upscope $end
$upscope $end
$enddefinitions $end
#0
$dumpvars
b1 :
b0 9
b0 8
b1 7
b0 6
b0 5
bx 4
03
02
11
10
x/
1.
x-
0,
0+
0*
1)
1(
0'
1&
bx %
b0x $
0#
x"
1!
$end
#4
0(
#10
0!
#20
0"
0-
1/
13
1!
#30
0!
#40
1!
#50
0!
#60
1!
#70
0!
#80
1!
#90
0!
#100
1!
#110
0!
#120
1!
#130
0!
#140
1!
#150
0!
#160
1!
#170
0!
#180
1!
#190
0!
#200
1!
#210
0!
#220
1!
#230
0!
#240
1!
#250
0!
#260
1!
#270
0!
#280
1!
#290
0!
#300
1!
#310
0!
#320
1!
#330
0!
#340
1!
#350
0!
#360
1!
#370
0!
#380
1!
#390
0!
#400
1!
#410
0!
#420
1!
#430
0!
#440
1!
#450
0!
#460
1!
#470
0!
#480
1!
#490
0!
#500
1!
#510
0!
#520
1!
#530
0!
#540
1!
#550
0!
#560
1!
#570
0!
#580
1!
#590
0!
#600
1!
#610
0!
#620
1!
#630
0!
#640
1!
#650
0!
#660
1!
#670
0!
#680
1!
#690
0!
#700
1!
#710
0!
#720
1!
#730
0!
#740
1!
#750
0!
#760
1!
#770
0!
#780
1!
#790
0!
#800
1!
#810
0!
#820
1!
#830
0!
#840
1!
#850
0!
#860
1!
#870
0!
#880
1!
#890
0!
#900
1!
#910
0!
#920
1!
#930
0!
#940
1!
#950
0!
#960
1!
#970
0!
#980
1!
#990
0!
#1000
1!
#1010
0!
#1020
1!
#1030
0!
#1040
1!
#1050
0!
#1060
1!
#1070
0!
#1080
1!
#1090
0!
#1100
1!
#1110
0!
#1120
1!
#1130
0!
#1140
1!
#1150
0!
#1160
1!
#1170
0!
#1180
1!
#1190
0!
#1200
1!
#1210
0!
#1220
1!
#1230
0!
#1240
1!
#1250
0!
#1260
1!
#1270
0!
#1280
1!
#1290
0!
#1300
1!
#1310
0!
#1320
1!
#1330
0!
#1340
1!
#1350
0!
#1360
1!
#1370
0!
#1380
1!
#1390
0!
#1400
1!
#1410
0!
#1420
1!
#1430
0!
#1440
1!
#1450
0!
#1460
1!
#1470
0!
#1480
1!
#1490
0!
#1500
1!
#1510
0!
#1520
1!
#1530
0!
#1540
1!
#1550
0!
#1560
1!
#1570
0!
#1580
1!
#1590
0!
#1600
1!
#1610
0!
#1620
1!
#1630
0!
#1640
1!
#1650
0!
#1660
1!
#1670
0!
#1680
1!
#1690
0!
#1700
1!
#1710
0!
#1720
1!
#1730
0!
#1740
1!
#1750
0!
#1760
1!
#1770
0!
#1780
1!
#1790
0!
#1800
1!
#1810
0!
#1820
1!
#1830
0!
#1840
1!
#1850
0!
#1860
1!
#1870
0!
#1880
1!
#1890
0!
#1900
1!
#1910
0!
#1920
1!
#1930
0!
#1940
1!
#1950
0!
#1960
1!
#1970
0!
#1980
1!
#1990
0!
#2000
1!
#2010
0!
#2020
1!
#2030
0!
#2040
1!
#2050
0!
#2060
1!
#2070
0!
#2080
1!
#2090
0!
#2100
1!
#2110
0!
#2120
1!
#2130
0!
#2140
1!
#2150
0!
#2160
1!
#2170
0!
#2180
1!
#2190
0!
#2200
1!
#2210
0!
#2220
1!
#2230
0!
#2240
1!
#2250
0!
#2260
1!
#2270
0!
#2280
1!
#2290
0!
#2300
1!
#2310
0!
#2320
1!
#2330
0!
#2340
1!
#2350
0!
#2360
1!
#2370
0!
#2380
1!
#2390
0!
#2400
1!
#2410
0!
#2420
1!
#2430
0!
#2440
1!
#2450
0!
#2460
1!
#2470
0!
#2480
1!
#2490
0!
#2500
1!
#2510
0!
#2520
1!
#2530
0!
#2540
1!
#2550
0!
#2560
1!
#2570
0!
#2580
1!
#2590
0!
#2600
1!
#2610
0!
#2620
1!
#2630
0!
#2640
1!
#2650
0!
#2660
1!
#2670
0!
#2680
1!
#2690
0!
#2700
1!
#2710
0!
#2720
1!
#2730
0!
#2740
1!
#2750
0!
#2760
1!
#2770
0!
#2780
1!
#2790
0!
#2800
1!
#2810
0!
#2820
1!
#2830
0!
#2840
1!
#2850
0!
#2860
1!
#2870
0!
#2880
1!
#2890
0!
#2900
1!
#2910
0!
#2920
1!
#2930
0!
#2940
1!
#2950
0!
#2960
1!
#2970
0!
#2980
1!
#2990
0!
#3000
1!
#3010
0!
#3020
1!
#3030
0!
#3040
1!
#3050
0!
#3060
1!
#3070
0!
#3080
1!
#3090
0!
#3100
1!
#3110
0!
#3120
1!
#3130
0!
#3140
1!
#3150
0!
#3160
1!
#3170
0!
#3180
1!
#3190
0!
#3200
1!
#3210
0!
#3220
1!
#3230
0!
#3240
1!
#3250
0!
#3260
1!
#3270
0!
#3280
1!
#3290
0!
#3300
1!
#3310
0!
#3320
1!
#3330
0!
#3340
1!
#3350
0!
#3360
1!
#3370
0!
#3380
1!
#3390
0!
#3400
1!
#3410
0!
#3420
1!
#3430
0!
b0 $
0)
#3440
1*
00
b1 8
1#
0.
1!
#3450
0!
#3460
0*
b10 :
0#
0&
01
b1 9
0/
1!
#3470
0!
#3480
1!
#3490
0!
#3500
1!
#3510
0!
#3520
1!
#3530
0!
#3540
1!
#3550
0!
#3560
1!
#3570
0!
#3580
1!
#3590
0!
#3600
1!
#3610
0!
#3620
1!
#3630
0!
#3640
1!
#3650
0!
#3660
1!
#3670
0!
#3680
1!
#3690
0!
#3700
1!
#3710
0!
#3720
1!
#3730
0!
#3740
1!
#3750
0!
#3760
1!
#3770
0!
#3780
1!
#3790
0!
#3800
1!
#3810
0!
#3820
1!
#3830
0!
#3840
1!
#3850
0!
#3860
1!
#3870
0!
#3880
1!
#3890
0!
#3900
1!
#3910
0!
#3920
1!
#3930
0!
#3940
1!
#3950
0!
#3960
1!
#3970
0!
#3980
1!
#3990
0!
#4000
1!
#4010
0!
#4020
1!
#4030
0!
#4040
1!
#4050
0!
#4060
1!
#4070
0!
#4080
1!
#4090
0!
#4100
1!
#4110
0!
#4120
1!
#4130
0!
#4140
1!
#4150
0!
#4160
1!
#4170
0!
#4180
1!
#4190
0!
#4200
1!
#4210
0!
#4220
1!
#4230
0!
#4240
1!
#4250
0!
#4260
1!
#4270
0!
#4280
1!
#4290
0!
#4300
1!
#4310
0!
#4320
1!
#4330
0!
#4340
1!
#4350
0!
#4360
1!
#4370
0!
#4380
1!
#4390
0!
#4400
1!
#4410
0!
#4420
1!
#4430
0!
#4440
1!
#4450
0!
#4460
1!
#4470
0!
#4480
1!
#4490
0!
#4500
1!
#4510
0!
#4520
1!
#4530
0!
#4540
1!
#4550
0!
#4560
1!
#4570
0!
#4580
1!
#4590
0!
#4600
1!
#4610
0!
#4620
1!
#4630
0!
#4640
1!
#4650
0!
#4660
1!
#4670
0!
#4680
1!
#4690
0!
#4700
1!
#4710
0!
#4720
1!
#4730
0!
#4740
1!
#4750
0!
#4760
1!
#4770
0!
#4780
1!
#4790
0!
#4800
1!
#4810
0!
#4820
1!
#4830
0!
#4840
1!
#4850
0!
#4860
1!
#4870
0!
#4880
1!
#4890
0!
#4900
1!
#4910
0!
#4920
1!
#4930
0!
#4940
1!
#4950
0!
#4960
1!
#4970
0!
#4980
1!
#4990
0!
#5000
1!
#5010
0!
#5020
1!
#5030
0!
#5040
1!
#5050
0!
#5060
1!
#5070
0!
#5080
1!
#5090
0!
#5100
1!
#5110
0!
#5120
1!
#5130
0!
#5140
1!
#5150
0!
#5160
1!
#5170
0!
#5180
1!
#5190
0!
#5200
1!
#5210
0!
#5220
1!
#5230
0!
#5240
1!
#5250
0!
#5260
1!
#5270
0!
#5280
1!
#5290
0!
#5300
1!
#5310
0!
#5320
1!
#5330
0!
#5340
1!
#5350
0!
#5360
1!
#5370
0!
#5380
1!
#5390
0!
#5400
1!
#5410
0!
#5420
1!
#5430
0!
#5440
1!
#5450
0!
#5460
1!
#5470
0!
#5480
1!
#5490
0!
#5500
1!
#5510
0!
#5520
1!
#5530
0!
#5540
1!
#5550
0!
#5560
1!
#5570
0!
#5580
1!
#5590
0!
#5600
1!
#5610
0!
#5620
1!
#5630
0!
#5640
1!
#5650
0!
#5660
1!
#5670
0!
#5680
1!
#5690
0!
#5700
1!
#5710
0!
#5720
1!
#5730
0!
#5740
1!
#5750
0!
#5760
1!
#5770
0!
#5780
1!
#5790
0!
#5800
1!
#5810
0!
#5820
1!
#5830
0!
#5840
1!
#5850
0!
#5860
1!
#5870
0!
#5880
1!
#5890
0!
#5900
1!
#5910
0!
#5920
1!
#5930
0!
#5940
1!
#5950
0!
#5960
1!
#5970
0!
#5980
1!
#5990
0!
#6000
1!
#6010
0!
#6020
1!
#6030
0!
#6040
1!
#6050
0!
#6060
1!
#6070
0!
#6080
1!
#6090
0!
#6100
1!
#6110
0!
#6120
1!
#6130
0!
#6140
1!
#6150
0!
#6160
1!
#6170
0!
#6180
1!
#6190
0!
#6200
1!
#6210
0!
#6220
1!
#6230
0!
#6240
1!
#6250
0!
#6260
1!
#6270
0!
#6280
1!
#6290
0!
#6300
1!
#6310
0!
#6320
1!
#6330
0!
#6340
1!
#6350
0!
#6360
1!
#6370
0!
#6380
1!
#6390
0!
#6400
1!
#6410
0!
#6420
1!
#6430
0!
#6440
1!
#6450
0!
#6460
1!
#6470
0!
#6480
1!
#6490
0!
#6500
1!
#6510
0!
#6520
1!
#6530
0!
#6540
1!
#6550
0!
#6560
1!
#6570
0!
#6580
1!
#6590
0!
#6600
1!
#6610
0!
#6620
1!
#6630
0!
#6640
1!
#6650
0!
#6660
1!
#6670
0!
#6680
1!
#6690
0!
#6700
1!
#6710
0!
#6720
1!
#6730
0!
#6740
1!
#6750
0!
#6760
1!
#6770
0!
#6780
1!
#6790
0!
#6800
1!
#6810
0!
#6820
1!
#6830
0!
#6840
1!
#6850
0!
#6860
1.
1!
b1 $
1)
#6870
0!
#6880
1/
1!
