HW/RTL/07TOUCH/Version_02/02 verilog/ModulosBasicos/FIFO/fifo.v
// diseño de una fifo ciclica, para implementar en cada  bloque de proyecto
// ferney alberto beltran 2016 electrónica digital 1 universidad Nacional

module fifo
   #(
  	parameter adr_width = 10,
	parameter dat_width = 8
   )
   (
    input  clk, reset,
    input  rd, wr,
    input  [dat_width-1:0] data_in,
    output [dat_width-1:0] data_out,
    output empty, 
    output full
   );

   
   parameter depth = (1 << adr_width);

   //declaración de registros 
 
   reg [dat_width-1:0] array_reg [depth-1:0];// register array FIFO

   reg [adr_width-1:0] w_ptr_reg, w_ptr_next;
   reg [adr_width-1:0] r_ptr_reg, r_ptr_next;
   reg full_reg, empty_reg, full_next, empty_next;
   wire wr_en;


   assign data_out = array_reg[r_ptr_reg];
   assign wr_en = wr & ~full_reg;

   assign full = full_reg;
   assign empty = empty_reg;

   always @(posedge clk) begin
      if (wr_en)
         array_reg[w_ptr_reg] <= data_in;
   end

   // fifo control logic
   // register for read and write pointers
   always @(posedge clk, posedge reset) begin
      if (reset)
         begin
            w_ptr_reg <= 0;
            r_ptr_reg <= 0;
            full_reg <= 1'b0;
            empty_reg <= 1'b1;
         end
      else
         begin
            w_ptr_reg <= w_ptr_next;
            r_ptr_reg <= r_ptr_next;
            full_reg <= full_next;
            empty_reg <= empty_next;
         end
   end


   
   always @(posedge reset, posedge wr, posedge rd)
   begin
      if (reset) begin
	w_ptr_next =  0;
        r_ptr_next =  0;       
      end else begin
	      full_next = full_reg;
	      empty_next = empty_reg;
	      case ({wr, rd})
		 2'b01: // read
		    if (~empty_reg) // not empty
		       begin
		          r_ptr_next = r_ptr_reg + 1;
		          full_next = 1'b0;
		          if (r_ptr_next==w_ptr_reg)
		             empty_next = 1'b1;
		       end
		 2'b10: // write
		    if (~full_reg) // not full
		       begin
		          w_ptr_next = w_ptr_reg + 1;
		          empty_next = 1'b0;
		          if (w_ptr_next==r_ptr_reg)
		             full_next = 1'b1;
		       end
		 2'b11: // write and read
		    begin
		       w_ptr_next =  w_ptr_reg + 1;
		       r_ptr_next = r_ptr_reg + 1;
		    end
	      endcase
	end
   end


  
endmodule

HW/RTL/07TOUCH/Version_02/02 verilog/ModulosBasicos/FIFO/fifo_TB.v
//----------------------------------------------------------------------------
`timescale 1 ns / 100 ps

module fifo_TB;

//----------------------------------------------------------------------------
// Parameter (may differ for physical synthesis)
//----------------------------------------------------------------------------
parameter tck              = 2;       // clock period in ns
//----------------------------------------------------------------------------
//----------------------------------------------------------------------------

reg clk;
reg rst;

reg rd,wr;
reg [7:0] data_in;

//----------------------------------------------------------------------------
// Device Under Test 
//------------------------------------------------------------------

fifo  uut(.reset(rst),.clk(clk),.rd(rd),.wr(wr),.data_in(data_in));


/* Clocking device */
initial begin
	clk <= 0;
	rst <=1;
	#(2*tck) rst=0;
	rd <=0;
	wr<=0;
end

always #(tck/2) clk <= ~clk;


initial begin
#4;
data_in="h"; #1 wr=1; #2 wr=0;
data_in="o"; #1 wr=1; #2 wr=0;
data_in="l"; #1 wr=1; #2 wr=0;
data_in="a"; #1 wr=1; #2 wr=0;
data_in=" "; #1 wr=1; #2 wr=0;
data_in="m"; #1 wr=1; #2 wr=0;
data_in="u"; #1 wr=1; #2 wr=0;
data_in="n"; #1 wr=1; #2 wr=0;
data_in="d"; #1 wr=1; #2 wr=0;
data_in="o"; #1 wr=1; #2 wr=0;
data_in="."; #1 wr=1; #2 wr=0;
data_in="1"; #1 wr=1; #2 wr=0;
data_in="2"; #1 wr=1; #2 wr=0;
data_in="3"; #1 wr=1; #2 wr=0;
data_in="4"; #1 wr=1; #2 wr=0;
data_in="5"; #1 wr=1; #2 wr=0;
data_in="6"; #1 wr=1; #2 wr=0;
data_in="7"; #1 wr=1; #2 wr=0;
data_in="8"; #1 wr=1; #2 wr=0;
data_in="9"; #1 wr=1; #2 wr=0;
data_in="0"; #1 wr=1; #2 wr=0;

#1 rd=1; #2 rd=0;
#1 rd=1; #2 rd=0;
#1 rd=1; #2 rd=0;

data_in="a"; #1 wr=1; rd=0;#2 wr=0;rd=1;
data_in="b"; #1 wr=1; #2 wr=0;
data_in="c"; #1 wr=1; #2 wr=0;
data_in="d"; #1 wr=1; #2 wr=0;

#1 rd=1; #2 rd=0;
#1 rd=1; #2 rd=0;
#1 rd=1; #2 rd=0;
#1 rd=1; #2 rd=0;
#1 rd=1; #2 rd=0;
#1 rd=1; #2 rd=0;
#1 rd=1; #2 rd=0;
#1 rd=1; #2 rd=0;
#1 rd=1; #2 rd=0;
#1 rd=1; #2 rd=0;
#1 rd=1; #2 rd=0;
#1 rd=1; #2 rd=0;
#1 rd=1; #2 rd=0;
#1 rd=1; #2 rd=0;
#1 rd=1; #2 rd=0;
#1 rd=1; #2 rd=0;
#1 rd=1; #2 rd=0;
#1 rd=1; #2 rd=0;


end
initial begin: TEST_CASE
     $dumpfile("fifo_TB.vcd");
     $dumpvars(-1, uut);
     #(200) $finish;
   end

endmodule //

HW/RTL/07TOUCH/Version_02/02 verilog/ModulosBasicos/FIFO/simulation/fifo_TB.vcd
$date
	Sun Oct 29 16:19:06 2017
$end
$version
	Icarus Verilog
$end
$timescale
	100ps
$end
$scope module fifo_TB $end
$scope module uut $end
$var wire 1 ! clk $end
$var wire 8 " data_in [7:0] $end
$var wire 8 # data_out [7:0] $end
$var wire 1 $ empty $end
$var wire 1 % full $end
$var wire 1 & rd $end
$var wire 1 ' reset $end
$var wire 1 ( wr $end
$var wire 1 ) wr_en $end
$var reg 1 * empty_next $end
$var reg 1 + empty_reg $end
$var reg 1 , full_next $end
$var reg 1 - full_reg $end
$var reg 4 . r_ptr_next [3:0] $end
$var reg 4 / r_ptr_reg [3:0] $end
$var reg 4 0 w_ptr_next [3:0] $end
$var reg 4 1 w_ptr_reg [3:0] $end
$upscope $end
$upscope $end
$enddefinitions $end
#0
$dumpvars
b0 1
b0 0
b0 /
b0 .
0-
x,
1+
x*
x)
x(
1'
x&
0%
1$
bx #
bx "
0!
$end
#10
1!
#20
0!
#30
1!
#40
0)
0!
0(
0&
b1101000 "
0'
#50
0+
0$
b1 1
b1101000 #
1!
1)
b1 0
0*
0,
1(
#60
0!
#70
1!
0)
b1101111 "
0(
#80
0!
1)
b10 0
1(
#90
b10 1
1!
#100
0!
0)
b1101100 "
0(
#110
b11 1
1!
1)
b11 0
1(
#120
0!
#130
1!
0)
b1100001 "
0(
#140
0!
1)
b100 0
1(
#150
b100 1
1!
#160
0!
0)
b100000 "
0(
#170
b101 1
1!
1)
b101 0
1(
#180
0!
#190
1!
0)
b1101101 "
0(
#200
0!
1)
b110 0
1(
#210
b110 1
1!
#220
0!
0)
b1110101 "
0(
#230
b111 1
1!
1)
b111 0
1(
#240
0!
#250
1!
0)
b1101110 "
0(
#260
0!
1)
b1000 0
1(
#270
b1000 1
1!
#280
0!
0)
b1100100 "
0(
#290
b1001 1
1!
1)
b1001 0
1(
#300
0!
#310
1!
0)
b1101111 "
0(
#320
0!
1)
b1010 0
1(
#330
b1010 1
1!
#340
0!
0)
b101110 "
0(
#350
b1011 1
1!
1)
b1011 0
1(
#360
0!
#370
1!
0)
b110001 "
0(
#380
0!
1)
b1100 0
1(
#390
b1100 1
1!
#400
0!
0)
b110010 "
0(
#410
b1101 1
1!
1)
b1101 0
1(
#420
0!
#430
1!
0)
b110011 "
0(
#440
0!
1)
b1110 0
1(
#450
b1110 1
1!
#460
0!
0)
b110100 "
0(
#470
b1111 1
1!
1)
b1111 0
1(
#480
0!
#490
1!
0)
b110101 "
0(
#500
0!
1)
1,
b0 0
1(
#510
0)
1-
1%
b0 1
1!
#520
0!
b110110 "
0(
#530
1!
1(
#540
0!
#550
1!
b110111 "
0(
#560
0!
1(
#570
1!
#580
0!
b111000 "
0(
#590
1!
1(
#600
0!
#610
1!
b111001 "
0(
#620
0!
1(
#630
1!
#640
0!
b110000 "
0(
#650
1!
1(
#660
0!
#670
1!
0(
#680
0!
0,
b1 .
1&
#690
0-
0%
b1 /
b1101111 #
1!
#700
0!
0&
#710
b10 /
b1101100 #
1!
b10 .
1&
#720
0!
#730
1!
0&
#740
0!
b11 .
1&
#750
b11 /
b1100001 #
1!
#760
0!
b1100001 "
0&
#770
b1 1
1!
1)
b1 0
1(
#780
0!
#790
1!
0)
b1100010 "
0(
#800
0!
1)
b10 0
1(
#810
b10 1
1!
#820
0!
0)
b1100011 "
0(
#830
1-
1%
b11 1
1!
0)
1,
b11 0
1(
#840
0!
#850
1!
b1100100 "
0(
#860
0!
1(
#870
1!
#880
0!
0(
#890
0-
0%
b100 /
b100000 #
1!
0,
b100 .
1&
#900
0!
#910
1!
0&
#920
0!
b101 .
1&
#930
b101 /
b1101101 #
1!
#940
0!
0&
#950
b110 /
b1110101 #
1!
b110 .
1&
#960
0!
#970
1!
0&
#980
0!
b111 .
1&
#990
b111 /
b1101110 #
1!
#1000
0!
0&
#1010
b1000 /
b1100100 #
1!
b1000 .
1&
#1020
0!
#1030
1!
0&
#1040
0!
b1001 .
1&
#1050
b1001 /
b1101111 #
1!
#1060
0!
0&
#1070
b1010 /
b101110 #
1!
b1010 .
1&
#1080
0!
#1090
1!
0&
#1100
0!
b1011 .
1&
#1110
b1011 /
b110001 #
1!
#1120
0!
0&
#1130
b1100 /
b110010 #
1!
b1100 .
1&
#1140
0!
#1150
1!
0&
#1160
0!
b1101 .
1&
#1170
b1101 /
b110011 #
1!
#1180
0!
0&
#1190
b1110 /
b110100 #
1!
b1110 .
1&
#1200
0!
#1210
1!
0&
#1220
0!
b1111 .
1&
#1230
b1111 /
b110101 #
1!
#1240
0!
0&
#1250
b0 /
b1100001 #
1!
b0 .
1&
#1260
0!
#1270
1!
0&
#1280
0!
b1 .
1&
#1290
b1 /
b1100010 #
1!
#1300
0!
0&
#1310
b10 /
b1100011 #
1!
b10 .
1&
#1320
0!
#1330
1!
0&
#1340
0!
1*
b11 .
1&
#1350
1+
1$
b11 /
b1100001 #
1!
#1360
0!
0&
#1370
1!
1&
#1380
0!
#1390
1!
0&
#1400
0!
1&
#1410
1!
#1420
0!
0&
#1430
1!
#1440
0!
#1450
1!
#1460
0!
b1000100 "
#1470
b100 /
b100 1
b100000 #
1!
1)
b100 .
b100 0
1&
1(
#1480
0!
#1490
1!
0)
b1100001 "
0&
0(
#1500
0!
1)
b101 .
b101 0
1&
1(
#1510
b101 /
b101 1
b1101101 #
1!
#1520
0!
0)
b1101101 "
0&
0(
#1530
b110 /
b1110101 #
b110 1
1!
1)
b110 .
b110 0
1&
1(
#1540
0!
#1550
1!
0)
b1101001 "
0&
0(
#1560
0!
1)
b111 .
b111 0
1&
1(
#1570
b111 /
b111 1
b1101110 #
1!
#1580
0!
0)
b1110100 "
0&
0(
#1590
b1000 /
b1000 1
b1100100 #
1!
1)
b1000 .
b1000 0
1&
1(
#1600
0!
#1610
1!
0)
b1100001 "
0&
0(
#1620
0!
1)
b1001 .
b1001 0
1&
1(
#1630
b1001 /
b1001 1
b1101111 #
1!
#1640
0!
0)
b101100 "
0&
0(
#1650
b1010 /
b1010 1
b101110 #
1!
1)
b1010 .
b1010 0
1&
1(
#1660
0!
#1670
1!
0)
b100000 "
0&
0(
#1680
0!
1)
b1011 .
b1011 0
1&
1(
#1690
b1011 /
b1011 1
b110001 #
1!
#1700
0!
0)
b1110100 "
0&
0(
#1710
b1100 /
b1100 1
b110010 #
1!
1)
b1100 .
b1100 0
1&
1(
#1720
0!
#1730
1!
0)
b1110101 "
0&
0(
#1740
0!
1)
b1101 .
b1101 0
1&
1(
#1750
b1101 /
b1101 1
b110011 #
1!
#1760
0!
0)
b100000 "
0&
0(
#1770
b1110 /
b1110 1
b110100 #
1!
1)
b1110 .
b1110 0
1&
1(
#1780
0!
#1790
1!
0)
b1101110 "
0&
0(
#1800
0!
1)
b1111 .
b1111 0
1&
1(
#1810
b1111 /
b1111 1
b110101 #
1!
#1820
0!
0)
b1101111 "
0&
0(
#1830
b0 /
b0 1
b1100001 #
1!
1)
b0 .
b0 0
1&
1(
#1840
0!
#1850
1!
0)
b1110110 "
0&
0(
#1860
0!
1)
b1 .
b1 0
1&
1(
#1870
b1 /
b1 1
b1100010 #
1!
#1880
0!
0)
b1101001 "
0&
0(
#1890
b10 /
b10 1
b1100011 #
1!
1)
b10 .
b10 0
1&
1(
#1900
0!
#1910
1!
0)
b1101111 "
0&
0(
#1920
0!
1)
b11 .
b11 0
1&
1(
#1930
b11 /
b11 1
b1000100 #
1!
#1940
0!
0)
b100000 "
0&
0(
#1950
b100 /
b100 1
b1100001 #
1!
1)
b100 .
b100 0
1&
1(
#1960
0!
#1970
1!
0)
b1100101 "
0&
0(
#1980
0!
1)
b101 .
b101 0
1&
1(
#1990
b101 /
b101 1
b1101101 #
1!
#2000
0!
0)
b1110011 "
0&
0(
#2010
b110 /
b110 1
b1101001 #
1!
1)
b110 .
b110 0
1&
1(
#2020
0!
#2030
1!
0)
b100000 "
0&
0(
#2040
0!
1)
b111 .
b111 0
1&
1(
#2050
b111 /
b111 1
b1110100 #
1!
#2060
0!
0)
b1100101 "
0&
0(
#2070
b1000 /
b1000 1
b1100001 #
1!
1)
b1000 .
b1000 0
1&
1(
#2080
0!
#2090
1!
0)
0&
0(
#2100
0!
#2110
1!
#2120
0!
#2130
b0 /
b1110110 #
b0 1
1!
b0 .
b0 0
1'
#2140
0!
#2150
1!
#2160
0!
#2170
1!
0'
#2180
0!
#2190
1!
#2200
0!
#2210
1!
b1110011 "
#2220
0!
1)
b1 .
b1 0
1&
1(
#2230
b1 /
b1 1
b1101001 #
1!
#2240
0!
0)
b100000 "
0&
0(
#2250
b10 /
b10 1
b1101111 #
1!
1)
b10 .
b10 0
1&
1(
#2260
0!
#2270
1!
0)
b1100101 "
0&
0(
#2280
0!
1)
b11 .
b11 0
1&
1(
#2290
b11 /
b11 1
b100000 #
1!
#2300
0!
0)
b1101100 "
0&
0(
#2310
b100 /
b100 1
b1100101 #
1!
1)
b100 .
b100 0
1&
1(
#2320
0!
#2330
1!
0)
b100000 "
0&
0(
#2340
0!
1)
b101 .
b101 0
1&
1(
#2350
b101 /
b101 1
b1110011 #
1!
#2360
0!
0)
b1101000 "
0&
0(
#2370
b110 /
b110 1
b100000 #
1!
1)
b110 .
b110 0
1&
1(
#2380
0!
#2390
1!
0)
b1101111 "
0&
0(
#2400
0!
1)
b111 .
b111 0
1&
1(
#2410
b111 /
b111 1
b1100101 #
1!
#2420
0!
0)
b1101101 "
0&
0(
#2430
b1000 /
b1000 1
b1100001 #
1!
1)
b1000 .
b1000 0
1&
1(
#2440
0!
#2450
1!
0)
b1100010 "
0&
0(
#2460
0!
1)
b1001 .
b1001 0
1&
1(
#2470
b1001 /
b1001 1
b101100 #
1!
#2480
0!
0)
b1110010 "
0&
0(
#2490
b1010 /
b1010 1
b100000 #
1!
1)
b1010 .
b1010 0
1&
1(
#2500
0!
#2510
1!
0)
b1100101 "
0&
0(
#2520
0!
1)
b1011 .
b1011 0
1&
1(
#2530
b1011 /
b1011 1
b1110100 #
1!
#2540
0!
0)
b100000 "
0&
0(
#2550
b1100 /
b1100 1
b1110101 #
1!
1)
b1100 .
b1100 0
1&
1(
#2560
0!
#2570
1!
0)
b1101101 "
0&
0(
#2580
0!
1)
b1101 .
b1101 0
1&
1(
#2590
b1101 /
b1101 1
b100000 #
1!
#2600
0!
0)
b1100001 "
0&
0(
#2610
b1110 /
b1110 1
b1101110 #
1!
1)
b1110 .
b1110 0
1&
1(
#2620
0!
#2630
1!
0)
b1110011 "
0&
0(
#2640
0!
1)
b1111 .
b1111 0
1&
1(
#2650
b1111 /
b1111 1
b1101111 #
1!
#2660
0!
0)
b100000 "
0&
0(
#2670
b0 /
b0 1
b1110011 #
1!
1)
b0 .
b0 0
1&
1(
#2680
0!
#2690
1!
0)
b1100001 "
0&
0(
#2700
0!
1)
b1 .
b1 0
1&
1(
#2710
b1 /
b1 1
b100000 #
1!
#2720
0!
0)
b1100110 "
0&
0(
#2730
b10 /
b10 1
b1100101 #
1!
1)
b10 .
b10 0
1&
1(
#2740
0!
#2750
1!
0)
b1101111 "
0&
0(
#2760
0!
1)
b11 .
b11 0
1&
1(
#2770
b11 /
b11 1
b1101100 #
1!
#2780
0!
0)
b1110010 "
0&
0(
#2790
b100 /
b100 1
b100000 #
1!
1)
b100 .
b100 0
1&
1(
#2800
0!
#2810
1!
0)
b1110100 "
0&
0(
#2820
0!
1)
b101 .
b101 0
1&
1(
#2830
b101 /
b101 1
b1101000 #
1!
#2840
0!
0)
0&
0(
#2850
1!
#2860
0!
#2870
1!
#2880
b0 /
b1100001 #
b0 1
0!
b0 .
b0 0
1'
#2890
1!
#2900
0!
#2910
1!
#2920
0!
0'
#2930
1!
#2940
0!
#2950
1!
#2960
0!
b1010001 "
#2970
0+
0$
b1 1
b1010001 #
1!
1)
0*
b1 0
1(
#2980
0!
#2990
1!
0)
b1110101 "
0(
#3000
0!
1)
b10 0
1(
#3010
b10 1
1!
#3020
0!
0)
b1100101 "
0(
#3030
b11 1
1!
1)
b11 0
1(
#3040
0!
#3050
1!
0)
b100000 "
0(
#3060
0!
1)
b100 0
1(
#3070
b100 1
1!
#3080
0!
0)
b1101100 "
0(
#3090
b101 1
1!
1)
b101 0
1(
#3100
0!
#3110
1!
0)
b1100001 "
0(
#3120
0!
1)
b110 0
1(
#3130
b110 1
1!
#3140
0!
0)
b100000 "
0(
#3150
b111 1
1!
1)
b111 0
1(
#3160
0!
#3170
1!
0)
b1110110 "
0(
#3180
0!
1)
b1000 0
1(
#3190
b1000 1
1!
#3200
0!
0)
b1101001 "
0(
#3210
b1001 1
1!
1)
b1001 0
1(
#3220
0!
#3230
1!
0)
b1100100 "
0(
#3240
0!
1)
b1010 0
1(
#3250
b1010 1
1!
#3260
0!
0)
b1100001 "
0(
#3270
b1011 1
1!
1)
b1011 0
1(
#3280
0!
#3290
1!
0)
b100000 "
0(
#3300
0!
1)
b1100 0
1(
#3310
b1100 1
1!
#3320
0!
0)
b1110011 "
0(
#3330
b1101 1
1!
1)
b1101 0
1(
#3340
0!
#3350
1!
0)
b1100101 "
0(
#3360
0!
1)
b1110 0
1(
#3370
b1110 1
1!
#3380
0!
0)
b1100001 "
0(
#3390
b1111 1
1!
1)
b1111 0
1(
#3400
0!
#3410
1!
0)
b100000 "
0(
#3420
0!
1)
1,
b0 0
1(
#3430
0)
1-
1%
b0 1
1!
#3440
0!
b1101101 "
0(
#3450
1!
1(
#3460
0!
#3470
1!
b1100001 "
0(
#3480
0!
1(
#3490
1!
#3500
0!
b1110011 "
0(
#3510
1!
1(
#3520
0!
#3530
1!
b100000 "
0(
#3540
0!
1(
#3550
1!
#3560
0!
b1110000 "
0(
#3570
1!
1(
#3580
0!
#3590
1!
0(
#3600
0!
0,
b1 .
1&
#3610
0-
0%
b1 /
b1110101 #
1!
#3620
0!
0&
#3630
b10 /
b1100101 #
1!
b10 .
1&
#3640
0!
#3650
1!
0&
#3660
0!
b11 .
1&
#3670
b11 /
b100000 #
1!
#3680
0!
0&
#3690
b100 /
b1101100 #
1!
b100 .
1&
#3700
0!
#3710
1!
0&
#3720
0!
b101 .
1&
#3730
b101 /
b1100001 #
1!
#3740
0!
0&
#3750
b110 /
b100000 #
1!
b110 .
1&
#3760
0!
#3770
1!
0&
#3780
0!
b111 .
1&
#3790
b111 /
b1110110 #
1!
#3800
0!
0&
#3810
b1000 /
b1101001 #
1!
b1000 .
1&
#3820
0!
#3830
1!
0&
#3840
0!
b1001 .
1&
#3850
b1001 /
b1100100 #
1!
#3860
0!
0&
#3870
b1010 /
b1100001 #
1!
b1010 .
1&
#3880
0!
#3890
1!
0&
#3900
0!
b1011 .
1&
#3910
b1011 /
b100000 #
1!
#3920
0!
0&
#3930
b1100 /
b1110011 #
1!
b1100 .
1&
#3940
0!
#3950
1!
0&
#3960
0!
b1101 .
1&
#3970
b1101 /
b1100101 #
1!
#3980
0!
0&
#3990
b1110 /
b1100001 #
1!
b1110 .
1&
#4000
0!
#4010
1!
0&
#4020
0!
b1111 .
1&
#4030
b1111 /
b100000 #
1!
#4040
0!
0&
#4050
1+
1$
b0 /
b1010001 #
1!
1*
b0 .
1&
#4060
0!
#4070
1!
0&
#4080
0!
1&
#4090
1!
#4100
0!
0&
#4110
1!
1&
#4120
0!
#4130
1!
0&
#4140
0!
#4150
1!
#4160
0!
#4170
1!
b1011001 "
#4180
0!
1)
0*
b1 0
1(
#4190
0+
0$
b1 1
b1011001 #
1!
#4200
0!
0)
b1101111 "
0(
#4210
b10 1
1!
1)
b10 0
1(
#4220
0!
#4230
1!
0)
b100000 "
0(
#4240
0!
1)
b11 0
1(
#4250
b11 1
1!
#4260
0!
0)
b1110100 "
0(
#4270
b100 1
1!
1)
b100 0
1(
#4280
0!
#4290
1!
0)
b1100101 "
0(
#4300
0!
1)
b101 0
1(
#4310
b101 1
1!
#4320
0!
0)
b100000 "
0(
#4330
b110 1
1!
1)
b110 0
1(
#4340
0!
#4350
1!
0)
b1100100 "
0(
#4360
0!
1)
b111 0
1(
#4370
b111 1
1!
#4380
0!
0)
b1100001 "
0(
#4390
b1000 1
1!
1)
b1000 0
1(
#4400
0!
#4410
1!
0)
b1110010 "
0(
#4420
0!
1)
b1001 0
1(
#4430
b1001 1
1!
#4440
0!
0)
b1100101 "
0(
#4450
b1010 1
1!
1)
b1010 0
1(
#4460
0!
#4470
1!
0)
b101100 "
0(
#4480
0!
1)
b1011 0
1(
#4490
b1011 1
1!
#4500
0!
0)
b100000 "
0(
#4510
b1100 1
1!
1)
b1100 0
1(
#4520
0!
#4530
1!
0)
b1110100 "
0(
#4540
0!
1)
b1101 0
1(
#4550
b1101 1
1!
#4560
0!
0)
b1100101 "
0(
#4570
b1110 1
1!
1)
b1110 0
1(
#4580
0!
#4590
1!
0)
b100000 "
0(
#4600
0!
1)
b1111 0
1(
#4610
b1111 1
1!
#4620
0!
0)
b1100100 "
0(
#4630
1-
1%
b0 1
1!
0)
1,
b0 0
1(
#4640
0!
#4650
1!
b1100001 "
0(
#4660
0!
1(
#4670
1!
#4680
0!
b1110010 "
0(
#4690
1!
1(
#4700
0!
#4710
1!
b1100101 "
0(
#4720
0!
1(
#4730
1!
#4740
0!
b100000 "
0(
#4750
1!
1(
#4760
0!
#4770
1!
b1101101 "
0(
#4780
0!
1(
#4790
1!
#4800
0!
0(
#4810
0-
0%
b1 /
b1101111 #
1!
0,
b1 .
1&
#4820
0!
#4830
1!
0&
#4840
0!
b10 .
1&
#4850
b10 /
b100000 #
1!
#4860
0!
0&
#4870
b11 /
b1110100 #
1!
b11 .
1&
#4880
0!
#4890
1!
0&
#4900
0!
b100 .
1&
#4910
b100 /
b1100101 #
1!
#4920
0!
0&
#4930
b101 /
b100000 #
1!
b101 .
1&
#4940
0!
#4950
1!
0&
#4960
0!
b110 .
1&
#4970
b110 /
b1100100 #
1!
#4980
0!
0&
#4990
b111 /
b1100001 #
1!
b111 .
1&
#5000
0!
#5010
1!
0&
#5020
0!
b1000 .
1&
#5030
b1000 /
b1110010 #
1!
#5040
0!
0&
#5050
b1001 /
b1100101 #
1!
b1001 .
1&
#5060
0!
#5070
1!
0&
#5080
0!
b1010 .
1&
#5090
b1010 /
b101100 #
1!
#5100
0!
0&
#5110
b1011 /
b100000 #
1!
b1011 .
1&
#5120
0!
#5130
1!
0&
#5140
0!
b1100 .
1&
#5150
b1100 /
b1110100 #
1!
#5160
0!
0&
#5170
b1101 /
b1100101 #
1!
b1101 .
1&
#5180
0!
#5190
1!
0&
#5200
0!
b1110 .
1&
#5210
b1110 /
b100000 #
1!
#5220
0!
0&
#5230
b1111 /
b1100100 #
1!
b1111 .
1&
#5240
0!
#5250
1!
0&
#5260
0!
1*
b0 .
1&
#5270
1+
1$
b0 /
b1011001 #
1!
#5280
0!
0&
#5290
1!
1&
#5300
0!
#5310
1!
0&
#5320
0!
1&
#5330
1!
#5340
0!
0&
#5350
1!
#5360
0!
#5370
1!
#5380
0!
1'
#5390
1!
#5400
0!
#5410
1!
#5420
0!
0'
#5430
1!
#5440
0!
#5450
1!
#5460
0!
b1100001 "
#5470
0+
0$
b1 1
b1100001 #
1!
1)
0*
b1 0
1(
#5480
0!
#5490
1!
0)
b1100010 "
0(
#5500
0!
1)
b10 0
1(
#5510
b10 1
1!
#5520
0!
0)
b1100011 "
0(
#5530
b11 1
1!
1)
b11 0
1(
#5540
0!
#5550
1!
0)
b1100100 "
0(
#5560
0!
1)
b100 0
1(
#5570
b100 1
1!
#5580
0!
0)
b1100101 "
0(
#5590
b101 1
1!
1)
b101 0
1(
#5600
0!
#5610
1!
0)
b1100110 "
0(
#5620
0!
1)
b110 0
1(
#5630
b110 1
1!
#5640
0!
0)
b1100111 "
0(
#5650
b111 1
1!
1)
b111 0
1(
#5660
0!
#5670
1!
0)
b1101000 "
0(
#5680
0!
1)
b1000 0
1(
#5690
b1000 1
1!
#5700
0!
0)
b1101001 "
0(
#5710
b1001 1
1!
1)
b1001 0
1(
#5720
0!
#5730
1!
0)
b1101010 "
0(
#5740
0!
1)
b1010 0
1(
#5750
b1010 1
1!
#5760
0!
0)
b1101011 "
0(
#5770
b1011 1
1!
1)
b1011 0
1(
#5780
0!
#5790
1!
0)
b1101100 "
0(
#5800
0!
1)
b1100 0
1(
#5810
b1100 1
1!
#5820
0!
0)
b1101101 "
0(
#5830
b1101 1
1!
1)
b1101 0
1(
#5840
0!
#5850
1!
0)
b1101110 "
0(
#5860
0!
1)
b1110 0
1(
#5870
b1110 1
1!
#5880
0!
0)
b1101111 "
0(
#5890
b1111 1
1!
1)
b1111 0
1(
#5900
0!
#5910
1!
0)
b1110000 "
0(
#5920
0!
1)
1,
b0 0
1(
#5930
0)
1-
1%
b0 1
1!
#5940
0!
0(
#5950
0-
0%
b1 /
b1100010 #
1!
0,
b1 .
1&
#5960
0!
#5970
1!
0&
#5980
0!
b10 .
1&
#5990
b10 /
b1100011 #
1!
#6000
0!
0&
#6010
b11 /
b1100100 #
1!
b11 .
1&
#6020
0!
#6030
1!
0&
#6040
0!
b100 .
1&
#6050
b100 /
b1100101 #
1!
#6060
0!
0&
#6070
b101 /
b1100110 #
1!
b101 .
1&
#6080
0!
#6090
1!
0&
#6100
0!
b110 .
1&
#6110
b110 /
b1100111 #
1!
#6120
0!
0&
#6130
b111 /
b1101000 #
1!
b111 .
1&
#6140
0!
#6150
1!
0&
#6160
0!
b1000 .
1&
#6170
b1000 /
b1101001 #
1!
#6180
0!
0&
#6190
b1001 /
b1101010 #
1!
b1001 .
1&
#6200
0!
#6210
1!
0&
#6220
0!
b1010 .
1&
#6230
b1010 /
b1101011 #
1!
#6240
0!
0&
#6250
b1011 /
b1101100 #
1!
b1011 .
1&
#6260
0!
#6270
1!
0&
#6280
0!
b1100 .
1&
#6290
b1100 /
b1101101 #
1!
#6300
0!
0&
#6310
b1101 /
b1101110 #
1!
b1101 .
1&
#6320
0!
#6330
1!
0&
#6340
0!
b1110 .
1&
#6350
b1110 /
b1101111 #
1!
#6360
0!
0&
#6370
b1111 /
b1110000 #
1!
b1111 .
1&
#6380
0!
#6390
1!
0&
#6400
0!
1*
b0 .
1&
#6410
1+
1$
b0 /
b1100001 #
1!
#6420
0!
0&
#6430
1!
1&
#6440
0!
#6450
1!
0&
#6460
0!
1&
#6470
1!
#6480
0!
0&
#6490
1!
1&
#6500
0!
#6510
1!
0&
#6520
0!
1&
#6530
1!
#6540
0!
0&
#6550
1!
1&
#6560
0!
#6570
1!
0&
#6580
0!
1&
#6590
1!
#6600
0!
0&
#6610
1!
1&
#6620
0!
#6630
1!
0&
#6640
0!
1&
#6650
1!
#6660
0!
0&
#6670
1!
1&
#6680
0!
#6690
1!
0&
#6700
0!
1&
#6710
1!
#6720
0!
0&
#6730
1!
1&
#6740
0!
#6750
1!
0&
#6760
0!
1&
#6770
1!
#6780
0!
0&
#6790
1!
1&
#6800
0!
#6810
1!
0&
#6820
0!
1&
#6830
1!
#6840
0!
0&
#6850
1!
1&
#6860
0!
#6870
1!
0&
#6880
0!
1&
#6890
1!
#6900
0!
0&
#6910
1!
#6920
0!
#6930
1!
#6940
0!
1'
#6950
1!
#6960
0!
#6970
1!
#6980
0!
0'
#6990
1!
#7000
0!
#7010
1!
#7020
0!
b1101000 "
#7030
0+
0$
b1 1
b1101000 #
1!
1)
0*
b1 0
1(
#7040
0!
#7050
1!
0)
b1101111 "
0(
#7060
0!
1)
b10 0
1(
#7070
b10 1
1!
#7080
0!
0)
b1101100 "
0(
#7090
b11 1
1!
1)
b11 0
1(
#7100
0!
#7110
1!
0)
b1100001 "
0(
#7120
0!
1)
b100 0
1(
#7130
b100 1
1!
#7140
0!
0)
b100000 "
0(
#7150
b101 1
1!
1)
b101 0
1(
#7160
0!
#7170
1!
0)
b1101101 "
0(
#7180
0!
1)
b110 0
1(
#7190
b110 1
1!
#7200
0!
0)
b1110101 "
0(
#7210
b111 1
1!
1)
b111 0
1(
#7220
0!
#7230
1!
0)
b1101110 "
0(
#7240
0!
1)
b1000 0
1(
#7250
b1000 1
1!
#7260
0!
0)
b1100100 "
0(
#7270
b1001 1
1!
1)
b1001 0
1(
#7280
0!
#7290
1!
0)
b1101111 "
0(
#7300
0!
1)
b1010 0
1(
#7310
b1010 1
1!
#7320
0!
0)
b101110 "
0(
#7330
b1011 1
1!
1)
b1011 0
1(
#7340
0!
#7350
1!
0)
b110001 "
0(
#7360
0!
1)
b1100 0
1(
#7370
b1100 1
1!
#7380
0!
0)
b110010 "
0(
#7390
b1101 1
1!
1)
b1101 0
1(
#7400
0!
#7410
1!
0)
b110011 "
0(
#7420
0!
1)
b1110 0
1(
#7430
b1110 1
1!
#7440
0!
0)
b110100 "
0(
