HW/RTL/01BLUETOOTH/Version_02/02 verilog/BLUETOOTH/TX/transmision.v
module transmision (input rw, input wire clk_in, input wire clk_div, input wire [7:0] din, output busy, output done, output reg tx);

parameter count = 8;

reg [2:0] counter = 0; //registro para llevar el conteo

initial begin
	tx = 1'b1;
end

parameter STATE_IDLE	= 2'b00;
parameter STATE_START	= 2'b01;
parameter STATE_DATA	= 2'b10;
parameter STATE_STOP	= 2'b11;

reg [7:0] data = 8'b11111111;
reg [2:0] bitpos = 0;
reg [1:0] state = STATE_IDLE;

always @(posedge clk_in) begin
	case (state)
	STATE_IDLE: begin
		if (rw) begin
			state <= STATE_START;
			data <= din;
			bitpos <= 0;
		end
	end
	STATE_START: begin
		if (clk_div) begin
			tx <= 1'b0;
			state <= STATE_DATA;
		end
	end
	STATE_DATA: begin
		if (clk_div) begin
			if (bitpos == count-1)begin
				tx<=data[bitpos]; 
				state <= STATE_STOP;
			end
			else begin
				tx<=data[bitpos]; //hacer este cambio cuando todo funcine :v 
				bitpos <= bitpos + 1;
			end
			//tx <= data[bitpos];
		end
	end
	STATE_STOP: begin
		if (clk_div) begin
			tx <= 1'b1;
			state <= STATE_IDLE;
		end
	end
	default: begin
		tx <= 1'b1;
		state <= STATE_IDLE;
	end
	endcase
end

assign busy = (state != STATE_IDLE);
assign done = (state == STATE_STOP);

endmodule

HW/RTL/01BLUETOOTH/Version_02/02 verilog/BLUETOOTH/TX/transmision_TB.v
module transmision_TB();

//Registro para generar la señal de reloj
reg clk_in = 1;
reg clk_div=0;
//wire clk_out;
reg rw = 0;
reg [7:0] din = 0;
wire busy;
wire done;
wire tx;
reg [1:0] divcounter = 0; //registro para llevar el conteo

//Instanciar transmision
transmision dut(.clk_in(clk_in),.clk_div(clk_div),.rw(rw),.din(din),.busy(busy),.done(done),.tx(tx));

//Generador de reloj fpga. Periodo 2 unidades
always #1 clk_in = ~clk_in;

//Generador de reloj_div 

always @(posedge clk_in) begin
  if (divcounter == 2)begin
        divcounter <= 0;
        clk_div=1;
   end
  else begin
        divcounter <= divcounter + 1;
        clk_div = 0;
   end
end
initial begin
#20
rw = 1;
din = 8'b00110011;
#1
rw = 0;
end



//-- Proceso al inicio
initial begin

  //-- Fichero donde almacenar los resultados
  $dumpfile("transmision_TB.vcd");
  $dumpvars(0, transmision_TB);

  # 400 $display("FIN de la simulacion");
  $finish;
end
endmodule

HW/RTL/01BLUETOOTH/Version_02/02 verilog/BLUETOOTH/TX/simulation/transmision_TB.vcd
$date
	Tue Oct 31 10:00:40 2017
$end
$version
	Icarus Verilog
$end
$timescale
	1s
$end
$scope module transmision_TB $end
$var wire 1 ! busy $end
$var wire 1 " done $end
$var wire 1 # tx $end
$var reg 1 $ clk_div $end
$var reg 1 % clk_in $end
$var reg 8 & din [7:0] $end
$var reg 2 ' divcounter [1:0] $end
$var reg 1 ( rw $end
$scope module dut $end
$var wire 1 ! busy $end
$var wire 1 ) clk_div $end
$var wire 1 * clk_in $end
$var wire 8 + din [7:0] $end
$var wire 1 " done $end
$var wire 1 , rw $end
$var reg 3 - bitpos [2:0] $end
$var reg 3 . counter [2:0] $end
$var reg 8 / data [7:0] $end
$var reg 2 0 state [1:0] $end
$var reg 1 1 tx $end
$upscope $end
$upscope $end
$enddefinitions $end
#0
$dumpvars
11
b0 0
b11111111 /
b0 .
b0 -
0,
b0 +
1*
0)
0(
b0 '
b0 &
1%
0$
1#
0"
0!
$end
#1
0%
0*
#2
b1 '
1%
1*
#3
0%
0*
#4
b10 '
1%
1*
#5
0%
0*
#6
b0 '
1$
1)
1%
1*
#7
0%
0*
#8
b1 '
0$
0)
1%
1*
#9
0%
0*
#10
b10 '
1%
1*
#11
0%
0*
#12
b0 '
1$
1)
1%
1*
#13
0%
0*
#14
b1 '
0$
0)
1%
1*
#15
0%
0*
#16
b10 '
1%
1*
#17
0%
0*
#18
b0 '
1$
1)
1%
1*
#19
0%
0*
#20
b110011 /
b1 0
1!
b1 '
0$
0)
1%
1*
b110011 &
b110011 +
1(
1,
#21
0%
0*
0(
0,
#22
b10 '
1%
1*
#23
0%
0*
#24
b10 0
01
0#
b0 '
1$
1)
1%
1*
#25
0%
0*
#26
b1 '
b1 -
11
1#
0$
0)
1%
1*
#27
0%
0*
#28
b10 '
1%
1*
#29
0%
0*
#30
b0 '
1$
1)
1%
1*
#31
0%
0*
#32
b1 '
0$
0)
1%
1*
#33
0%
0*
#34
b10 '
1%
1*
#35
0%
0*
#36
b10 -
b0 '
1$
1)
1%
1*
#37
0%
0*
#38
b1 '
b11 -
01
0#
0$
0)
1%
1*
#39
0%
0*
#40
b10 '
1%
1*
#41
0%
0*
#42
b0 '
1$
1)
1%
1*
#43
0%
0*
#44
b1 '
0$
0)
1%
1*
#45
0%
0*
#46
b10 '
1%
1*
#47
0%
0*
#48
b100 -
b0 '
1$
1)
1%
1*
#49
0%
0*
#50
b1 '
b101 -
11
1#
0$
0)
1%
1*
#51
0%
0*
#52
b10 '
1%
1*
#53
0%
0*
#54
b0 '
1$
1)
1%
1*
#55
0%
0*
#56
b1 '
0$
0)
1%
1*
#57
0%
0*
#58
b10 '
1%
1*
#59
0%
0*
#60
b110 -
b0 '
1$
1)
1%
1*
#61
0%
0*
#62
b1 '
b111 -
01
0#
0$
0)
1%
1*
#63
0%
0*
#64
b10 '
1%
1*
#65
0%
0*
#66
b0 '
1$
1)
1%
1*
#67
0%
0*
#68
b1 '
0$
0)
1%
1*
#69
0%
0*
#70
b10 '
1%
1*
#71
0%
0*
#72
b11 0
1"
b0 '
1$
1)
1%
1*
#73
0%
0*
#74
b1 '
b0 0
0!
0"
11
1#
0$
0)
1%
1*
#75
0%
0*
#76
b10 '
1%
1*
#77
0%
0*
#78
b0 '
1$
1)
1%
1*
#79
0%
0*
#80
b1 '
0$
0)
1%
1*
#81
0%
0*
#82
b10 '
1%
1*
#83
0%
0*
#84
b0 '
1$
1)
1%
1*
#85
0%
0*
#86
b1 '
0$
0)
1%
1*
#87
0%
0*
#88
b10 '
1%
1*
#89
0%
0*
#90
b0 '
1$
1)
1%
1*
#91
0%
0*
#92
b1 '
0$
0)
1%
1*
#93
0%
0*
#94
b10 '
1%
1*
#95
0%
0*
#96
b0 '
1$
1)
1%
1*
#97
0%
0*
#98
b1 '
0$
0)
1%
1*
#99
0%
0*
#100
b10 '
1%
1*
#101
0%
0*
#102
b0 '
1$
1)
1%
1*
#103
0%
0*
#104
b1 '
0$
0)
1%
1*
#105
0%
0*
#106
b10 '
1%
1*
#107
0%
0*
#108
b0 '
1$
1)
1%
1*
#109
0%
0*
#110
b1 '
0$
0)
1%
1*
#111
0%
0*
#112
b10 '
1%
1*
#113
0%
0*
#114
b0 '
1$
1)
1%
1*
#115
0%
0*
#116
b1 '
0$
0)
1%
1*
#117
0%
0*
#118
b10 '
1%
1*
#119
0%
0*
#120
b0 '
1$
1)
1%
1*
#121
0%
0*
#122
b1 '
0$
0)
1%
1*
#123
0%
0*
#124
b10 '
1%
1*
#125
0%
0*
#126
b0 '
1$
1)
1%
1*
#127
0%
0*
#128
b1 '
0$
0)
1%
1*
#129
0%
0*
#130
b10 '
1%
1*
#131
0%
0*
#132
b0 '
1$
1)
1%
1*
#133
0%
0*
#134
b1 '
0$
0)
1%
1*
#135
0%
0*
#136
b10 '
1%
1*
#137
0%
0*
#138
b0 '
1$
1)
1%
1*
#139
0%
0*
#140
b1 '
0$
0)
1%
1*
#141
0%
0*
#142
b10 '
1%
1*
#143
0%
0*
#144
b0 '
1$
1)
1%
1*
#145
0%
0*
#146
b1 '
0$
0)
1%
1*
#147
0%
0*
#148
b10 '
1%
1*
#149
0%
0*
#150
b0 '
1$
1)
1%
1*
#151
0%
0*
#152
b1 '
0$
0)
1%
1*
#153
0%
0*
#154
b10 '
1%
1*
#155
0%
0*
#156
b0 '
1$
1)
1%
1*
#157
0%
0*
#158
b1 '
0$
0)
1%
1*
#159
0%
0*
#160
b10 '
1%
1*
#161
0%
0*
#162
b0 '
1$
1)
1%
1*
#163
0%
0*
#164
b1 '
0$
0)
1%
1*
#165
0%
0*
#166
b10 '
1%
1*
#167
0%
0*
#168
b0 '
1$
1)
1%
1*
#169
0%
0*
#170
b1 '
0$
0)
1%
1*
#171
0%
0*
#172
b10 '
1%
1*
#173
0%
0*
#174
b0 '
1$
1)
1%
1*
#175
0%
0*
#176
b1 '
0$
0)
1%
1*
#177
0%
0*
#178
b10 '
1%
1*
#179
0%
0*
#180
b0 '
1$
1)
1%
1*
#181
0%
0*
#182
b1 '
0$
0)
1%
1*
#183
0%
0*
#184
b10 '
1%
1*
#185
0%
0*
#186
b0 '
1$
1)
1%
1*
#187
0%
0*
#188
b1 '
0$
0)
1%
1*
#189
0%
0*
#190
b10 '
1%
1*
#191
0%
0*
#192
b0 '
1$
1)
1%
1*
#193
0%
0*
#194
b1 '
0$
0)
1%
1*
#195
0%
0*
#196
b10 '
1%
1*
#197
0%
0*
#198
b0 '
1$
1)
1%
1*
#199
0%
0*
#200
b1 '
0$
0)
1%
1*
#201
0%
0*
#202
b10 '
1%
1*
#203
0%
0*
#204
b0 '
1$
1)
1%
1*
#205
0%
0*
#206
b1 '
0$
0)
1%
1*
#207
0%
0*
#208
b10 '
1%
1*
#209
0%
0*
#210
b0 '
1$
1)
1%
1*
#211
0%
0*
#212
b1 '
0$
0)
1%
1*
#213
0%
0*
#214
b10 '
1%
1*
#215
0%
0*
#216
b0 '
1$
1)
1%
1*
#217
0%
0*
#218
b1 '
0$
0)
1%
1*
#219
0%
0*
#220
b10 '
1%
1*
#221
0%
0*
#222
b0 '
1$
1)
1%
1*
#223
0%
0*
#224
b1 '
0$
0)
1%
1*
#225
0%
0*
#226
b10 '
1%
1*
#227
0%
0*
#228
b0 '
1$
1)
1%
1*
#229
0%
0*
#230
b1 '
0$
0)
1%
1*
#231
0%
0*
#232
b10 '
1%
1*
#233
0%
0*
#234
b0 '
1$
1)
1%
1*
#235
0%
0*
#236
b1 '
0$
0)
1%
1*
#237
0%
0*
#238
b10 '
1%
1*
#239
0%
0*
#240
b0 '
1$
1)
1%
1*
#241
0%
0*
#242
b1 '
0$
0)
1%
1*
#243
0%
0*
#244
b10 '
1%
1*
#245
0%
0*
#246
b0 '
1$
1)
1%
1*
#247
0%
0*
#248
b1 '
0$
0)
1%
1*
#249
0%
0*
#250
b10 '
1%
1*
#251
0%
0*
#252
b0 '
1$
1)
1%
1*
#253
0%
0*
#254
b1 '
0$
0)
1%
1*
#255
0%
0*
#256
b10 '
1%
1*
#257
0%
0*
#258
b0 '
1$
1)
1%
1*
#259
0%
0*
#260
b1 '
0$
0)
1%
1*
#261
0%
0*
#262
b10 '
1%
1*
#263
0%
0*
#264
b0 '
1$
1)
1%
1*
#265
0%
0*
#266
b1 '
0$
0)
1%
1*
#267
0%
0*
#268
b10 '
1%
1*
#269
0%
0*
#270
b0 '
1$
1)
1%
1*
#271
0%
0*
#272
b1 '
0$
0)
1%
1*
#273
0%
0*
#274
b10 '
1%
1*
#275
0%
0*
#276
b0 '
1$
1)
1%
1*
#277
0%
0*
#278
b1 '
0$
0)
1%
1*
#279
0%
0*
#280
b10 '
1%
1*
#281
0%
0*
#282
b0 '
1$
1)
1%
1*
#283
0%
0*
#284
b1 '
0$
0)
1%
1*
#285
0%
0*
#286
b10 '
1%
1*
#287
0%
0*
#288
b0 '
1$
1)
1%
1*
#289
0%
0*
#290
b1 '
0$
0)
1%
1*
#291
0%
0*
#292
b10 '
1%
1*
#293
0%
0*
#294
b0 '
1$
1)
1%
1*
#295
0%
0*
#296
b1 '
0$
0)
1%
1*
#297
0%
0*
#298
b10 '
1%
1*
#299
0%
0*
#300
b0 '
1$
1)
1%
1*
#301
0%
0*
#302
b1 '
0$
0)
1%
1*
#303
0%
0*
#304
b10 '
1%
1*
#305
0%
0*
#306
b0 '
1$
1)
1%
1*
#307
0%
0*
#308
b1 '
0$
0)
1%
1*
#309
0%
0*
#310
b10 '
1%
1*
#311
0%
0*
#312
b0 '
1$
1)
1%
1*
#313
0%
0*
#314
b1 '
0$
0)
1%
1*
#315
0%
0*
#316
b10 '
1%
1*
#317
0%
0*
#318
b0 '
1$
1)
1%
1*
#319
0%
0*
#320
b1 '
0$
0)
1%
1*
#321
0%
0*
#322
b10 '
1%
1*
#323
0%
0*
#324
b0 '
1$
1)
1%
1*
#325
0%
0*
#326
b1 '
0$
0)
1%
1*
#327
0%
0*
#328
b10 '
1%
1*
#329
0%
0*
#330
b0 '
1$
1)
1%
1*
#331
0%
0*
#332
b1 '
0$
0)
1%
1*
#333
0%
0*
#334
b10 '
1%
1*
#335
0%
0*
#336
b0 '
1$
1)
1%
1*
#337
0%
0*
#338
b1 '
0$
0)
1%
1*
#339
0%
0*
#340
b10 '
1%
1*
#341
0%
0*
#342
b0 '
1$
1)
1%
1*
#343
0%
0*
#344
b1 '
0$
0)
1%
1*
#345
0%
0*
#346
b10 '
1%
1*
#347
0%
0*
#348
b0 '
1$
1)
1%
1*
#349
0%
0*
#350
b1 '
0$
0)
1%
1*
#351
0%
0*
#352
b10 '
1%
1*
#353
0%
0*
#354
b0 '
1$
1)
1%
1*
#355
0%
0*
#356
b1 '
0$
0)
1%
1*
#357
0%
0*
#358
b10 '
1%
1*
#359
0%
0*
#360
b0 '
1$
1)
1%
1*
#361
0%
0*
#362
b1 '
0$
0)
1%
1*
#363
0%
0*
#364
b10 '
1%
1*
#365
0%
0*
#366
b0 '
1$
1)
1%
1*
#367
0%
0*
#368
b1 '
0$
0)
1%
1*
#369
0%
0*
#370
b10 '
1%
1*
#371
0%
0*
#372
b0 '
1$
1)
1%
1*
#373
0%
0*
#374
b1 '
0$
0)
1%
1*
#375
0%
0*
#376
b10 '
1%
1*
#377
0%
0*
#378
b0 '
1$
1)
1%
1*
#379
0%
0*
#380
b1 '
0$
0)
1%
1*
#381
0%
0*
#382
b10 '
1%
1*
#383
0%
0*
#384
b0 '
1$
1)
1%
1*
#385
0%
0*
#386
b1 '
0$
0)
1%
1*
#387
0%
0*
#388
b10 '
1%
1*
#389
0%
0*
#390
b0 '
1$
1)
1%
1*
#391
0%
0*
#392
b1 '
0$
0)
1%
1*
#393
0%
0*
#394
b10 '
1%
1*
#395
0%
0*
#396
b0 '
1$
1)
1%
1*
#397
0%
0*
#398
b1 '
0$
0)
1%
1*
#399
0%
0*
#400
b10 '
1%
1*
