HW/RTL/01BLUETOOTH/Version_02/02 verilog/BLUETOOTH/TX/Divisor_Frecuencia.v
module Divisor_Frecuencia #(
              parameter   fi     = 100000000,           
              parameter   fs	 = 76000     //flckout=((0.238*fs)/500000)MHZ fs=Fout*500000/0.238
  )(input clk_in, output reg clk_div, input reset);

reg [15:0] count;

always @(posedge  clk_in)
    begin
	if (reset) begin
		count <=count-1;
		if (count==0)begin
			clk_div <=~clk_div;
			count <= fi/fs;
		end
	end
	else begin
		count <= fi/fs;
		clk_div <=0;
			
	end	
end
endmodule

HW/RTL/01BLUETOOTH/Version_02/02 verilog/BLUETOOTH/TX/transmision.v
module transmision (input rw,
            input clk_in,
            input reset, 
            input wire [7:0] din, 
            output busy, 
            output done, 
            output reg tx);



 wire clk_div;
Divisor_Frecuencia div(.clk_in(clk_in), .clk_div(clk_div), .reset(reset));

parameter count = 8;
reg [2:0] counter = 0; //registro para llevar el conteo

initial begin
	tx = 1'b1;
end

parameter STATE_IDLE	= 2'b00;
parameter STATE_START	= 2'b01;
parameter STATE_DATA	= 2'b10;
parameter STATE_STOP	= 2'b11;

reg [7:0] data = 8'b11111111;
reg [2:0] bitpos = 0;
reg [1:0] state = STATE_IDLE;

always @(posedge clk_div) begin
	case (state)
	STATE_IDLE: begin
		if (rw) begin
			state <= STATE_START;
			data <= din;
			bitpos <= 0;
		end
	end
	STATE_START: begin
		if (clk_div) begin
			tx <= 1'b0;
			state <= STATE_DATA;
		end
	end
	STATE_DATA: begin
		if (clk_div) begin
			if (bitpos == count-1)begin
				tx<=data[bitpos]; 
				state <= STATE_STOP;
			end
			else begin
				tx<=data[bitpos]; //hacer este cambio cuando todo funcine :v 
				bitpos <= bitpos + 1;
			end
			//tx <= data[bitpos];
		end
	end
	STATE_STOP: begin
		if (clk_div) begin
			tx <= 1'b1;
			state <= STATE_IDLE;
		end
	end
	default: begin
		tx <= 1'b1;
		state <= STATE_IDLE;
	end
	endcase
end

assign busy = (state != STATE_IDLE);
assign done = (state == STATE_STOP);

endmodule

HW/RTL/01BLUETOOTH/Version_02/02 verilog/BLUETOOTH/TX/transmision_TB.v
module transmision_TB;

//Registro para generar la señal de reloj
reg clk_in=0;
reg clk_div;
//wire clk_out;
reg rw = 0;
reg [7:0] din = 0;
reg reset;
wire busy;
wire done;
wire tx;//registro para llevar el conteo

//Instanciar transmision
transmision dut(.clk_in(clk_in),.rw(rw),.din(din),.busy(busy),.done(done),.tx(tx),.reset(reset));
initial clk_in=0;
//Generador de reloj fpga. Periodo 2 unidades
always #1 clk_in = ~clk_in;
initial begin
reset=1'b0;
#10
reset=1'b1;
end

initial begin
#20
rw = 1;
din = 8'b00110011;
#4000
rw = 0;
end

//-- Proceso al inicio
initial begin

  //-- Fichero donde almacenar los resultados
  $dumpfile("transmision_TB.vcd");
  $dumpvars(0, transmision_TB);

  #100000 $display("FIN de la simulacion");
  $finish;
end
endmodule

HW/RTL/01BLUETOOTH/Version_02/02 verilog/BLUETOOTH/TX/simulation/transmision_TB.vcd
$date
	Fri Nov  3 07:24:15 2017
$end
$version
	Icarus Verilog
$end
$timescale
	1s
$end
$scope module transmision_TB $end
$var wire 1 ! busy $end
$var wire 1 " done $end
$var wire 1 # tx $end
$var reg 1 $ clk_in $end
$var reg 8 % din [7:0] $end
$var reg 1 & reset $end
$var reg 1 ' rw $end
$scope module dut $end
$var wire 1 ! busy $end
$var wire 1 ( clk_div $end
$var wire 1 ) clk_in $end
$var wire 8 * din [7:0] $end
$var wire 1 " done $end
$var wire 1 + reset $end
$var wire 1 , rw $end
$var reg 3 - bitpos [2:0] $end
$var reg 3 . counter [2:0] $end
$var reg 8 / data [7:0] $end
$var reg 2 0 state [1:0] $end
$var reg 1 1 tx $end
$scope module div $end
$var wire 1 ) clk_in $end
$var wire 1 + reset $end
$var reg 1 2 clk_div $end
$var reg 16 3 count [15:0] $end
$upscope $end
$upscope $end
$upscope $end
$enddefinitions $end
#0
$dumpvars
bx 3
x2
11
b0 0
b11111111 /
b0 .
b0 -
0,
0+
b0 *
0)
x(
0'
0&
b0 %
0$
1#
0"
0!
$end
#1
02
0(
b10100100011 3
1$
1)
#2
0$
0)
#3
1$
1)
#4
0$
0)
#5
1$
1)
#6
0$
0)
#7
1$
1)
#8
0$
0)
#9
1$
1)
#10
0$
0)
1&
1+
#11
b10100100010 3
1$
1)
#12
0$
0)
#13
b10100100001 3
1$
1)
#14
0$
0)
#15
b10100100000 3
1$
1)
#16
0$
0)
#17
b10100011111 3
1$
1)
#18
0$
0)
#19
b10100011110 3
1$
1)
#20
0$
0)
b110011 %
b110011 *
1'
1,
#21
b10100011101 3
1$
1)
#22
0$
0)
#23
b10100011100 3
1$
1)
#24
0$
0)
#25
b10100011011 3
1$
1)
#26
0$
0)
#27
b10100011010 3
1$
1)
#28
0$
0)
#29
b10100011001 3
1$
1)
#30
0$
0)
#31
b10100011000 3
1$
1)
#32
0$
0)
#33
b10100010111 3
1$
1)
#34
0$
0)
#35
b10100010110 3
1$
1)
#36
0$
0)
#37
b10100010101 3
1$
1)
#38
0$
0)
#39
b10100010100 3
1$
1)
#40
0$
0)
#41
b10100010011 3
1$
1)
#42
0$
0)
#43
b10100010010 3
1$
1)
#44
0$
0)
#45
b10100010001 3
1$
1)
#46
0$
0)
#47
b10100010000 3
1$
1)
#48
0$
0)
#49
b10100001111 3
1$
1)
#50
0$
0)
#51
b10100001110 3
1$
1)
#52
0$
0)
#53
b10100001101 3
1$
1)
#54
0$
0)
#55
b10100001100 3
1$
1)
#56
0$
0)
#57
b10100001011 3
1$
1)
#58
0$
0)
#59
b10100001010 3
1$
1)
#60
0$
0)
#61
b10100001001 3
1$
1)
#62
0$
0)
#63
b10100001000 3
1$
1)
#64
0$
0)
#65
b10100000111 3
1$
1)
#66
0$
0)
#67
b10100000110 3
1$
1)
#68
0$
0)
#69
b10100000101 3
1$
1)
#70
0$
0)
#71
b10100000100 3
1$
1)
#72
0$
0)
#73
b10100000011 3
1$
1)
#74
0$
0)
#75
b10100000010 3
1$
1)
#76
0$
0)
#77
b10100000001 3
1$
1)
#78
0$
0)
#79
b10100000000 3
1$
1)
#80
0$
0)
#81
b10011111111 3
1$
1)
#82
0$
0)
#83
b10011111110 3
1$
1)
#84
0$
0)
#85
b10011111101 3
1$
1)
#86
0$
0)
#87
b10011111100 3
1$
1)
#88
0$
0)
#89
b10011111011 3
1$
1)
#90
0$
0)
#91
b10011111010 3
1$
1)
#92
0$
0)
#93
b10011111001 3
1$
1)
#94
0$
0)
#95
b10011111000 3
1$
1)
#96
0$
0)
#97
b10011110111 3
1$
1)
#98
0$
0)
#99
b10011110110 3
1$
1)
#100
0$
0)
#101
b10011110101 3
1$
1)
#102
0$
0)
#103
b10011110100 3
1$
1)
#104
0$
0)
#105
b10011110011 3
1$
1)
#106
0$
0)
#107
b10011110010 3
1$
1)
#108
0$
0)
#109
b10011110001 3
1$
1)
#110
0$
0)
#111
b10011110000 3
1$
1)
#112
0$
0)
#113
b10011101111 3
1$
1)
#114
0$
0)
#115
b10011101110 3
1$
1)
#116
0$
0)
#117
b10011101101 3
1$
1)
#118
0$
0)
#119
b10011101100 3
1$
1)
#120
0$
0)
#121
b10011101011 3
1$
1)
#122
0$
0)
#123
b10011101010 3
1$
1)
#124
0$
0)
#125
b10011101001 3
1$
1)
#126
0$
0)
#127
b10011101000 3
1$
1)
#128
0$
0)
#129
b10011100111 3
1$
1)
#130
0$
0)
#131
b10011100110 3
1$
1)
#132
0$
0)
#133
b10011100101 3
1$
1)
#134
0$
0)
#135
b10011100100 3
1$
1)
#136
0$
0)
#137
b10011100011 3
1$
1)
#138
0$
0)
#139
b10011100010 3
1$
1)
#140
0$
0)
#141
b10011100001 3
1$
1)
#142
0$
0)
#143
b10011100000 3
1$
1)
#144
0$
0)
#145
b10011011111 3
1$
1)
#146
0$
0)
#147
b10011011110 3
1$
1)
#148
0$
0)
#149
b10011011101 3
1$
1)
#150
0$
0)
#151
b10011011100 3
1$
1)
#152
0$
0)
#153
b10011011011 3
1$
1)
#154
0$
0)
#155
b10011011010 3
1$
1)
#156
0$
0)
#157
b10011011001 3
1$
1)
#158
0$
0)
#159
b10011011000 3
1$
1)
#160
0$
0)
#161
b10011010111 3
1$
1)
#162
0$
0)
#163
b10011010110 3
1$
1)
#164
0$
0)
#165
b10011010101 3
1$
1)
#166
0$
0)
#167
b10011010100 3
1$
1)
#168
0$
0)
#169
b10011010011 3
1$
1)
#170
0$
0)
#171
b10011010010 3
1$
1)
#172
0$
0)
#173
b10011010001 3
1$
1)
#174
0$
0)
#175
b10011010000 3
1$
1)
#176
0$
0)
#177
b10011001111 3
1$
1)
#178
0$
0)
#179
b10011001110 3
1$
1)
#180
0$
0)
#181
b10011001101 3
1$
1)
#182
0$
0)
#183
b10011001100 3
1$
1)
#184
0$
0)
#185
b10011001011 3
1$
1)
#186
0$
0)
#187
b10011001010 3
1$
1)
#188
0$
0)
#189
b10011001001 3
1$
1)
#190
0$
0)
#191
b10011001000 3
1$
1)
#192
0$
0)
#193
b10011000111 3
1$
1)
#194
0$
0)
#195
b10011000110 3
1$
1)
#196
0$
0)
#197
b10011000101 3
1$
1)
#198
0$
0)
#199
b10011000100 3
1$
1)
#200
0$
0)
#201
b10011000011 3
1$
1)
#202
0$
0)
#203
b10011000010 3
1$
1)
#204
0$
0)
#205
b10011000001 3
1$
1)
#206
0$
0)
#207
b10011000000 3
1$
1)
#208
0$
0)
#209
b10010111111 3
1$
1)
#210
0$
0)
#211
b10010111110 3
1$
1)
#212
0$
0)
#213
b10010111101 3
1$
1)
#214
0$
0)
#215
b10010111100 3
1$
1)
#216
0$
0)
#217
b10010111011 3
1$
1)
#218
0$
0)
#219
b10010111010 3
1$
1)
#220
0$
0)
#221
b10010111001 3
1$
1)
#222
0$
0)
#223
b10010111000 3
1$
1)
#224
0$
0)
#225
b10010110111 3
1$
1)
#226
0$
0)
#227
b10010110110 3
1$
1)
#228
0$
0)
#229
b10010110101 3
1$
1)
#230
0$
0)
#231
b10010110100 3
1$
1)
#232
0$
0)
#233
b10010110011 3
1$
1)
#234
0$
0)
#235
b10010110010 3
1$
1)
#236
0$
0)
#237
b10010110001 3
1$
1)
#238
0$
0)
#239
b10010110000 3
1$
1)
#240
0$
0)
#241
b10010101111 3
1$
1)
#242
0$
0)
#243
b10010101110 3
1$
1)
#244
0$
0)
#245
b10010101101 3
1$
1)
#246
0$
0)
#247
b10010101100 3
1$
1)
#248
0$
0)
#249
b10010101011 3
1$
1)
#250
0$
0)
#251
b10010101010 3
1$
1)
#252
0$
0)
#253
b10010101001 3
1$
1)
#254
0$
0)
#255
b10010101000 3
1$
1)
#256
0$
0)
#257
b10010100111 3
1$
1)
#258
0$
0)
#259
b10010100110 3
1$
1)
#260
0$
0)
#261
b10010100101 3
1$
1)
#262
0$
0)
#263
b10010100100 3
1$
1)
#264
0$
0)
#265
b10010100011 3
1$
1)
#266
0$
0)
#267
b10010100010 3
1$
1)
#268
0$
0)
#269
b10010100001 3
1$
1)
#270
0$
0)
#271
b10010100000 3
1$
1)
#272
0$
0)
#273
b10010011111 3
1$
1)
#274
0$
0)
#275
b10010011110 3
1$
1)
#276
0$
0)
#277
b10010011101 3
1$
1)
#278
0$
0)
#279
b10010011100 3
1$
1)
#280
0$
0)
#281
b10010011011 3
1$
1)
#282
0$
0)
#283
b10010011010 3
1$
1)
#284
0$
0)
#285
b10010011001 3
1$
1)
#286
0$
0)
#287
b10010011000 3
1$
1)
#288
0$
0)
#289
b10010010111 3
1$
1)
#290
0$
0)
#291
b10010010110 3
1$
1)
#292
0$
0)
#293
b10010010101 3
1$
1)
#294
0$
0)
#295
b10010010100 3
1$
1)
#296
0$
0)
#297
b10010010011 3
1$
1)
#298
0$
0)
#299
b10010010010 3
1$
1)
#300
0$
0)
#301
b10010010001 3
1$
1)
#302
0$
0)
#303
b10010010000 3
1$
1)
#304
0$
0)
#305
b10010001111 3
1$
1)
#306
0$
0)
#307
b10010001110 3
1$
1)
#308
0$
0)
#309
b10010001101 3
1$
1)
#310
0$
0)
#311
b10010001100 3
1$
1)
#312
0$
0)
#313
b10010001011 3
1$
1)
#314
0$
0)
#315
b10010001010 3
1$
1)
#316
0$
0)
#317
b10010001001 3
1$
1)
#318
0$
0)
#319
b10010001000 3
1$
1)
#320
0$
0)
#321
b10010000111 3
1$
1)
#322
0$
0)
#323
b10010000110 3
1$
1)
#324
0$
0)
#325
b10010000101 3
1$
1)
#326
0$
0)
#327
b10010000100 3
1$
1)
#328
0$
0)
#329
b10010000011 3
1$
1)
#330
0$
0)
#331
b10010000010 3
1$
1)
#332
0$
0)
#333
b10010000001 3
1$
1)
#334
0$
0)
#335
b10010000000 3
1$
1)
#336
0$
0)
#337
b10001111111 3
1$
1)
#338
0$
0)
#339
b10001111110 3
1$
1)
#340
0$
0)
#341
b10001111101 3
1$
1)
#342
0$
0)
#343
b10001111100 3
1$
1)
#344
0$
0)
#345
b10001111011 3
1$
1)
#346
0$
0)
#347
b10001111010 3
1$
1)
#348
0$
0)
#349
b10001111001 3
1$
1)
#350
0$
0)
#351
b10001111000 3
1$
1)
#352
0$
0)
#353
b10001110111 3
1$
1)
#354
0$
0)
#355
b10001110110 3
1$
1)
#356
0$
0)
#357
b10001110101 3
1$
1)
#358
0$
0)
#359
b10001110100 3
1$
1)
#360
0$
0)
#361
b10001110011 3
1$
1)
#362
0$
0)
#363
b10001110010 3
1$
1)
#364
0$
0)
#365
b10001110001 3
1$
1)
#366
0$
0)
#367
b10001110000 3
1$
1)
#368
0$
0)
#369
b10001101111 3
1$
1)
#370
0$
0)
#371
b10001101110 3
1$
1)
#372
0$
0)
#373
b10001101101 3
1$
1)
#374
0$
0)
#375
b10001101100 3
1$
1)
#376
0$
0)
#377
b10001101011 3
1$
1)
#378
0$
0)
#379
b10001101010 3
1$
1)
#380
0$
0)
#381
b10001101001 3
1$
1)
#382
0$
0)
#383
b10001101000 3
1$
1)
#384
0$
0)
#385
b10001100111 3
1$
1)
#386
0$
0)
#387
b10001100110 3
1$
1)
#388
0$
0)
#389
b10001100101 3
1$
1)
#390
0$
0)
#391
b10001100100 3
1$
1)
#392
0$
0)
#393
b10001100011 3
1$
1)
#394
0$
0)
#395
b10001100010 3
1$
1)
#396
0$
0)
#397
b10001100001 3
1$
1)
#398
0$
0)
#399
b10001100000 3
1$
1)
#400
0$
0)
#401
b10001011111 3
1$
1)
#402
0$
0)
#403
b10001011110 3
1$
1)
#404
0$
0)
#405
b10001011101 3
1$
1)
#406
0$
0)
#407
b10001011100 3
1$
1)
#408
0$
0)
#409
b10001011011 3
1$
1)
#410
0$
0)
#411
b10001011010 3
1$
1)
#412
0$
0)
#413
b10001011001 3
1$
1)
#414
0$
0)
#415
b10001011000 3
1$
1)
#416
0$
0)
#417
b10001010111 3
1$
1)
#418
0$
0)
#419
b10001010110 3
1$
1)
#420
0$
0)
#421
b10001010101 3
1$
1)
#422
0$
0)
#423
b10001010100 3
1$
1)
#424
0$
0)
#425
b10001010011 3
1$
1)
#426
0$
0)
#427
b10001010010 3
1$
1)
#428
0$
0)
#429
b10001010001 3
1$
1)
#430
0$
0)
#431
b10001010000 3
1$
1)
#432
0$
0)
#433
b10001001111 3
1$
1)
#434
0$
0)
#435
b10001001110 3
1$
1)
#436
0$
0)
#437
b10001001101 3
1$
1)
#438
0$
0)
#439
b10001001100 3
1$
1)
#440
0$
0)
#441
b10001001011 3
1$
1)
#442
0$
0)
#443
b10001001010 3
1$
1)
#444
0$
0)
#445
b10001001001 3
1$
1)
#446
0$
0)
#447
b10001001000 3
1$
1)
#448
0$
0)
#449
b10001000111 3
1$
1)
#450
0$
0)
#451
b10001000110 3
1$
1)
#452
0$
0)
#453
b10001000101 3
1$
1)
#454
0$
0)
#455
b10001000100 3
1$
1)
#456
0$
0)
#457
b10001000011 3
1$
1)
#458
0$
0)
#459
b10001000010 3
1$
1)
#460
0$
0)
#461
b10001000001 3
1$
1)
#462
0$
0)
#463
b10001000000 3
1$
1)
#464
0$
0)
#465
b10000111111 3
1$
1)
#466
0$
0)
#467
b10000111110 3
1$
1)
#468
0$
0)
#469
b10000111101 3
1$
1)
#470
0$
0)
#471
b10000111100 3
1$
1)
#472
0$
0)
#473
b10000111011 3
1$
1)
#474
0$
0)
#475
b10000111010 3
1$
1)
#476
0$
0)
#477
b10000111001 3
1$
1)
#478
0$
0)
#479
b10000111000 3
1$
1)
#480
0$
0)
#481
b10000110111 3
1$
1)
#482
0$
0)
#483
b10000110110 3
1$
1)
#484
0$
0)
#485
b10000110101 3
1$
1)
#486
0$
0)
#487
b10000110100 3
1$
1)
#488
0$
0)
#489
b10000110011 3
1$
1)
#490
0$
0)
#491
b10000110010 3
1$
1)
#492
0$
0)
#493
b10000110001 3
1$
1)
#494
0$
0)
#495
b10000110000 3
1$
1)
#496
0$
0)
#497
b10000101111 3
1$
1)
#498
0$
0)
#499
b10000101110 3
1$
1)
#500
0$
0)
#501
b10000101101 3
1$
1)
#502
0$
0)
#503
b10000101100 3
1$
1)
#504
0$
0)
#505
b10000101011 3
1$
1)
#506
0$
0)
#507
b10000101010 3
1$
1)
#508
0$
0)
#509
b10000101001 3
1$
1)
#510
0$
0)
#511
b10000101000 3
1$
1)
#512
0$
0)
#513
b10000100111 3
1$
1)
#514
0$
0)
#515
b10000100110 3
1$
1)
#516
0$
0)
#517
b10000100101 3
1$
1)
#518
0$
0)
#519
b10000100100 3
1$
1)
#520
0$
0)
#521
b10000100011 3
1$
1)
#522
0$
0)
#523
b10000100010 3
1$
1)
#524
0$
0)
#525
b10000100001 3
1$
1)
#526
0$
0)
#527
b10000100000 3
1$
1)
#528
0$
0)
#529
b10000011111 3
1$
1)
#530
0$
0)
#531
b10000011110 3
1$
1)
#532
0$
0)
#533
b10000011101 3
1$
1)
#534
0$
0)
#535
b10000011100 3
1$
1)
#536
0$
0)
#537
b10000011011 3
1$
1)
#538
0$
0)
#539
b10000011010 3
1$
1)
#540
0$
0)
#541
b10000011001 3
1$
1)
#542
0$
0)
#543
b10000011000 3
1$
1)
#544
0$
0)
#545
b10000010111 3
1$
1)
#546
0$
0)
#547
b10000010110 3
1$
1)
#548
0$
0)
#549
b10000010101 3
1$
1)
#550
0$
0)
#551
b10000010100 3
1$
1)
#552
0$
0)
#553
b10000010011 3
1$
1)
#554
0$
0)
#555
b10000010010 3
1$
1)
#556
0$
0)
#557
b10000010001 3
1$
1)
#558
0$
0)
#559
b10000010000 3
1$
1)
#560
0$
0)
#561
b10000001111 3
1$
1)
#562
0$
0)
#563
b10000001110 3
1$
1)
#564
0$
0)
#565
b10000001101 3
1$
1)
#566
0$
0)
#567
b10000001100 3
1$
1)
#568
0$
0)
#569
b10000001011 3
1$
1)
#570
0$
0)
#571
b10000001010 3
1$
1)
#572
0$
0)
#573
b10000001001 3
1$
1)
#574
0$
0)
#575
b10000001000 3
1$
1)
#576
0$
0)
#577
b10000000111 3
1$
1)
#578
0$
0)
#579
b10000000110 3
1$
1)
#580
0$
0)
#581
b10000000101 3
1$
1)
#582
0$
0)
#583
b10000000100 3
1$
1)
#584
0$
0)
#585
b10000000011 3
1$
1)
#586
0$
0)
#587
b10000000010 3
1$
1)
#588
0$
0)
#589
b10000000001 3
1$
1)
#590
0$
0)
#591
b10000000000 3
1$
1)
#592
0$
0)
#593
b1111111111 3
1$
1)
#594
0$
0)
#595
b1111111110 3
1$
1)
#596
0$
0)
#597
b1111111101 3
1$
1)
#598
0$
0)
#599
b1111111100 3
1$
1)
#600
0$
0)
#601
b1111111011 3
1$
1)
#602
0$
0)
#603
b1111111010 3
1$
1)
#604
0$
0)
#605
b1111111001 3
1$
1)
#606
0$
0)
#607
b1111111000 3
1$
1)
#608
0$
0)
#609
b1111110111 3
1$
1)
#610
0$
0)
#611
b1111110110 3
1$
1)
#612
0$
0)
#613
b1111110101 3
1$
1)
#614
0$
0)
#615
b1111110100 3
1$
1)
#616
0$
0)
#617
b1111110011 3
1$
1)
#618
0$
0)
#619
b1111110010 3
1$
1)
#620
0$
0)
#621
b1111110001 3
1$
1)
#622
0$
0)
#623
b1111110000 3
1$
1)
#624
0$
0)
#625
b1111101111 3
1$
1)
#626
0$
0)
#627
b1111101110 3
1$
1)
#628
0$
0)
#629
b1111101101 3
1$
1)
#630
0$
0)
#631
b1111101100 3
1$
1)
#632
0$
0)
#633
b1111101011 3
1$
1)
#634
0$
0)
#635
b1111101010 3
1$
1)
#636
0$
0)
#637
b1111101001 3
1$
1)
#638
0$
0)
#639
b1111101000 3
1$
1)
#640
0$
0)
#641
b1111100111 3
1$
1)
#642
0$
0)
#643
b1111100110 3
1$
1)
#644
0$
0)
#645
b1111100101 3
1$
1)
#646
0$
0)
#647
b1111100100 3
1$
1)
#648
0$
0)
#649
b1111100011 3
1$
1)
#650
0$
0)
#651
b1111100010 3
1$
1)
#652
0$
0)
#653
b1111100001 3
1$
1)
#654
0$
0)
#655
b1111100000 3
1$
1)
#656
0$
0)
#657
b1111011111 3
1$
1)
#658
0$
0)
#659
b1111011110 3
1$
1)
#660
0$
0)
#661
b1111011101 3
1$
1)
#662
0$
0)
#663
b1111011100 3
1$
1)
#664
0$
0)
#665
b1111011011 3
1$
1)
#666
0$
0)
#667
b1111011010 3
1$
1)
#668
0$
0)
#669
b1111011001 3
1$
1)
#670
0$
0)
#671
b1111011000 3
1$
1)
#672
0$
0)
#673
b1111010111 3
1$
1)
#674
0$
0)
#675
b1111010110 3
1$
1)
#676
0$
0)
#677
b1111010101 3
1$
1)
#678
0$
0)
#679
b1111010100 3
1$
1)
#680
0$
0)
#681
b1111010011 3
1$
1)
#682
0$
0)
#683
b1111010010 3
1$
1)
#684
0$
0)
#685
b1111010001 3
1$
1)
#686
0$
0)
#687
b1111010000 3
1$
1)
#688
0$
0)
#689
b1111001111 3
1$
1)
#690
0$
0)
#691
b1111001110 3
1$
1)
#692
0$
0)
#693
b1111001101 3
1$
1)
#694
0$
0)
#695
b1111001100 3
1$
1)
#696
0$
0)
#697
b1111001011 3
1$
1)
#698
0$
0)
#699
b1111001010 3
1$
1)
#700
0$
0)
#701
b1111001001 3
1$
1)
#702
0$
0)
#703
b1111001000 3
1$
1)
#704
0$
0)
#705
b1111000111 3
1$
1)
#706
0$
0)
#707
b1111000110 3
1$
1)
#708
0$
0)
#709
b1111000101 3
1$
1)
#710
0$
0)
#711
b1111000100 3
1$
1)
#712
0$
0)
#713
b1111000011 3
1$
1)
#714
0$
0)
#715
b1111000010 3
1$
1)
#716
0$
0)
#717
b1111000001 3
1$
1)
#718
0$
0)
#719
b1111000000 3
1$
1)
#720
0$
0)
#721
b1110111111 3
1$
1)
#722
0$
0)
#723
b1110111110 3
1$
1)
#724
0$
0)
#725
b1110111101 3
1$
1)
#726
0$
0)
#727
b1110111100 3
1$
1)
#728
0$
0)
#729
b1110111011 3
1$
1)
#730
0$
0)
#731
b1110111010 3
1$
1)
#732
0$
0)
#733
b1110111001 3
1$
1)
#734
0$
0)
#735
b1110111000 3
1$
1)
#736
0$
0)
#737
b1110110111 3
1$
1)
#738
0$
0)
#739
b1110110110 3
1$
1)
#740
0$
0)
#741
b1110110101 3
1$
1)
#742
0$
0)
#743
b1110110100 3
1$
1)
#744
0$
0)
#745
b1110110011 3
1$
1)
#746
0$
0)
#747
b1110110010 3
1$
1)
#748
0$
0)
#749
b1110110001 3
1$
1)
#750
0$
0)
#751
b1110110000 3
1$
1)
#752
0$
0)
#753
b1110101111 3
1$
1)
#754
0$
0)
#755
b1110101110 3
1$
1)
#756
0$
0)
#757
b1110101101 3
1$
1)
#758
0$
0)
#759
b1110101100 3
1$
1)
#760
0$
0)
#761
b1110101011 3
1$
1)
#762
0$
0)
#763
b1110101010 3
1$
1)
#764
0$
0)
#765
b1110101001 3
1$
1)
#766
0$
0)
#767
b1110101000 3
1$
1)
#768
0$
0)
#769
b1110100111 3
1$
1)
#770
0$
0)
#771
b1110100110 3
1$
1)
#772
0$
0)
#773
b1110100101 3
1$
1)
#774
0$
0)
#775
b1110100100 3
1$
1)
#776
0$
0)
#777
b1110100011 3
1$
1)
#778
0$
0)
#779
b1110100010 3
1$
1)
#780
0$
0)
#781
b1110100001 3
1$
1)
#782
0$
0)
#783
b1110100000 3
1$
1)
#784
0$
0)
#785
b1110011111 3
1$
1)
#786
0$
0)
#787
b1110011110 3
1$
1)
#788
0$
0)
#789
b1110011101 3
1$
1)
#790
0$
0)
#791
b1110011100 3
1$
1)
#792
0$
0)
#793
b1110011011 3
1$
1)
#794
0$
0)
#795
b1110011010 3
1$
1)
#796
0$
0)
#797
b1110011001 3
1$
1)
#798
0$
0)
#799
b1110011000 3
1$
1)
#800
0$
0)
#801
b1110010111 3
1$
1)
#802
0$
0)
#803
b1110010110 3
1$
1)
#804
0$
0)
#805
b1110010101 3
1$
1)
#806
0$
0)
#807
b1110010100 3
1$
1)
#808
0$
0)
#809
b1110010011 3
1$
1)
#810
0$
0)
#811
b1110010010 3
1$
1)
#812
0$
0)
#813
b1110010001 3
1$
1)
#814
0$
0)
#815
b1110010000 3
1$
1)
#816
0$
0)
#817
b1110001111 3
1$
1)
#818
0$
0)
#819
b1110001110 3
1$
1)
#820
0$
0)
#821
b1110001101 3
1$
1)
#822
0$
0)
#823
b1110001100 3
1$
1)
#824
0$
0)
#825
b1110001011 3
1$
1)
#826
0$
0)
#827
b1110001010 3
1$
1)
#828
0$
0)
#829
b1110001001 3
1$
1)
#830
0$
0)
#831
b1110001000 3
1$
1)
#832
0$
0)
#833
b1110000111 3
1$
1)
#834
0$
0)
#835
b1110000110 3
1$
1)
#836
0$
0)
#837
b1110000101 3
1$
1)
#838
0$
0)
#839
b1110000100 3
1$
1)
#840
0$
0)
#841
b1110000011 3
1$
1)
#842
0$
0)
#843
b1110000010 3
1$
1)
#844
0$
0)
#845
b1110000001 3
1$
1)
#846
0$
0)
#847
b1110000000 3
1$
1)
#848
0$
0)
#849
b1101111111 3
1$
1)
#850
0$
0)
#851
b1101111110 3
1$
1)
#852
0$
0)
#853
b1101111101 3
1$
1)
#854
0$
0)
#855
b1101111100 3
1$
1)
#856
0$
0)
#857
b1101111011 3
1$
1)
#858
0$
0)
#859
b1101111010 3
1$
1)
#860
0$
0)
#861
b1101111001 3
1$
1)
#862
0$
0)
#863
b1101111000 3
1$
1)
#864
0$
0)
#865
b1101110111 3
1$
1)
#866
0$
0)
#867
b1101110110 3
1$
1)
#868
0$
0)
#869
b1101110101 3
1$
1)
#870
0$
0)
#871
b1101110100 3
1$
1)
#872
0$
0)
#873
b1101110011 3
1$
1)
#874
0$
0)
#875
b1101110010 3
1$
1)
#876
0$
0)
#877
b1101110001 3
1$
1)
#878
0$
0)
#879
b1101110000 3
1$
1)
#880
0$
0)
#881
b1101101111 3
1$
1)
#882
0$
0)
#883
b1101101110 3
1$
1)
#884
0$
0)
#885
b1101101101 3
1$
1)
#886
0$
0)
#887
b1101101100 3
1$
1)
#888
0$
0)
#889
b1101101011 3
1$
1)
#890
0$
0)
#891
b1101101010 3
1$
1)
#892
0$
0)
#893
b1101101001 3
1$
1)
#894
0$
0)
#895
b1101101000 3
1$
1)
#896
0$
0)
#897
b1101100111 3
1$
1)
#898
0$
0)
#899
b1101100110 3
1$
1)
#900
0$
0)
#901
b1101100101 3
1$
1)
#902
0$
0)
#903
b1101100100 3
1$
1)
#904
0$
0)
#905
b1101100011 3
1$
1)
#906
0$
0)
#907
b1101100010 3
1$
1)
#908
0$
0)
#909
b1101100001 3
1$
1)
#910
0$
0)
#911
b1101100000 3
1$
1)
#912
0$
0)
#913
b1101011111 3
1$
1)
#914
0$
0)
#915
b1101011110 3
1$
1)
#916
0$
0)
#917
b1101011101 3
1$
1)
#918
0$
0)
#919
b1101011100 3
1$
1)
#920
0$
0)
#921
b1101011011 3
1$
1)
#922
0$
0)
#923
b1101011010 3
1$
1)
#924
0$
0)
#925
b1101011001 3
1$
1)
#926
0$
0)
#927
b1101011000 3
1$
1)
#928
0$
0)
#929
b1101010111 3
1$
1)
#930
0$
0)
#931
b1101010110 3
1$
1)
#932
0$
0)
#933
b1101010101 3
1$
1)
#934
0$
0)
#935
b1101010100 3
1$
1)
#936
0$
0)
#937
b1101010011 3
1$
1)
#938
0$
0)
#939
b1101010010 3
1$
1)
#940
0$
0)
#941
b1101010001 3
1$
1)
#942
0$
0)
#943
b1101010000 3
1$
1)
#944
0$
0)
#945
b1101001111 3
1$
1)
#946
0$
0)
#947
b1101001110 3
1$
1)
#948
0$
0)
#949
b1101001101 3
1$
1)
#950
0$
0)
#951
b1101001100 3
1$
1)
#952
0$
0)
#953
b1101001011 3
1$
1)
#954
0$
0)
#955
b1101001010 3
1$
1)
#956
0$
0)
#957
b1101001001 3
1$
1)
#958
0$
0)
#959
b1101001000 3
1$
1)
#960
0$
0)
#961
b1101000111 3
1$
1)
#962
0$
0)
#963
b1101000110 3
1$
1)
#964
0$
0)
#965
b1101000101 3
1$
1)
#966
0$
0)
#967
b1101000100 3
1$
1)
#968
0$
0)
#969
b1101000011 3
1$
1)
#970
0$
0)
#971
b1101000010 3
1$
1)
#972
0$
0)
#973
b1101000001 3
1$
1)
#974
0$
0)
#975
b1101000000 3
1$
1)
#976
0$
0)
#977
b1100111111 3
1$
1)
#978
0$
0)
#979
b1100111110 3
1$
1)
#980
0$
0)
#981
b1100111101 3
1$
1)
#982
0$
0)
#983
b1100111100 3
1$
1)
#984
0$
0)
#985
b1100111011 3
1$
1)
#986
0$
0)
#987
b1100111010 3
1$
1)
#988
0$
0)
#989
b1100111001 3
1$
1)
#990
0$
0)
#991
b1100111000 3
1$
1)
#992
0$
0)
#993
b1100110111 3
1$
1)
#994
0$
0)
