HW/RTL/06PCM-AUDIO-MICROFONO/Version_01/02 verilog/Micled/div_freq.v
module div_freq #(
              parameter   fi     = 100000000,           
              parameter   fs	 = 25210.084034        //flckout=((0.238*fs)/500000)MHZ fs=Fout*500000/0.238
  )(input clk, output reg clkout,input reset, output reg led);



initial led=0;

reg [31:0] count;

always @(posedge  clk)
begin
	if (reset) begin
	led=1;
		count <=count-1;
		if (count==0)begin
			clkout <=~clkout;
			count <= fi/fs;
		end	

	end
	else begin
	led=0;
		count <= fi/fs;
		clkout <=0;
	end	
end


endmodule

HW/RTL/06PCM-AUDIO-MICROFONO/Version_01/02 verilog/Micled/microfono.v
module microfono
(
	output reg	ledlr,
	output 		ledres,
	output 	reg	ledc,
	input		clk,
	output		mclk,
	input		lr,
	output	reg	ws,
	input		dataint,
	input		reset,
	output reg [5:0] sregt//sregtl
	//output reg [5:0] sregtr


);
reg [0:127] count1=0;
reg [127:0] sregtc;
initial ws=0;

div_freq df(.clk(clk), .reset(reset),.clkout(mclk),.led(ledres));

always @(posedge  mclk)
begin

	if (reset)
	begin
		if(lr)
		begin
		ledlr=1;
			if (count1<=5)  /* guarda 5 bits */
			begin
		
			ledc=1;
			sregt<= {sregt[4:0],dataint};
			sregtc<= {sregtc[126:0],dataint};
			count1<=count1+1;
			end
		
			else 
			begin
				if(count1<=127)
				begin
				ledc=0;
				sregtc<= {sregtc[126:0],dataint};
				count1<=count1+1;
				end
				else
				begin
				count1<=0;
				end
			end
		end
		else
		begin
		ledlr=0;
		end
	end
	 
	
end
 
endmodule

HW/RTL/06PCM-AUDIO-MICROFONO/Version_01/02 verilog/Micled/microfono_TB.v

module microfono_TB;

reg dataint;
reg clk;
reg mclk;
reg ws;
reg reset;
reg lr;
microfono uut(.reset(reset),.dataint(dataint),.clk(clk),.lr(lr));

always
begin

clk =1'b1;
#2;
clk=1'b0;
#2;
end

initial
begin
reset =1'b0;
#10;
reset =1'b1;

end

initial
begin
lr =1'b0;
#10;
lr =1'b1;
#2000;
lr =1'b0;
#2000;
lr =1'b1;
end

initial begin
dataint = 1'b0;
#100 dataint = 1'b1;
#150 dataint = 1'b0;
#150 dataint = 1'b1;
#150 dataint = 1'b0;
#150 dataint = 1'b0;
#150 dataint = 1'b1;
#150 dataint = 1'b0;
#150 dataint = 1'b1;
end
	
initial begin: TEST_CASE
     $dumpfile("microfono_TB.vcd");
     $dumpvars(-1, uut);
     #(100000) $finish;
   end

endmodule //

HW/RTL/06PCM-AUDIO-MICROFONO/Version_01/02 verilog/Micled/simulation/microfono_TB.vcd
$date
	Thu Nov  2 19:39:11 2017
$end
$version
	Icarus Verilog
$end
$timescale
	1s
$end
$scope module microfono_TB $end
$scope module uut $end
$var wire 1 ! clk $end
$var wire 1 " dataint $end
$var wire 1 # lr $end
$var wire 1 $ reset $end
$var wire 1 % mclk $end
$var wire 1 & ledres $end
$var reg 128 ' count1 [0:127] $end
$var reg 1 ( ledc $end
$var reg 1 ) ledlr $end
$var reg 6 * sregt [5:0] $end
$var reg 128 + sregtc [127:0] $end
$var reg 1 , ws $end
$scope module df $end
$var wire 1 ! clk $end
$var wire 1 $ reset $end
$var reg 1 % clkout $end
$var reg 32 - count [31:0] $end
$var reg 1 & led $end
$upscope $end
$upscope $end
$upscope $end
$enddefinitions $end
#0
$dumpvars
b111101111111 -
0,
bx +
bx *
x)
x(
b0 '
0&
0%
0$
0#
0"
1!
$end
#2
0!
#4
1!
#6
0!
#8
1!
#10
0!
1#
1$
#12
b111101111110 -
1&
1!
#14
0!
#16
b111101111101 -
1!
#18
0!
#20
b111101111100 -
1!
#22
0!
#24
b111101111011 -
1!
#26
0!
#28
b111101111010 -
1!
#30
0!
#32
b111101111001 -
1!
#34
0!
#36
b111101111000 -
1!
#38
0!
#40
b111101110111 -
1!
#42
0!
#44
b111101110110 -
1!
#46
0!
#48
b111101110101 -
1!
#50
0!
#52
b111101110100 -
1!
#54
0!
#56
b111101110011 -
1!
#58
0!
#60
b111101110010 -
1!
#62
0!
#64
b111101110001 -
1!
#66
0!
#68
b111101110000 -
1!
#70
0!
#72
b111101101111 -
1!
#74
0!
#76
b111101101110 -
1!
#78
0!
#80
b111101101101 -
1!
#82
0!
#84
b111101101100 -
1!
#86
0!
#88
b111101101011 -
1!
#90
0!
#92
b111101101010 -
1!
#94
0!
#96
b111101101001 -
1!
#98
0!
#100
b111101101000 -
1!
1"
#102
0!
#104
b111101100111 -
1!
#106
0!
#108
b111101100110 -
1!
#110
0!
#112
b111101100101 -
1!
#114
0!
#116
b111101100100 -
1!
#118
0!
#120
b111101100011 -
1!
#122
0!
#124
b111101100010 -
1!
#126
0!
#128
b111101100001 -
1!
#130
0!
#132
b111101100000 -
1!
#134
0!
#136
b111101011111 -
1!
#138
0!
#140
b111101011110 -
1!
#142
0!
#144
b111101011101 -
1!
#146
0!
#148
b111101011100 -
1!
#150
0!
#152
b111101011011 -
1!
#154
0!
#156
b111101011010 -
1!
#158
0!
#160
b111101011001 -
1!
#162
0!
#164
b111101011000 -
1!
#166
0!
#168
b111101010111 -
1!
#170
0!
#172
b111101010110 -
1!
#174
0!
#176
b111101010101 -
1!
#178
0!
#180
b111101010100 -
1!
#182
0!
#184
b111101010011 -
1!
#186
0!
#188
b111101010010 -
1!
#190
0!
#192
b111101010001 -
1!
#194
0!
#196
b111101010000 -
1!
#198
0!
#200
b111101001111 -
1!
#202
0!
#204
b111101001110 -
1!
#206
0!
#208
b111101001101 -
1!
#210
0!
#212
b111101001100 -
1!
#214
0!
#216
b111101001011 -
1!
#218
0!
#220
b111101001010 -
1!
#222
0!
#224
b111101001001 -
1!
#226
0!
#228
b111101001000 -
1!
#230
0!
#232
b111101000111 -
1!
#234
0!
#236
b111101000110 -
1!
#238
0!
#240
b111101000101 -
1!
#242
0!
#244
b111101000100 -
1!
#246
0!
#248
b111101000011 -
1!
#250
0!
0"
#252
b111101000010 -
1!
#254
0!
#256
b111101000001 -
1!
#258
0!
#260
b111101000000 -
1!
#262
0!
#264
b111100111111 -
1!
#266
0!
#268
b111100111110 -
1!
#270
0!
#272
b111100111101 -
1!
#274
0!
#276
b111100111100 -
1!
#278
0!
#280
b111100111011 -
1!
#282
0!
#284
b111100111010 -
1!
#286
0!
#288
b111100111001 -
1!
#290
0!
#292
b111100111000 -
1!
#294
0!
#296
b111100110111 -
1!
#298
0!
#300
b111100110110 -
1!
#302
0!
#304
b111100110101 -
1!
#306
0!
#308
b111100110100 -
1!
#310
0!
#312
b111100110011 -
1!
#314
0!
#316
b111100110010 -
1!
#318
0!
#320
b111100110001 -
1!
#322
0!
#324
b111100110000 -
1!
#326
0!
#328
b111100101111 -
1!
#330
0!
#332
b111100101110 -
1!
#334
0!
#336
b111100101101 -
1!
#338
0!
#340
b111100101100 -
1!
#342
0!
#344
b111100101011 -
1!
#346
0!
#348
b111100101010 -
1!
#350
0!
#352
b111100101001 -
1!
#354
0!
#356
b111100101000 -
1!
#358
0!
#360
b111100100111 -
1!
#362
0!
#364
b111100100110 -
1!
#366
0!
#368
b111100100101 -
1!
#370
0!
#372
b111100100100 -
1!
#374
0!
#376
b111100100011 -
1!
#378
0!
#380
b111100100010 -
1!
#382
0!
#384
b111100100001 -
1!
#386
0!
#388
b111100100000 -
1!
#390
0!
#392
b111100011111 -
1!
#394
0!
#396
b111100011110 -
1!
#398
0!
#400
b111100011101 -
1!
1"
#402
0!
#404
b111100011100 -
1!
#406
0!
#408
b111100011011 -
1!
#410
0!
#412
b111100011010 -
1!
#414
0!
#416
b111100011001 -
1!
#418
0!
#420
b111100011000 -
1!
#422
0!
#424
b111100010111 -
1!
#426
0!
#428
b111100010110 -
1!
#430
0!
#432
b111100010101 -
1!
#434
0!
#436
b111100010100 -
1!
#438
0!
#440
b111100010011 -
1!
#442
0!
#444
b111100010010 -
1!
#446
0!
#448
b111100010001 -
1!
#450
0!
#452
b111100010000 -
1!
#454
0!
#456
b111100001111 -
1!
#458
0!
#460
b111100001110 -
1!
#462
0!
#464
b111100001101 -
1!
#466
0!
#468
b111100001100 -
1!
#470
0!
#472
b111100001011 -
1!
#474
0!
#476
b111100001010 -
1!
#478
0!
#480
b111100001001 -
1!
#482
0!
#484
b111100001000 -
1!
#486
0!
#488
b111100000111 -
1!
#490
0!
#492
b111100000110 -
1!
#494
0!
#496
b111100000101 -
1!
#498
0!
#500
b111100000100 -
1!
#502
0!
#504
b111100000011 -
1!
#506
0!
#508
b111100000010 -
1!
#510
0!
#512
b111100000001 -
1!
#514
0!
#516
b111100000000 -
1!
#518
0!
#520
b111011111111 -
1!
#522
0!
#524
b111011111110 -
1!
#526
0!
#528
b111011111101 -
1!
#530
0!
#532
b111011111100 -
1!
#534
0!
#536
b111011111011 -
1!
#538
0!
#540
b111011111010 -
1!
#542
0!
#544
b111011111001 -
1!
#546
0!
#548
b111011111000 -
1!
#550
0!
0"
#552
b111011110111 -
1!
#554
0!
#556
b111011110110 -
1!
#558
0!
#560
b111011110101 -
1!
#562
0!
#564
b111011110100 -
1!
#566
0!
#568
b111011110011 -
1!
#570
0!
#572
b111011110010 -
1!
#574
0!
#576
b111011110001 -
1!
#578
0!
#580
b111011110000 -
1!
#582
0!
#584
b111011101111 -
1!
#586
0!
#588
b111011101110 -
1!
#590
0!
#592
b111011101101 -
1!
#594
0!
#596
b111011101100 -
1!
#598
0!
#600
b111011101011 -
1!
#602
0!
#604
b111011101010 -
1!
#606
0!
#608
b111011101001 -
1!
#610
0!
#612
b111011101000 -
1!
#614
0!
#616
b111011100111 -
1!
#618
0!
#620
b111011100110 -
1!
#622
0!
#624
b111011100101 -
1!
#626
0!
#628
b111011100100 -
1!
#630
0!
#632
b111011100011 -
1!
#634
0!
#636
b111011100010 -
1!
#638
0!
#640
b111011100001 -
1!
#642
0!
#644
b111011100000 -
1!
#646
0!
#648
b111011011111 -
1!
#650
0!
#652
b111011011110 -
1!
#654
0!
#656
b111011011101 -
1!
#658
0!
#660
b111011011100 -
1!
#662
0!
#664
b111011011011 -
1!
#666
0!
#668
b111011011010 -
1!
#670
0!
#672
b111011011001 -
1!
#674
0!
#676
b111011011000 -
1!
#678
0!
#680
b111011010111 -
1!
#682
0!
#684
b111011010110 -
1!
#686
0!
#688
b111011010101 -
1!
#690
0!
#692
b111011010100 -
1!
#694
0!
#696
b111011010011 -
1!
#698
0!
#700
b111011010010 -
1!
#702
0!
#704
b111011010001 -
1!
#706
0!
#708
b111011010000 -
1!
#710
0!
#712
b111011001111 -
1!
#714
0!
#716
b111011001110 -
1!
#718
0!
#720
b111011001101 -
1!
#722
0!
#724
b111011001100 -
1!
#726
0!
#728
b111011001011 -
1!
#730
0!
#732
b111011001010 -
1!
#734
0!
#736
b111011001001 -
1!
#738
0!
#740
b111011001000 -
1!
#742
0!
#744
b111011000111 -
1!
#746
0!
#748
b111011000110 -
1!
#750
0!
#752
b111011000101 -
1!
#754
0!
#756
b111011000100 -
1!
#758
0!
#760
b111011000011 -
1!
#762
0!
#764
b111011000010 -
1!
#766
0!
#768
b111011000001 -
1!
#770
0!
#772
b111011000000 -
1!
#774
0!
#776
b111010111111 -
1!
#778
0!
#780
b111010111110 -
1!
#782
0!
#784
b111010111101 -
1!
#786
0!
#788
b111010111100 -
1!
#790
0!
#792
b111010111011 -
1!
#794
0!
#796
b111010111010 -
1!
#798
0!
#800
b111010111001 -
1!
#802
0!
#804
b111010111000 -
1!
#806
0!
#808
b111010110111 -
1!
#810
0!
#812
b111010110110 -
1!
#814
0!
#816
b111010110101 -
1!
#818
0!
#820
b111010110100 -
1!
#822
0!
#824
b111010110011 -
1!
#826
0!
#828
b111010110010 -
1!
#830
0!
#832
b111010110001 -
1!
#834
0!
#836
b111010110000 -
1!
#838
0!
#840
b111010101111 -
1!
#842
0!
#844
b111010101110 -
1!
#846
0!
#848
b111010101101 -
1!
#850
0!
1"
#852
b111010101100 -
1!
#854
0!
#856
b111010101011 -
1!
#858
0!
#860
b111010101010 -
1!
#862
0!
#864
b111010101001 -
1!
#866
0!
#868
b111010101000 -
1!
#870
0!
#872
b111010100111 -
1!
#874
0!
#876
b111010100110 -
1!
#878
0!
#880
b111010100101 -
1!
#882
0!
#884
b111010100100 -
1!
#886
0!
#888
b111010100011 -
1!
#890
0!
#892
b111010100010 -
1!
#894
0!
#896
b111010100001 -
1!
#898
0!
#900
b111010100000 -
1!
#902
0!
#904
b111010011111 -
1!
#906
0!
#908
b111010011110 -
1!
#910
0!
#912
b111010011101 -
1!
#914
0!
#916
b111010011100 -
1!
#918
0!
#920
b111010011011 -
1!
#922
0!
#924
b111010011010 -
1!
#926
0!
#928
b111010011001 -
1!
#930
0!
#932
b111010011000 -
1!
#934
0!
#936
b111010010111 -
1!
#938
0!
#940
b111010010110 -
1!
#942
0!
#944
b111010010101 -
1!
#946
0!
#948
b111010010100 -
1!
#950
0!
#952
b111010010011 -
1!
#954
0!
#956
b111010010010 -
1!
#958
0!
#960
b111010010001 -
1!
#962
0!
#964
b111010010000 -
1!
#966
0!
#968
b111010001111 -
1!
#970
0!
#972
b111010001110 -
1!
#974
0!
#976
b111010001101 -
1!
#978
0!
#980
b111010001100 -
1!
#982
0!
#984
b111010001011 -
1!
#986
0!
#988
b111010001010 -
1!
#990
0!
#992
b111010001001 -
1!
#994
0!
#996
b111010001000 -
1!
#998
0!
#1000
b111010000111 -
1!
0"
#1002
0!
#1004
b111010000110 -
1!
#1006
0!
#1008
b111010000101 -
1!
#1010
0!
#1012
b111010000100 -
1!
#1014
0!
#1016
b111010000011 -
1!
#1018
0!
#1020
b111010000010 -
1!
#1022
0!
#1024
b111010000001 -
1!
#1026
0!
#1028
b111010000000 -
1!
#1030
0!
#1032
b111001111111 -
1!
#1034
0!
#1036
b111001111110 -
1!
#1038
0!
#1040
b111001111101 -
1!
#1042
0!
#1044
b111001111100 -
1!
#1046
0!
#1048
b111001111011 -
1!
#1050
0!
#1052
b111001111010 -
1!
#1054
0!
#1056
b111001111001 -
1!
#1058
0!
#1060
b111001111000 -
1!
#1062
0!
#1064
b111001110111 -
1!
#1066
0!
#1068
b111001110110 -
1!
#1070
0!
#1072
b111001110101 -
1!
#1074
0!
#1076
b111001110100 -
1!
#1078
0!
#1080
b111001110011 -
1!
#1082
0!
#1084
b111001110010 -
1!
#1086
0!
#1088
b111001110001 -
1!
#1090
0!
#1092
b111001110000 -
1!
#1094
0!
#1096
b111001101111 -
1!
#1098
0!
#1100
b111001101110 -
1!
#1102
0!
#1104
b111001101101 -
1!
#1106
0!
#1108
b111001101100 -
1!
#1110
0!
#1112
b111001101011 -
1!
#1114
0!
#1116
b111001101010 -
1!
#1118
0!
#1120
b111001101001 -
1!
#1122
0!
#1124
b111001101000 -
1!
#1126
0!
#1128
b111001100111 -
1!
#1130
0!
#1132
b111001100110 -
1!
#1134
0!
#1136
b111001100101 -
1!
#1138
0!
#1140
b111001100100 -
1!
#1142
0!
#1144
b111001100011 -
1!
#1146
0!
#1148
b111001100010 -
1!
#1150
0!
1"
#1152
b111001100001 -
1!
#1154
0!
#1156
b111001100000 -
1!
#1158
0!
#1160
b111001011111 -
1!
#1162
0!
#1164
b111001011110 -
1!
#1166
0!
#1168
b111001011101 -
1!
#1170
0!
#1172
b111001011100 -
1!
#1174
0!
#1176
b111001011011 -
1!
#1178
0!
#1180
b111001011010 -
1!
#1182
0!
#1184
b111001011001 -
1!
#1186
0!
#1188
b111001011000 -
1!
#1190
0!
#1192
b111001010111 -
1!
#1194
0!
#1196
b111001010110 -
1!
#1198
0!
#1200
b111001010101 -
1!
#1202
0!
#1204
b111001010100 -
1!
#1206
0!
#1208
b111001010011 -
1!
#1210
0!
#1212
b111001010010 -
1!
#1214
0!
#1216
b111001010001 -
1!
#1218
0!
#1220
b111001010000 -
1!
#1222
0!
#1224
b111001001111 -
1!
#1226
0!
#1228
b111001001110 -
1!
#1230
0!
#1232
b111001001101 -
1!
#1234
0!
#1236
b111001001100 -
1!
#1238
0!
#1240
b111001001011 -
1!
#1242
0!
#1244
b111001001010 -
1!
#1246
0!
#1248
b111001001001 -
1!
#1250
0!
#1252
b111001001000 -
1!
#1254
0!
#1256
b111001000111 -
1!
#1258
0!
#1260
b111001000110 -
1!
#1262
0!
#1264
b111001000101 -
1!
#1266
0!
#1268
b111001000100 -
1!
#1270
0!
#1272
b111001000011 -
1!
#1274
0!
#1276
b111001000010 -
1!
#1278
0!
#1280
b111001000001 -
1!
#1282
0!
#1284
b111001000000 -
1!
#1286
0!
#1288
b111000111111 -
1!
#1290
0!
#1292
b111000111110 -
1!
#1294
0!
#1296
b111000111101 -
1!
#1298
0!
#1300
b111000111100 -
1!
#1302
0!
#1304
b111000111011 -
1!
#1306
0!
#1308
b111000111010 -
1!
#1310
0!
#1312
b111000111001 -
1!
#1314
0!
#1316
b111000111000 -
1!
#1318
0!
#1320
b111000110111 -
1!
#1322
0!
#1324
b111000110110 -
1!
#1326
0!
#1328
b111000110101 -
1!
#1330
0!
#1332
b111000110100 -
1!
#1334
0!
#1336
b111000110011 -
1!
#1338
0!
#1340
b111000110010 -
1!
#1342
0!
#1344
b111000110001 -
1!
#1346
0!
#1348
b111000110000 -
1!
#1350
0!
#1352
b111000101111 -
1!
#1354
0!
#1356
b111000101110 -
1!
#1358
0!
#1360
b111000101101 -
1!
#1362
0!
#1364
b111000101100 -
1!
#1366
0!
#1368
b111000101011 -
1!
#1370
0!
#1372
b111000101010 -
1!
#1374
0!
#1376
b111000101001 -
1!
#1378
0!
#1380
b111000101000 -
1!
#1382
0!
#1384
b111000100111 -
1!
#1386
0!
#1388
b111000100110 -
1!
#1390
0!
#1392
b111000100101 -
1!
#1394
0!
#1396
b111000100100 -
1!
#1398
0!
#1400
b111000100011 -
1!
#1402
0!
#1404
b111000100010 -
1!
#1406
0!
#1408
b111000100001 -
1!
#1410
0!
#1412
b111000100000 -
1!
#1414
0!
#1416
b111000011111 -
1!
#1418
0!
#1420
b111000011110 -
1!
#1422
0!
#1424
b111000011101 -
1!
#1426
0!
#1428
b111000011100 -
1!
#1430
0!
#1432
b111000011011 -
1!
#1434
0!
#1436
b111000011010 -
1!
#1438
0!
#1440
b111000011001 -
1!
#1442
0!
#1444
b111000011000 -
1!
#1446
0!
#1448
b111000010111 -
1!
#1450
0!
#1452
b111000010110 -
1!
#1454
0!
#1456
b111000010101 -
1!
#1458
0!
#1460
b111000010100 -
1!
#1462
0!
#1464
b111000010011 -
1!
#1466
0!
#1468
b111000010010 -
1!
#1470
0!
#1472
b111000010001 -
1!
#1474
0!
#1476
b111000010000 -
1!
#1478
0!
#1480
b111000001111 -
1!
#1482
0!
#1484
b111000001110 -
1!
#1486
0!
#1488
b111000001101 -
1!
#1490
0!
#1492
b111000001100 -
1!
#1494
0!
#1496
b111000001011 -
1!
#1498
0!
#1500
b111000001010 -
1!
#1502
0!
#1504
b111000001001 -
1!
#1506
0!
#1508
b111000001000 -
1!
#1510
0!
#1512
b111000000111 -
1!
#1514
0!
#1516
b111000000110 -
1!
#1518
0!
#1520
b111000000101 -
1!
#1522
0!
#1524
b111000000100 -
1!
#1526
0!
#1528
b111000000011 -
1!
#1530
0!
#1532
b111000000010 -
1!
#1534
0!
#1536
b111000000001 -
1!
#1538
0!
#1540
b111000000000 -
1!
#1542
0!
#1544
b110111111111 -
1!
#1546
0!
#1548
b110111111110 -
1!
#1550
0!
#1552
b110111111101 -
1!
#1554
0!
#1556
b110111111100 -
1!
#1558
0!
#1560
b110111111011 -
1!
#1562
0!
#1564
b110111111010 -
1!
#1566
0!
#1568
b110111111001 -
1!
#1570
0!
#1572
b110111111000 -
1!
#1574
0!
#1576
b110111110111 -
1!
#1578
0!
#1580
b110111110110 -
1!
#1582
0!
#1584
b110111110101 -
1!
#1586
0!
#1588
b110111110100 -
1!
#1590
0!
#1592
b110111110011 -
1!
#1594
0!
#1596
b110111110010 -
1!
#1598
0!
#1600
b110111110001 -
1!
#1602
0!
#1604
b110111110000 -
1!
#1606
0!
#1608
b110111101111 -
1!
#1610
0!
#1612
b110111101110 -
1!
#1614
0!
#1616
b110111101101 -
1!
#1618
0!
#1620
b110111101100 -
1!
#1622
0!
#1624
b110111101011 -
1!
#1626
0!
#1628
b110111101010 -
1!
#1630
0!
#1632
b110111101001 -
1!
#1634
0!
#1636
b110111101000 -
1!
#1638
0!
#1640
b110111100111 -
1!
#1642
0!
#1644
b110111100110 -
1!
#1646
0!
#1648
b110111100101 -
1!
#1650
0!
#1652
b110111100100 -
1!
#1654
0!
#1656
b110111100011 -
1!
#1658
0!
#1660
b110111100010 -
1!
#1662
0!
#1664
b110111100001 -
1!
#1666
0!
#1668
b110111100000 -
1!
#1670
0!
#1672
b110111011111 -
1!
#1674
0!
#1676
b110111011110 -
1!
#1678
0!
#1680
b110111011101 -
1!
#1682
0!
#1684
b110111011100 -
1!
#1686
0!
#1688
b110111011011 -
1!
#1690
0!
#1692
b110111011010 -
1!
#1694
0!
#1696
b110111011001 -
1!
#1698
0!
#1700
b110111011000 -
1!
#1702
0!
#1704
b110111010111 -
1!
#1706
0!
#1708
b110111010110 -
1!
#1710
0!
#1712
b110111010101 -
1!
#1714
0!
#1716
b110111010100 -
1!
#1718
0!
#1720
b110111010011 -
1!
#1722
0!
#1724
b110111010010 -
1!
#1726
0!
#1728
b110111010001 -
1!
#1730
0!
#1732
b110111010000 -
1!
#1734
0!
#1736
b110111001111 -
1!
#1738
0!
#1740
b110111001110 -
1!
#1742
0!
#1744
b110111001101 -
1!
#1746
0!
#1748
b110111001100 -
1!
#1750
0!
#1752
b110111001011 -
1!
#1754
0!
#1756
b110111001010 -
1!
#1758
0!
#1760
b110111001001 -
1!
#1762
0!
#1764
b110111001000 -
1!
#1766
0!
#1768
b110111000111 -
1!
#1770
0!
#1772
b110111000110 -
1!
#1774
0!
#1776
b110111000101 -
1!
#1778
0!
#1780
b110111000100 -
1!
#1782
0!
#1784
b110111000011 -
1!
#1786
0!
#1788
b110111000010 -
1!
#1790
0!
#1792
b110111000001 -
1!
#1794
0!
#1796
b110111000000 -
1!
#1798
0!
#1800
b110110111111 -
1!
#1802
0!
#1804
b110110111110 -
1!
#1806
0!
#1808
b110110111101 -
1!
#1810
0!
#1812
b110110111100 -
1!
#1814
0!
#1816
b110110111011 -
1!
#1818
0!
#1820
b110110111010 -
1!
#1822
0!
#1824
b110110111001 -
1!
#1826
0!
#1828
b110110111000 -
1!
#1830
0!
#1832
b110110110111 -
1!
#1834
0!
#1836
b110110110110 -
1!
#1838
0!
#1840
b110110110101 -
1!
#1842
0!
#1844
b110110110100 -
1!
#1846
0!
#1848
b110110110011 -
1!
#1850
0!
#1852
b110110110010 -
1!
#1854
0!
#1856
b110110110001 -
1!
#1858
0!
#1860
b110110110000 -
1!
#1862
0!
#1864
b110110101111 -
1!
#1866
0!
#1868
b110110101110 -
1!
#1870
0!
#1872
b110110101101 -
1!
#1874
0!
#1876
b110110101100 -
1!
#1878
0!
#1880
b110110101011 -
1!
#1882
0!
#1884
b110110101010 -
1!
#1886
0!
#1888
b110110101001 -
1!
#1890
0!
#1892
b110110101000 -
1!
#1894
0!
#1896
b110110100111 -
1!
#1898
0!
#1900
b110110100110 -
1!
#1902
0!
#1904
b110110100101 -
1!
#1906
0!
#1908
b110110100100 -
1!
#1910
0!
#1912
b110110100011 -
1!
#1914
0!
#1916
b110110100010 -
1!
#1918
0!
#1920
b110110100001 -
1!
#1922
0!
#1924
b110110100000 -
1!
#1926
0!
#1928
b110110011111 -
1!
#1930
0!
#1932
b110110011110 -
1!
#1934
0!
#1936
b110110011101 -
1!
#1938
0!
#1940
b110110011100 -
1!
#1942
0!
#1944
b110110011011 -
1!
#1946
0!
#1948
b110110011010 -
1!
#1950
0!
#1952
b110110011001 -
1!
#1954
0!
#1956
b110110011000 -
1!
#1958
0!
#1960
b110110010111 -
1!
#1962
0!
#1964
b110110010110 -
1!
#1966
0!
#1968
b110110010101 -
1!
#1970
0!
#1972
b110110010100 -
1!
#1974
0!
#1976
b110110010011 -
1!
#1978
0!
#1980
b110110010010 -
1!
#1982
0!
#1984
b110110010001 -
1!
#1986
0!
#1988
b110110010000 -
1!
#1990
0!
#1992
b110110001111 -
1!
#1994
0!
#1996
b110110001110 -
1!
#1998
0!
#2000
b110110001101 -
1!
#2002
0!
#2004
b110110001100 -
1!
#2006
0!
#2008
b110110001011 -
1!
#2010
0!
0#
#2012
b110110001010 -
1!
#2014
0!
#2016
b110110001001 -
1!
#2018
0!
#2020
b110110001000 -
1!
#2022
0!
#2024
b110110000111 -
1!
#2026
0!
#2028
b110110000110 -
1!
#2030
0!
#2032
b110110000101 -
1!
#2034
0!
#2036
b110110000100 -
1!
#2038
0!
#2040
b110110000011 -
1!
#2042
0!
#2044
b110110000010 -
1!
#2046
0!
#2048
b110110000001 -
1!
#2050
0!
#2052
b110110000000 -
1!
#2054
0!
#2056
b110101111111 -
1!
#2058
0!
#2060
b110101111110 -
1!
#2062
0!
#2064
b110101111101 -
1!
#2066
0!
#2068
b110101111100 -
1!
#2070
0!
#2072
b110101111011 -
1!
#2074
0!
#2076
b110101111010 -
1!
#2078
0!
#2080
b110101111001 -
1!
#2082
0!
#2084
b110101111000 -
1!
#2086
0!
#2088
b110101110111 -
1!
#2090
0!
#2092
b110101110110 -
1!
#2094
0!
#2096
b110101110101 -
1!
#2098
0!
#2100
b110101110100 -
1!
#2102
0!
#2104
b110101110011 -
1!
#2106
0!
#2108
b110101110010 -
1!
#2110
0!
#2112
b110101110001 -
1!
#2114
0!
#2116
b110101110000 -
1!
#2118
0!
#2120
b110101101111 -
1!
#2122
0!
#2124
b110101101110 -
1!
#2126
0!
#2128
b110101101101 -
1!
#2130
0!
#2132
b110101101100 -
1!
#2134
0!
#2136
b110101101011 -
1!
#2138
0!
#2140
b110101101010 -
1!
#2142
0!
#2144
b110101101001 -
1!
#2146
0!
#2148
b110101101000 -
1!
#2150
0!
#2152
b110101100111 -
1!
#2154
0!
#2156
b110101100110 -
1!
#2158
0!
#2160
b110101100101 -
1!
#2162
0!
#2164
b110101100100 -
1!
#2166
0!
#2168
b110101100011 -
1!
#2170
0!
#2172
b110101100010 -
1!
#2174
0!
#2176
b110101100001 -
1!
#2178
0!
#2180
b110101100000 -
1!
#2182
0!
#2184
b110101011111 -
1!
#2186
0!
#2188
b110101011110 -
1!
#2190
0!
#2192
b110101011101 -
1!
#2194
0!
#2196
b110101011100 -
1!
#2198
0!
#2200
b110101011011 -
1!
#2202
0!
#2204
b110101011010 -
1!
#2206
0!
#2208
b110101011001 -
1!
#2210
0!
#2212
b110101011000 -
1!
#2214
0!
#2216
b110101010111 -
1!
#2218
0!
#2220
b110101010110 -
1!
#2222
0!
#2224
b110101010101 -
1!
#2226
0!
#2228
b110101010100 -
1!
#2230
0!
#2232
b110101010011 -
1!
#2234
0!
#2236
b110101010010 -
1!
#2238
0!
#2240
b110101010001 -
1!
#2242
0!
#2244
b110101010000 -
1!
#2246
0!
#2248
b110101001111 -
1!
#2250
0!
#2252
b110101001110 -
1!
#2254
0!
#2256
b110101001101 -
1!
#2258
0!
#2260
b110101001100 -
1!
#2262
0!
#2264
b110101001011 -
1!
#2266
0!
#2268
b110101001010 -
1!
#2270
0!
#2272
b110101001001 -
1!
#2274
0!
#2276
b110101001000 -
1!
#2278
0!
#2280
b110101000111 -
1!
#2282
0!
#2284
b110101000110 -
1!
#2286
0!
#2288
b110101000101 -
1!
#2290
0!
#2292
b110101000100 -
1!
#2294
0!
#2296
b110101000011 -
1!
#2298
0!
#2300
b110101000010 -
1!
#2302
0!
#2304
b110101000001 -
1!
#2306
0!
#2308
b110101000000 -
1!
#2310
0!
#2312
b110100111111 -
1!
#2314
0!
#2316
b110100111110 -
1!
#2318
0!
#2320
b110100111101 -
1!
#2322
0!
#2324
b110100111100 -
1!
#2326
0!
#2328
b110100111011 -
1!
#2330
0!
#2332
b110100111010 -
1!
#2334
0!
#2336
b110100111001 -
1!
#2338
0!
#2340
b110100111000 -
1!
#2342
0!
#2344
b110100110111 -
1!
#2346
0!
#2348
b110100110110 -
1!
#2350
0!
#2352
b110100110101 -
1!
#2354
0!
#2356
b110100110100 -
1!
#2358
0!
#2360
b110100110011 -
1!
#2362
0!
#2364
b110100110010 -
1!
#2366
0!
#2368
b110100110001 -
1!
#2370
0!
#2372
b110100110000 -
1!
#2374
0!
#2376
b110100101111 -
1!
#2378
0!
#2380
b110100101110 -
1!
#2382
0!
#2384
b110100101101 -
1!
#2386
0!
#2388
b110100101100 -
1!
#2390
0!
#2392
b110100101011 -
1!
#2394
0!
#2396
b110100101010 -
1!
#2398
0!
#2400
b110100101001 -
1!
#2402
0!
#2404
b110100101000 -
1!
#2406
0!
#2408
b110100100111 -
1!
#2410
0!
#2412
b110100100110 -
1!
#2414
0!
#2416
b110100100101 -
1!
#2418
0!
#2420
b110100100100 -
1!
#2422
0!
#2424
b110100100011 -
1!
#2426
0!
#2428
b110100100010 -
1!
#2430
0!
#2432
b110100100001 -
1!
#2434
0!
#2436
b110100100000 -
1!
#2438
0!
#2440
b110100011111 -
1!
#2442
0!
#2444
b110100011110 -
1!
#2446
0!
#2448
b110100011101 -
1!
#2450
0!
#2452
b110100011100 -
1!
#2454
0!
#2456
b110100011011 -
1!
#2458
0!
#2460
b110100011010 -
1!
#2462
0!
#2464
b110100011001 -
1!
#2466
0!
#2468
b110100011000 -
1!
#2470
0!
#2472
b110100010111 -
1!
#2474
0!
#2476
b110100010110 -
1!
#2478
0!
#2480
b110100010101 -
1!
#2482
0!
#2484
b110100010100 -
1!
#2486
0!
#2488
b110100010011 -
1!
#2490
0!
#2492
b110100010010 -
1!
#2494
0!
#2496
b110100010001 -
1!
#2498
0!
#2500
b110100010000 -
1!
