HW/RTL/06PCM-AUDIO-MICROFONO/Version_01/02 verilog/Prueba4/div_freq.v
module div_freq #(
              parameter   fi     = 50000000,        //<- fFPGA/2=fi  
              parameter   fs	 = 3125000        //<- flckout=fs
  )(input clk, output reg clkout,input reset, output reg led);



initial led=0;

reg [31:0] count;
initial count<= fi/fs;

always @(posedge  clk)
begin
	if (reset) begin
	led=0;
	count <= fi/fs;
	clkout <=0;
	end
	else begin
	led=1;
		
		if (count==0)begin
		clkout <=~clkout;
		count <= fi/fs;
		end	
		else begin
		count <=count-1;
		end

	
	end	
end


endmodule

HW/RTL/06PCM-AUDIO-MICROFONO/Version_01/02 verilog/Prueba4/microfono.v
module microfono
(
	input			reset,	
	input         		micData, 
	input			clk,
	output			mclk,
	output	reg		micLRSel,
        output			ledres,
        output  reg		ampPWM,
        output  reg     	ampSD,
	output          	mclk2,
	output  reg 		sregt,
	output  reg     	done 

);

reg [15:0] count=16;

assign mclk2=mclk1;
assign mclk=mclk1;
initial done<=0;
initial micLRSel <= 0;
initial ampSD <= 1;

div_freq df(.clk(clk), .reset(reset),.clkout(mclk1),.led(ledres));

always @(posedge  mclk)
begin
	if (reset)
     	ampPWM<=0; 	
	else 
	begin	
	done<=0;
	ampPWM <= micData;
	sregt<= micData;
	count<=count-1;
			if(count<=0)
			begin
			done<=1;
			count<=16;
			end
	
	end
end




endmodule

HW/RTL/06PCM-AUDIO-MICROFONO/Version_01/02 verilog/Prueba4/fifo.v
module fifo # (parameter abits = 10, dbits = 1)(
	input 			clock,
	input 			clk,
   	input 			micData,
	input 			reset,
	input 			wr,
	input 			rd,
	input [dbits-1:0]	din,
	output 			empty,
	output 			full,
	output [dbits-1:0]	dout,
	output			micLRSel,
        output			ledres,
        output  		ampPWM,
        output  	     	ampSD,
	output 			mclk,
	output			mclk2
    );

microfono mi(.clk(clk),.reset(reset),.mclk(mclk),.micLRSel(micLRSel),.micData(micData),.ledres(ledres),.ampPWM(ampPWM),.ampSD(ampSD),.done(clock),.sregt(din),.mclk2(mclk2));

wire db_wr, db_rd;
reg dffw1, dffw2, dffr1, dffr2;
reg [dbits-1:0] out;
 reg [dbits-1:0] out2;
always @ (posedge clock) dffw1 <= wr; 
always @ (posedge clock) dffw2 <= dffw1;
 
assign db_wr = ~dffw1 & dffw2; //monostable multivibrator to detect only one pulse of the button
 
always @ (posedge clock) dffr1 <= rd;
always @ (posedge clock) dffr2 <= dffr1;
 
assign db_rd = ~dffr1 & dffr2; //monostable multivibrator to detect only one pulse of the button
 
 
reg [dbits-1:0] regarray[2**abits-1:0]; //number of words in fifo = 2^(number of address bits)
reg [abits-1:0] wr_reg, wr_next, wr_succ; //points to the register that needs to be written to
reg [abits-1:0] rd_reg, rd_next, rd_succ; //points to the register that needs to be read from
reg full_reg, empty_reg, full_next, empty_next;
 
assign wr_en = db_wr & ~full; //only write if write signal is high and fifo is not full
 
//always block for write operation
always @ (posedge clock)
 begin
  if(wr_en)
   regarray[wr_reg] <= din;  //at wr_reg location of regarray store what is given at din
 
 end
  
//always block for read operation
always @ (posedge clock)
 begin
  if(db_rd)
   out <= regarray[rd_reg];
 end

always @ (posedge clock or posedge reset)
 begin
  if (reset)
   begin
   wr_reg <= 0;
   rd_reg <= 0;
   full_reg <= 1'b0;
   empty_reg <= 1'b1;
   end
   
  else
   begin
   wr_reg <= wr_next; //created the next registers to avoid the error of mixing blocking and non blocking assignment to the same signal
   rd_reg <= rd_next;
   full_reg <= full_next;
   empty_reg <= empty_next;
   end
 end
  
always @(*)
 begin
  wr_succ = wr_reg + 1; //assigned to new value as wr_next cannot be tested for in same always block
  rd_succ = rd_reg + 1; //assigned to new value as rd_next cannot be tested for in same always block
  wr_next = wr_reg;  //defaults state stays the same
  rd_next = rd_reg;  //defaults state stays the same
  full_next = full_reg;  //defaults state stays the same
  empty_next = empty_reg;  //defaults state stays the same
   
   case({db_wr,db_rd})
    //2'b00: do nothing LOL..
     
    2'b01: //read
     begin
      if(~empty) //if fifo is not empty continue
       begin
        rd_next = rd_succ;
        full_next = 1'b0;
       if(rd_succ == wr_reg) //all data has been read
         empty_next = 1'b1;  //its empty again
       end
     end
2'b10: //write
     begin
       
      if(~full) //if fifo is not full continue
       begin
        wr_next = wr_succ;
        empty_next = 1'b0;
        if(wr_succ == (2**abits-1)) //all registers have been written to
         full_next = 1'b1;   //its full now
       end
     end
      
    2'b11: //read and write
     begin
      wr_next = wr_succ;
      rd_next = rd_succ;
     end
     //no empty or full flag will be checked for or asserted in this state since data is being written to and read from together it can  not get full in this state.
    endcase
    
 
 end
 
assign full = full_reg;
assign empty = empty_reg;
assign dout = out;
assign dout=out2;
assign ampPWM=out2;
endmodule

HW/RTL/06PCM-AUDIO-MICROFONO/Version_01/02 verilog/Prueba fifo/fifo_TB.v
module fifo_TB;

reg clk;
reg reset;
reg rd;
reg wr;
reg[7:0] dataint;
reg clock;


fifo uttf(.rd(rd),.wr(wr),.din(dataint),.clk(clk),.reset(reset),.clock(clock));


always
begin
clk =1'b1;
#10;
clk=1'b0;
#10;
end

initial
begin
reset = 1'b1;
#4 reset = 1'b0;
end

initial
begin

wr = 1'b0;
#34300;
wr=1'b1;
#343000;
wr = 1'b0;
#343000;
/*wr = 1'b1;
#3430;
wr=1'b0;
#3430;
wr = 1'b1;
#3430;
wr=1'b0;
#3430;
wr = 1'b1;
#3430;
wr=1'b0;
#3430;
wr = 1'b1;
#3430;
wr=1'b0;
#3430;
wr = 1'b1;
#3430;
wr=1'b0;
#3430;
wr = 1'b1;
#3430;
wr=1'b0;
#3430;
wr = 1'b1;
#3430;
wr=1'b0;
#3430;
wr = 1'b1;
#3430;
wr=1'b0;
#3430;
wr = 1'b1;
#3430;
wr=1'b0;
#3430;
wr = 1'b1;
#3430;
wr=1'b0;*/
end

always
begin
clock =1'b1;
#20;
clock=1'b0;
#20;
end


initial
begin

rd=1'b0;
#643000;
rd=1'b1;
#343000;
rd=1'b0;
#34300;
/*
rd=1'b1;
#3430;
rd=1'b0;
#3430;
rd=1'b1;
#3430;
rd=1'b0;
#3430;
rd=1'b1;
#3430;
rd=1'b0;
#3430;
rd=1'b1;
#3430;
rd=1'b0;
#3430;
rd=1'b1;
#3430;
rd=1'b0;
#3430;
rd=1'b1;
#3430;
rd=1'b0;
#3430;
rd=1'b1;
#3430;
rd=1'b0;
#3430;
rd=1'b1;
#3430;
rd=1'b0;
#3430;
rd=1'b1;
#3430;
rd=1'b0;
#3430;
rd=1'b1;
#3430;
rd=1'b0;
#3430;
rd=1'b1;
#3430;
rd=1'b0;
#3430;
rd=1'b1;
#3430;
rd=1'b0;
#3430;
rd=1'b1;
#3430;
rd=1'b0;
#3430;
rd=1'b1;
#3430;
rd=1'b0;
#3430;
rd=1'b1;
#3430;
rd=1'b0;*/
end


initial begin

#3430 dataint = 7'h1;
#3400 dataint = 7'h3;
#3400 dataint = 7'hA;
#3400 dataint = 7'h3;
#3430 dataint = 7'hA;
#3430 dataint = 7'h05;
#3430 dataint = 7'h1;
#3400 dataint = 7'h3;
#3400 dataint = 7'hA;
#3400 dataint = 7'h3;
#3430 dataint = 7'hA;
#3430 dataint = 7'h05;
#3430 dataint = 7'h1;
#3400 dataint = 7'h3;
#3400 dataint = 7'hA;
#3400 dataint = 7'h3;
#3430 dataint = 7'hA;
#3430 dataint = 7'h05;
#3400 dataint = 7'hA;
#3400 dataint = 7'h3;
#3430 dataint = 7'hA;
#3430 dataint = 7'h05;
#3430 dataint = 7'h05;
#3430 dataint = 7'h1;
#3400 dataint = 7'h3;
#3400 dataint = 7'hA;
#3400 dataint = 7'h3;
#3430 dataint = 7'hA;
#3430 dataint = 7'h05;
#3400 dataint = 7'hA;
#3400 dataint = 7'h3;
#3430 dataint = 7'hA;
#3430 dataint = 7'h05;
#3430 dataint = 1'b0;
#3430 dataint = 1'b1;
#3430 dataint = 1'b0;
#3430 dataint = 1'b1;
#3430 dataint = 1'b0;
#3430 dataint = 1'b1;
#3430 dataint = 1'b0;
#3430 dataint = 1'b1;
#3430 dataint = 1'b0;
end
	
initial begin: TEST_CASE
     $dumpfile("fifo_TB.vcd");
     $dumpvars(-1, uttf);

     #(1000000) $finish;
   end

endmodule //

HW/RTL/06PCM-AUDIO-MICROFONO/Version_01/02 verilog/Prueba4/simulation/fifo_TB.vcd
$date
	Fri Nov 17 09:48:06 2017
$end
$version
	Icarus Verilog
$end
$timescale
	1s
$end
$scope module fifo_TB $end
$scope module uttf $end
$var wire 1 ! ampPWM $end
$var wire 1 " clk $end
$var wire 1 # db_rd $end
$var wire 1 $ db_wr $end
$var wire 1 % dout $end
$var wire 1 & empty $end
$var wire 1 ' micData $end
$var wire 1 ( rd $end
$var wire 1 ) reset $end
$var wire 1 * wr $end
$var wire 1 + wr_en $end
$var wire 1 , micLRSel $end
$var wire 1 - mclk2 $end
$var wire 1 . mclk $end
$var wire 1 / ledres $end
$var wire 1 0 full $end
$var wire 1 1 din $end
$var wire 1 2 clock $end
$var wire 1 3 ampSD $end
$var reg 1 4 dffr1 $end
$var reg 1 5 dffr2 $end
$var reg 1 6 dffw1 $end
$var reg 1 7 dffw2 $end
$var reg 1 8 empty_next $end
$var reg 1 9 empty_reg $end
$var reg 1 : full_next $end
$var reg 1 0 full_reg $end
$var reg 1 ; out $end
$var reg 1 < out2 $end
$var reg 10 = rd_next [9:0] $end
$var reg 10 > rd_reg [9:0] $end
$var reg 10 ? rd_succ [9:0] $end
$var reg 10 @ wr_next [9:0] $end
$var reg 10 A wr_reg [9:0] $end
$var reg 10 B wr_succ [9:0] $end
$scope module mi $end
$var wire 1 " clk $end
$var wire 1 . mclk $end
$var wire 1 - mclk2 $end
$var wire 1 ' micData $end
$var wire 1 ) reset $end
$var wire 1 C mclk1 $end
$var wire 1 / ledres $end
$var reg 1 D ampPWM $end
$var reg 1 3 ampSD $end
$var reg 16 E count [15:0] $end
$var reg 1 2 done $end
$var reg 1 , micLRSel $end
$var reg 1 1 sregt $end
$scope module df $end
$var wire 1 " clk $end
$var wire 1 ) reset $end
$var reg 1 C clkout $end
$var reg 32 F count [31:0] $end
$var reg 1 / led $end
$upscope $end
$upscope $end
$upscope $end
$upscope $end
$enddefinitions $end
#0
$dumpvars
b10000 F
b10000 E
xD
0C
b1 B
b0 A
b0 @
b1 ?
b0 >
b0 =
x<
x;
0:
19
18
x7
x6
x5
x4
13
02
x1
00
0/
0.
0-
0,
x+
1*
1)
0(
x'
1&
x%
x$
x#
1"
x!
$end
#4
0)
#10
0"
#20
b1111 F
1/
1"
#30
0"
#40
b1110 F
1"
#50
0"
#60
b1101 F
1"
#70
0"
#80
b1100 F
1"
#90
0"
#100
b1011 F
1"
#110
0"
#120
b1010 F
1"
#130
0"
#140
b1001 F
1"
#150
0"
#160
b1000 F
1"
#170
0"
#180
b111 F
1"
#190
0"
#200
b110 F
1"
#210
0"
#220
b101 F
1"
#230
0"
#240
b100 F
1"
#250
0"
#260
b11 F
1"
#270
0"
#280
b10 F
1"
#290
0"
#300
b1 F
1"
#310
0"
#320
b0 F
1"
#330
0"
#340
b1111 E
b10000 F
1.
1-
1C
1"
#350
0"
#360
b1111 F
1"
#370
0"
#380
b1110 F
1"
#390
0"
#400
b1101 F
1"
#410
0"
#420
b1100 F
1"
#430
0"
#440
b1011 F
1"
#450
0"
#460
b1010 F
1"
#470
0"
#480
b1001 F
1"
#490
0"
#500
b1000 F
1"
#510
0"
#520
b111 F
1"
#530
0"
#540
b110 F
1"
#550
0"
#560
b101 F
1"
#570
0"
#580
b100 F
1"
#590
0"
#600
b11 F
1"
#610
0"
#620
b10 F
1"
#630
0"
#640
b1 F
1"
#650
0"
#660
b0 F
1"
#670
0"
#680
b10000 F
0.
0-
0C
1"
#690
0"
#700
b1111 F
1"
#710
0"
#720
b1110 F
1"
#730
0"
#740
b1101 F
1"
#750
0"
#760
b1100 F
1"
#770
0"
#780
b1011 F
1"
#790
0"
#800
b1010 F
1"
#810
0"
#820
b1001 F
1"
#830
0"
#840
b1000 F
1"
#850
0"
#860
b111 F
1"
#870
0"
#880
b110 F
1"
#890
0"
#900
b101 F
1"
#910
0"
#920
b100 F
1"
#930
0"
#940
b11 F
1"
#950
0"
#960
b10 F
1"
#970
0"
#980
b1 F
1"
#990
0"
#1000
b0 F
1"
#1010
0"
#1020
b1110 E
b10000 F
1.
1-
1C
1"
#1030
0"
#1040
b1111 F
1"
#1050
0"
#1060
b1110 F
1"
#1070
0"
#1080
b1101 F
1"
#1090
0"
#1100
b1100 F
1"
#1110
0"
#1120
b1011 F
1"
#1130
0"
#1140
b1010 F
1"
#1150
0"
#1160
b1001 F
1"
#1170
0"
#1180
b1000 F
1"
#1190
0"
#1200
b111 F
1"
#1210
0"
#1220
b110 F
1"
#1230
0"
#1240
b101 F
1"
#1250
0"
#1260
b100 F
1"
#1270
0"
#1280
b11 F
1"
#1290
0"
#1300
b10 F
1"
#1310
0"
#1320
b1 F
1"
#1330
0"
#1340
b0 F
1"
#1350
0"
#1360
b10000 F
0.
0-
0C
1"
#1370
0"
#1380
b1111 F
1"
#1390
0"
#1400
b1110 F
1"
#1410
0"
#1420
b1101 F
1"
#1430
0"
#1440
b1100 F
1"
#1450
0"
#1460
b1011 F
1"
#1470
0"
#1480
b1010 F
1"
#1490
0"
#1500
b1001 F
1"
#1510
0"
#1520
b1000 F
1"
#1530
0"
#1540
b111 F
1"
#1550
0"
#1560
b110 F
1"
#1570
0"
#1580
b101 F
1"
#1590
0"
#1600
b100 F
1"
#1610
0"
#1620
b11 F
1"
#1630
0"
#1640
b10 F
1"
#1650
0"
#1660
b1 F
1"
#1670
0"
#1680
b0 F
1"
#1690
0"
#1700
b1101 E
b10000 F
1.
1-
1C
1"
#1710
0"
#1720
b1111 F
1"
#1730
0"
#1740
b1110 F
1"
#1750
0"
#1760
b1101 F
1"
#1770
0"
#1780
b1100 F
1"
#1790
0"
#1800
b1011 F
1"
#1810
0"
#1820
b1010 F
1"
#1830
0"
#1840
b1001 F
1"
#1850
0"
#1860
b1000 F
1"
#1870
0"
#1880
b111 F
1"
#1890
0"
#1900
b110 F
1"
#1910
0"
#1920
b101 F
1"
#1930
0"
#1940
b100 F
1"
#1950
0"
#1960
b11 F
1"
#1970
0"
#1980
b10 F
1"
#1990
0"
#2000
b1 F
1"
#2010
0"
#2020
b0 F
1"
#2030
0"
#2040
b10000 F
0.
0-
0C
1"
#2050
0"
#2060
b1111 F
1"
#2070
0"
#2080
b1110 F
1"
#2090
0"
#2100
b1101 F
1"
#2110
0"
#2120
b1100 F
1"
#2130
0"
#2140
b1011 F
1"
#2150
0"
#2160
b1010 F
1"
#2170
0"
#2180
b1001 F
1"
#2190
0"
#2200
b1000 F
1"
#2210
0"
#2220
b111 F
1"
#2230
0"
#2240
b110 F
1"
#2250
0"
#2260
b101 F
1"
#2270
0"
#2280
b100 F
1"
#2290
0"
#2300
b11 F
1"
#2310
0"
#2320
b10 F
1"
#2330
0"
#2340
b1 F
1"
#2350
0"
#2360
b0 F
1"
#2370
0"
#2380
b1100 E
b10000 F
1.
1-
1C
1"
#2390
0"
#2400
b1111 F
1"
#2410
0"
#2420
b1110 F
1"
#2430
0"
#2440
b1101 F
1"
#2450
0"
#2460
b1100 F
1"
#2470
0"
#2480
b1011 F
1"
#2490
0"
#2500
b1010 F
1"
#2510
0"
#2520
b1001 F
1"
#2530
0"
#2540
b1000 F
1"
#2550
0"
#2560
b111 F
1"
#2570
0"
#2580
b110 F
1"
#2590
0"
#2600
b101 F
1"
#2610
0"
#2620
b100 F
1"
#2630
0"
#2640
b11 F
1"
#2650
0"
#2660
b10 F
1"
#2670
0"
#2680
b1 F
1"
#2690
0"
#2700
b0 F
1"
#2710
0"
#2720
b10000 F
0.
0-
0C
1"
#2730
0"
#2740
b1111 F
1"
#2750
0"
#2760
b1110 F
1"
#2770
0"
#2780
b1101 F
1"
#2790
0"
#2800
b1100 F
1"
#2810
0"
#2820
b1011 F
1"
#2830
0"
#2840
b1010 F
1"
#2850
0"
#2860
b1001 F
1"
#2870
0"
#2880
b1000 F
1"
#2890
0"
#2900
b111 F
1"
#2910
0"
#2920
b110 F
1"
#2930
0"
#2940
b101 F
1"
#2950
0"
#2960
b100 F
1"
#2970
0"
#2980
b11 F
1"
#2990
0"
#3000
b10 F
1"
#3010
0"
#3020
b1 F
1"
#3030
0"
#3040
b0 F
1"
#3050
0"
#3060
b1011 E
b10000 F
1.
1-
1C
1"
#3070
0"
#3080
b1111 F
1"
#3090
0"
#3100
b1110 F
1"
#3110
0"
#3120
b1101 F
1"
#3130
0"
#3140
b1100 F
1"
#3150
0"
#3160
b1011 F
1"
#3170
0"
#3180
b1010 F
1"
#3190
0"
#3200
b1001 F
1"
#3210
0"
#3220
b1000 F
1"
#3230
0"
#3240
b111 F
1"
#3250
0"
#3260
b110 F
1"
#3270
0"
#3280
b101 F
1"
#3290
0"
#3300
b100 F
1"
#3310
0"
#3320
b11 F
1"
#3330
0"
#3340
b10 F
1"
#3350
0"
#3360
b1 F
1"
#3370
0"
#3380
b0 F
1"
#3390
0"
#3400
b10000 F
0.
0-
0C
1"
#3410
0"
#3420
b1111 F
1"
#3430
0"
0'
0*
#3440
b1110 F
1"
#3450
0"
#3460
b1101 F
1"
#3470
0"
#3480
b1100 F
1"
#3490
0"
#3500
b1011 F
1"
#3510
0"
#3520
b1010 F
1"
#3530
0"
#3540
b1001 F
1"
#3550
0"
#3560
b1000 F
1"
#3570
0"
#3580
b111 F
1"
#3590
0"
#3600
b110 F
1"
#3610
0"
#3620
b101 F
1"
#3630
0"
#3640
b100 F
1"
#3650
0"
#3660
b11 F
1"
#3670
0"
#3680
b10 F
1"
#3690
0"
#3700
b1 F
1"
#3710
0"
#3720
b0 F
1"
#3730
0"
#3740
b1010 E
01
0D
b10000 F
1.
1-
1C
1"
#3750
0"
#3760
b1111 F
1"
#3770
0"
#3780
b1110 F
1"
#3790
0"
#3800
b1101 F
1"
#3810
0"
#3820
b1100 F
1"
#3830
0"
#3840
b1011 F
1"
#3850
0"
#3860
b1010 F
1"
#3870
0"
#3880
b1001 F
1"
#3890
0"
#3900
b1000 F
1"
#3910
0"
#3920
b111 F
1"
#3930
0"
#3940
b110 F
1"
#3950
0"
#3960
b101 F
1"
#3970
0"
#3980
b100 F
1"
#3990
0"
#4000
b11 F
1"
#4010
0"
#4020
b10 F
1"
#4030
0"
#4040
b1 F
1"
#4050
0"
#4060
b0 F
1"
#4070
0"
#4080
b10000 F
0.
0-
0C
1"
#4090
0"
#4100
b1111 F
1"
#4110
0"
#4120
b1110 F
1"
#4130
0"
#4140
b1101 F
1"
#4150
0"
#4160
b1100 F
1"
#4170
0"
#4180
b1011 F
1"
#4190
0"
#4200
b1010 F
1"
#4210
0"
#4220
b1001 F
1"
#4230
0"
#4240
b1000 F
1"
#4250
0"
#4260
b111 F
1"
#4270
0"
#4280
b110 F
1"
#4290
0"
#4300
b101 F
1"
#4310
0"
#4320
b100 F
1"
#4330
0"
#4340
b11 F
1"
#4350
0"
#4360
b10 F
1"
#4370
0"
#4380
b1 F
1"
#4390
0"
#4400
b0 F
1"
#4410
0"
#4420
b1001 E
b10000 F
1.
1-
1C
1"
#4430
0"
#4440
b1111 F
1"
#4450
0"
#4460
b1110 F
1"
#4470
0"
#4480
b1101 F
1"
#4490
0"
#4500
b1100 F
1"
#4510
0"
#4520
b1011 F
1"
#4530
0"
#4540
b1010 F
1"
#4550
0"
#4560
b1001 F
1"
#4570
0"
#4580
b1000 F
1"
#4590
0"
#4600
b111 F
1"
#4610
0"
#4620
b110 F
1"
#4630
0"
#4640
b101 F
1"
#4650
0"
#4660
b100 F
1"
#4670
0"
#4680
b11 F
1"
#4690
0"
#4700
b10 F
1"
#4710
0"
#4720
b1 F
1"
#4730
0"
#4740
b0 F
1"
#4750
0"
#4760
b10000 F
0.
0-
0C
1"
#4770
0"
#4780
b1111 F
1"
#4790
0"
#4800
b1110 F
1"
#4810
0"
#4820
b1101 F
1"
#4830
0"
#4840
b1100 F
1"
#4850
0"
#4860
b1011 F
1"
#4870
0"
#4880
b1010 F
1"
#4890
0"
#4900
b1001 F
1"
#4910
0"
#4920
b1000 F
1"
#4930
0"
#4940
b111 F
1"
#4950
0"
#4960
b110 F
1"
#4970
0"
#4980
b101 F
1"
#4990
0"
#5000
b100 F
1"
#5010
0"
#5020
b11 F
1"
#5030
0"
#5040
b10 F
1"
#5050
0"
#5060
b1 F
1"
#5070
0"
#5080
b0 F
1"
#5090
0"
#5100
b1000 E
b10000 F
1.
1-
1C
1"
#5110
0"
#5120
b1111 F
1"
#5130
0"
#5140
b1110 F
1"
#5150
0"
#5160
b1101 F
1"
#5170
0"
#5180
b1100 F
1"
#5190
0"
#5200
b1011 F
1"
#5210
0"
#5220
b1010 F
1"
#5230
0"
#5240
b1001 F
1"
#5250
0"
#5260
b1000 F
1"
#5270
0"
#5280
b111 F
1"
#5290
0"
#5300
b110 F
1"
#5310
0"
#5320
b101 F
1"
#5330
0"
#5340
b100 F
1"
#5350
0"
#5360
b11 F
1"
#5370
0"
#5380
b10 F
1"
#5390
0"
#5400
b1 F
1"
#5410
0"
#5420
b0 F
1"
#5430
0"
#5440
b10000 F
0.
0-
0C
1"
#5450
0"
#5460
b1111 F
1"
#5470
0"
#5480
b1110 F
1"
#5490
0"
#5500
b1101 F
1"
#5510
0"
#5520
b1100 F
1"
#5530
0"
#5540
b1011 F
1"
#5550
0"
#5560
b1010 F
1"
#5570
0"
#5580
b1001 F
1"
#5590
0"
#5600
b1000 F
1"
#5610
0"
#5620
b111 F
1"
#5630
0"
#5640
b110 F
1"
#5650
0"
#5660
b101 F
1"
#5670
0"
#5680
b100 F
1"
#5690
0"
#5700
b11 F
1"
#5710
0"
#5720
b10 F
1"
#5730
0"
#5740
b1 F
1"
#5750
0"
#5760
b0 F
1"
#5770
0"
#5780
b111 E
b10000 F
1.
1-
1C
1"
#5790
0"
#5800
b1111 F
1"
#5810
0"
#5820
b1110 F
1"
#5830
0"
#5840
b1101 F
1"
#5850
0"
#5860
b1100 F
1"
#5870
0"
#5880
b1011 F
1"
#5890
0"
#5900
b1010 F
1"
#5910
0"
#5920
b1001 F
1"
#5930
0"
#5940
b1000 F
1"
#5950
0"
#5960
b111 F
1"
#5970
0"
#5980
b110 F
1"
#5990
0"
#6000
b101 F
1"
#6010
0"
#6020
b100 F
1"
#6030
0"
#6040
b11 F
1"
#6050
0"
#6060
b10 F
1"
#6070
0"
#6080
b1 F
1"
#6090
0"
#6100
b0 F
1"
#6110
0"
#6120
b10000 F
0.
0-
0C
1"
#6130
0"
#6140
b1111 F
1"
#6150
0"
#6160
b1110 F
1"
#6170
0"
#6180
b1101 F
1"
#6190
0"
#6200
b1100 F
1"
#6210
0"
#6220
b1011 F
1"
#6230
0"
#6240
b1010 F
1"
#6250
0"
#6260
b1001 F
1"
#6270
0"
#6280
b1000 F
1"
#6290
0"
#6300
b111 F
1"
#6310
0"
#6320
b110 F
1"
#6330
0"
#6340
b101 F
1"
#6350
0"
#6360
b100 F
1"
#6370
0"
#6380
b11 F
1"
#6390
0"
#6400
b10 F
1"
#6410
0"
#6420
b1 F
1"
#6430
0"
#6440
b0 F
1"
#6450
0"
#6460
b110 E
b10000 F
1.
1-
1C
1"
#6470
0"
#6480
b1111 F
1"
#6490
0"
#6500
b1110 F
1"
#6510
0"
#6520
b1101 F
1"
#6530
0"
#6540
b1100 F
1"
#6550
0"
#6560
b1011 F
1"
#6570
0"
#6580
b1010 F
1"
#6590
0"
#6600
b1001 F
1"
#6610
0"
#6620
b1000 F
1"
#6630
0"
#6640
b111 F
1"
#6650
0"
#6660
b110 F
1"
#6670
0"
#6680
b101 F
1"
#6690
0"
#6700
b100 F
1"
#6710
0"
#6720
b11 F
1"
#6730
0"
#6740
b10 F
1"
#6750
0"
#6760
b1 F
1"
#6770
0"
#6780
b0 F
1"
#6790
0"
#6800
b10000 F
0.
0-
0C
1"
#6810
0"
#6820
b1111 F
1"
#6830
0"
#6840
b1110 F
1"
#6850
0"
#6860
b1101 F
1"
1'
1*
#6870
0"
#6880
b1100 F
1"
#6890
0"
#6900
b1011 F
1"
#6910
0"
#6920
b1010 F
1"
#6930
0"
#6940
b1001 F
1"
#6950
0"
#6960
b1000 F
1"
#6970
0"
#6980
b111 F
1"
#6990
0"
#7000
b110 F
1"
#7010
0"
#7020
b101 F
1"
#7030
0"
#7040
b100 F
1"
#7050
0"
#7060
b11 F
1"
#7070
0"
#7080
b10 F
1"
#7090
0"
#7100
b1 F
1"
#7110
0"
#7120
b0 F
1"
#7130
0"
#7140
b101 E
11
1D
b10000 F
1.
1-
1C
1"
#7150
0"
#7160
b1111 F
1"
#7170
0"
#7180
b1110 F
1"
#7190
0"
#7200
b1101 F
1"
#7210
0"
#7220
b1100 F
1"
#7230
0"
#7240
b1011 F
1"
#7250
0"
#7260
b1010 F
1"
#7270
0"
#7280
b1001 F
1"
#7290
0"
#7300
b1000 F
1"
#7310
0"
#7320
b111 F
1"
#7330
0"
#7340
b110 F
1"
#7350
0"
#7360
b101 F
1"
#7370
0"
#7380
b100 F
1"
#7390
0"
#7400
b11 F
1"
#7410
0"
#7420
b10 F
1"
#7430
0"
#7440
b1 F
1"
#7450
0"
#7460
b0 F
1"
#7470
0"
#7480
b10000 F
0.
0-
0C
1"
#7490
0"
#7500
b1111 F
1"
#7510
0"
#7520
b1110 F
1"
#7530
0"
#7540
b1101 F
1"
#7550
0"
#7560
b1100 F
1"
#7570
0"
#7580
b1011 F
1"
#7590
0"
#7600
b1010 F
1"
#7610
0"
#7620
b1001 F
1"
#7630
0"
#7640
b1000 F
1"
#7650
0"
#7660
b111 F
1"
#7670
0"
#7680
b110 F
1"
#7690
0"
#7700
b101 F
1"
#7710
0"
#7720
b100 F
1"
#7730
0"
#7740
b11 F
1"
#7750
0"
#7760
b10 F
1"
#7770
0"
#7780
b1 F
1"
#7790
0"
#7800
b0 F
1"
#7810
0"
#7820
b100 E
b10000 F
1.
1-
1C
1"
#7830
0"
#7840
b1111 F
1"
#7850
0"
#7860
b1110 F
1"
#7870
0"
#7880
b1101 F
1"
#7890
0"
#7900
b1100 F
1"
#7910
0"
#7920
b1011 F
1"
#7930
0"
#7940
b1010 F
1"
#7950
0"
#7960
b1001 F
1"
#7970
0"
#7980
b1000 F
1"
#7990
0"
#8000
b111 F
1"
#8010
0"
#8020
b110 F
1"
#8030
0"
#8040
b101 F
1"
#8050
0"
#8060
b100 F
1"
#8070
0"
#8080
b11 F
1"
#8090
0"
#8100
b10 F
1"
#8110
0"
#8120
b1 F
1"
#8130
0"
#8140
b0 F
1"
#8150
0"
#8160
b10000 F
0.
0-
0C
1"
#8170
0"
#8180
b1111 F
1"
#8190
0"
#8200
b1110 F
1"
#8210
0"
#8220
b1101 F
1"
#8230
0"
#8240
b1100 F
1"
#8250
0"
#8260
b1011 F
1"
#8270
0"
#8280
b1010 F
1"
#8290
0"
#8300
b1001 F
1"
#8310
0"
#8320
b1000 F
1"
#8330
0"
#8340
b111 F
1"
#8350
0"
#8360
b110 F
1"
#8370
0"
#8380
b101 F
1"
#8390
0"
#8400
b100 F
1"
#8410
0"
#8420
b11 F
1"
#8430
0"
#8440
b10 F
1"
#8450
0"
#8460
b1 F
1"
#8470
0"
#8480
b0 F
1"
#8490
0"
#8500
b11 E
b10000 F
1.
1-
1C
1"
#8510
0"
#8520
b1111 F
1"
#8530
0"
#8540
b1110 F
1"
#8550
0"
#8560
b1101 F
1"
#8570
0"
#8580
b1100 F
1"
#8590
0"
#8600
b1011 F
1"
#8610
0"
#8620
b1010 F
1"
#8630
0"
#8640
b1001 F
1"
#8650
0"
#8660
b1000 F
1"
#8670
0"
#8680
b111 F
1"
#8690
0"
#8700
b110 F
1"
#8710
0"
#8720
b101 F
1"
#8730
0"
#8740
b100 F
1"
#8750
0"
#8760
b11 F
1"
#8770
0"
#8780
b10 F
1"
#8790
0"
#8800
b1 F
1"
#8810
0"
#8820
b0 F
1"
#8830
0"
#8840
b10000 F
0.
0-
0C
1"
#8850
0"
#8860
b1111 F
1"
#8870
0"
#8880
b1110 F
1"
#8890
0"
#8900
b1101 F
1"
#8910
0"
#8920
b1100 F
1"
#8930
0"
#8940
b1011 F
1"
#8950
0"
#8960
b1010 F
1"
#8970
0"
#8980
b1001 F
1"
#8990
0"
#9000
b1000 F
1"
#9010
0"
#9020
b111 F
1"
#9030
0"
#9040
b110 F
1"
#9050
0"
#9060
b101 F
1"
#9070
0"
#9080
b100 F
1"
#9090
0"
#9100
b11 F
1"
#9110
0"
#9120
b10 F
1"
#9130
0"
#9140
b1 F
1"
#9150
0"
#9160
b0 F
1"
#9170
0"
#9180
b10 E
b10000 F
1.
1-
1C
1"
#9190
0"
#9200
b1111 F
1"
#9210
0"
#9220
b1110 F
1"
#9230
0"
#9240
b1101 F
1"
#9250
0"
#9260
b1100 F
1"
#9270
0"
#9280
b1011 F
1"
#9290
0"
#9300
b1010 F
1"
#9310
0"
#9320
b1001 F
1"
#9330
0"
#9340
b1000 F
1"
#9350
0"
#9360
b111 F
1"
#9370
0"
#9380
b110 F
1"
#9390
0"
#9400
b101 F
1"
#9410
0"
#9420
b100 F
1"
#9430
0"
#9440
b11 F
1"
#9450
0"
#9460
b10 F
1"
#9470
0"
#9480
b1 F
1"
#9490
0"
#9500
b0 F
1"
#9510
0"
#9520
b10000 F
0.
0-
0C
1"
#9530
0"
#9540
b1111 F
1"
#9550
0"
#9560
b1110 F
1"
#9570
0"
#9580
b1101 F
1"
#9590
0"
#9600
b1100 F
1"
#9610
0"
#9620
b1011 F
1"
#9630
0"
#9640
b1010 F
1"
#9650
0"
#9660
b1001 F
1"
#9670
0"
