HW/RTL/06PCM-AUDIO-MICROFONO/Version_01/02 verilog/prueb_mic.v
module prueb_mic
(
	input		enable,
	input		clk,
	output reg 	[17:0]  sdata,
	output		mclk,
	output		ws,
	input		dataint,
	input		reset,
	output		done

);

reg [0:31] count;
reg [17:0] sregt;
reg done=0;
reg ws=1;




always @(negedge  clk, posedge enable)

	if (enable && done<=0) 
	begin	
		count<=0;
		if (count<=17)
			begin
			sregt<= {sregt[16:0],dataint};
			count<=count+1;
			end
		
		else if(dataint<=1'b0)
			begin
				if(count<=31)
				begin		
				sdata<= sregt[17:0];
				count<=count+1;
				end
				else
				begin
				ws=!ws;
				count<=0;
				end								
			end	
		else
			begin
			sdata<=0;
			done=1;
				
		end	
						
	end	
	else
	begin
	end


endmodule

HW/RTL/06PCM-AUDIO-MICROFONO/Version_01/02 verilog/prueb_mic_TB.v
module prueb_mic_TB;

reg dataint;
reg clk;
reg enable;
reg mclk;
reg ws;
reg done;
reg reset;
prueb_mic  uut(.enable(enable),.reset(reset),.dataint(dataint),.clk(clk));

always
begin
clk =1'b1;
#2;
clk=1'b0;
#2;
end

always
begin
reset =1'b1;
#130;
reset =1'b0;
#130;
end

initial begin
enable=0;
#2 enable=1;
end 
initial begin
dataint = 1'b0;
#4 dataint = 1'b1;
#4 dataint = 1'b0;
#4 dataint = 1'b1;
#4 dataint = 1'b0;
#4 dataint = 1'b0;
#4 dataint = 1'b1;
#4 dataint = 1'b0;
#4 dataint = 1'b1;
#4 dataint = 1'b0;
#4 dataint = 1'b1;
#4 dataint = 1'b0;
#4 dataint = 1'b1;
#4 dataint = 1'b1;
#4 dataint = 1'b0;
#4 dataint = 1'b0;
#75 dataint = 1'b1;
#4 dataint = 1'b1;
#4 dataint = 1'b1;
#4 dataint = 1'b0;
#4 dataint = 1'b1;
#4 dataint = 1'b1;
#4 dataint = 1'b1;
#4 dataint = 1'b0;
#4 dataint = 1'b1;
#4 dataint = 1'b0;
#4 dataint = 1'b1;
#4 dataint = 1'b0;
#4 dataint = 1'b1;
#4 dataint = 1'b1;
#4 dataint = 1'b0;
#4 dataint = 1'b0;
end
	
initial begin: TEST_CASE
     $dumpfile("prueb_mic_TB.vcd");
     $dumpvars(-1, uut);
     #(300) $finish;
   end

endmodule //

HW/RTL/06PCM-AUDIO-MICROFONO/Version_01/02 verilog/simulation/prueb_mic_TB.vcd
$date
	Wed Oct  4 00:36:38 2017
$end
$version
	Icarus Verilog
$end
$timescale
	1s
$end
$scope module prueb_mic_TB $end
$scope module uut $end
$var wire 1 ! clk $end
$var wire 1 " dataint $end
$var wire 1 # enable $end
$var wire 1 $ mclk $end
$var wire 1 % reset $end
$var reg 32 & count [0:31] $end
$var reg 1 ' done $end
$var reg 18 ( sdata [17:0] $end
$var reg 18 ) sregt [17:0] $end
$var reg 1 * ws $end
$upscope $end
$upscope $end
$enddefinitions $end
#0
$dumpvars
1*
bx )
bx (
0'
bx &
1%
z$
0#
0"
1!
$end
#2
b0 &
0*
1#
0!
#4
1!
1"
#6
b1 &
bx1 )
0!
#8
1!
0"
#10
bx10 )
b10 &
0!
#12
1!
1"
#14
bx101 )
b11 &
0!
#16
1!
0"
#18
bx1010 )
b100 &
0!
#20
1!
#22
bx10100 )
b101 &
0!
#24
1!
1"
#26
bx101001 )
b110 &
0!
#28
1!
0"
#30
bx1010010 )
b111 &
0!
#32
1!
1"
#34
bx10100101 )
b1000 &
0!
#36
1!
0"
#38
bx101001010 )
b1001 &
0!
#40
1!
1"
#42
bx1010010101 )
b1010 &
0!
#44
1!
0"
#46
bx10100101010 )
b1011 &
0!
#48
1!
1"
#50
bx101001010101 )
b1100 &
0!
#52
1!
#54
bx1010010101011 )
b1101 &
0!
#56
1!
0"
#58
bx10100101010110 )
b1110 &
0!
#60
1!
#62
bx101001010101100 )
b1111 &
0!
#64
1!
#66
bx1010010101011000 )
b10000 &
0!
#68
1!
#70
bx10100101010110000 )
b10001 &
0!
#72
1!
#74
b101001010101100000 )
b10010 &
0!
#76
1!
#78
b101001010101100000 (
b10011 &
0!
#80
1!
#82
b10100 &
0!
#84
1!
#86
b10101 &
0!
#88
1!
#90
b10110 &
0!
#92
1!
#94
b10111 &
0!
#96
1!
#98
b11000 &
0!
#100
1!
#102
b11001 &
0!
#104
1!
#106
b11010 &
0!
#108
1!
#110
b11011 &
0!
#112
1!
#114
b11100 &
0!
#116
1!
#118
b11101 &
0!
#120
1!
#122
b11110 &
0!
#124
1!
#126
b11111 &
0!
#128
1!
#130
b100000 &
0!
0%
#132
1!
#134
b0 &
1*
0!
#135
1"
#136
1!
#138
b1 &
b10010101011000001 )
0!
#140
1!
#142
b100101010110000011 )
b10 &
0!
#144
1!
#146
b1010101100000111 )
b11 &
0!
#147
0"
#148
1!
#150
b10101011000001110 )
b100 &
0!
#151
1"
#152
1!
#154
b101010110000011101 )
b101 &
0!
#156
1!
#158
b10101100000111011 )
b110 &
0!
#160
1!
#162
b101011000001110111 )
b111 &
0!
#163
0"
#164
1!
#166
b10110000011101110 )
b1000 &
0!
#167
1"
#168
1!
#170
b101100000111011101 )
b1001 &
0!
#171
0"
#172
1!
#174
b11000001110111010 )
b1010 &
0!
#175
1"
#176
1!
#178
b110000011101110101 )
b1011 &
0!
#179
0"
#180
1!
#182
b100000111011101010 )
b1100 &
0!
#183
1"
#184
1!
#186
b1110111010101 )
b1101 &
0!
#188
1!
#190
b11101110101011 )
b1110 &
0!
#191
0"
#192
1!
#194
b111011101010110 )
b1111 &
0!
#196
1!
#198
b1110111010101100 )
b10000 &
0!
#200
1!
#202
b11101110101011000 )
b10001 &
0!
#204
1!
#206
b111011101010110000 )
b10010 &
0!
#208
1!
#210
b111011101010110000 (
b10011 &
0!
#212
1!
#214
b10100 &
0!
#216
1!
#218
b10101 &
0!
#220
1!
#222
b10110 &
0!
#224
1!
#226
b10111 &
0!
#228
1!
#230
b11000 &
0!
#232
1!
#234
b11001 &
0!
#236
1!
#238
b11010 &
0!
#240
1!
#242
b11011 &
0!
#244
1!
#246
b11100 &
0!
#248
1!
#250
b11101 &
0!
#252
1!
#254
b11110 &
0!
#256
1!
#258
b11111 &
0!
#260
1!
1%
#262
b100000 &
0!
#264
1!
#266
b0 &
0*
0!
#268
1!
#270
b1 &
b110111010101100000 )
0!
#272
1!
#274
b101110101011000000 )
b10 &
0!
#276
1!
#278
b11101010110000000 )
b11 &
0!
#280
1!
#282
b111010101100000000 )
b100 &
0!
#284
1!
#286
b110101011000000000 )
b101 &
0!
#288
1!
#290
b101010110000000000 )
b110 &
0!
#292
1!
#294
b10101100000000000 )
b111 &
0!
#296
1!
#298
b101011000000000000 )
b1000 &
0!
