HW/RTL/06PCM-AUDIO-MICROFONO/Version_01/02 verilog/prueb_mic.v
module prueb_mic
(
	input     enable,
	input 	  clk,
	output    [31:0]  sdata,
	output     mclk,
	output     ws,
	input     dataint,
	input reset,
	output    done

);

reg [17:0] count=18;
reg [17:0] sregt;
reg done=0;



always @(negedge  clk, posedge enable)

	if (enable) 
		if (count<=18)
		begin
		sregt<= {sregt[16:0],dataint};
		count<=count-1;
		end		
		else if(dataint<=0)
		done<=1;
	else 
	count<=1;


endmodule

HW/RTL/06PCM-AUDIO-MICROFONO/Version_01/02 verilog/prueb_mic_TB.v
module prueb_mic_TB;

reg [35:0] sdata;
reg dataint;
reg clk;
reg enable;
reg mclk;
reg ws;
reg done;
prueb_mic  uut(.enable(enable),.reset(reset),.dataint(dataint),.clk(clk));

always
begin
clk =1'b1;
#2;
clk=1'b0;
#2;
end

initial begin
enable=1;

#1 dataint = 1'b0;
#2 dataint = 1'b0;
#3 dataint = 1'b1;
#4 dataint = 1'b1;
#5 dataint = 1'b0;
#6 dataint = 1'b0;
#7 dataint = 1'b1;
#8 dataint = 1'b0;
#9 dataint = 1'b0;
#10 dataint = 1'b0;
#11 dataint = 1'b0;
#12 dataint = 1'b1;
#13 dataint = 1'b1;
#14 dataint = 1'b0;
#15 dataint = 1'b0;
#16 dataint = 1'b1;
#17 dataint = 1'b0;
#18 dataint = 1'b0;
end
	
initial begin: TEST_CASE
     $dumpfile("prueb_mic_TB.vcd");
     $dumpvars(-1, uut);
     #(200) $finish;
   end

endmodule //

HW/RTL/06PCM-AUDIO-MICROFONO/Version_01/02 verilog/simulation/prueb_mic_TB.vcd
$date
	Tue Oct  3 19:51:33 2017
$end
$version
	Icarus Verilog
$end
$timescale
	1s
$end
$scope module prueb_mic_TB $end
$scope module uut $end
$var wire 1 ! clk $end
$var wire 1 " dataint $end
$var wire 1 # enable $end
$var wire 1 $ mclk $end
$var wire 1 % reset $end
$var wire 32 & sdata [31:0] $end
$var wire 1 ' ws $end
$var reg 18 ( count [17:0] $end
$var reg 1 ) done $end
$var reg 18 * sregt [17:0] $end
$upscope $end
$upscope $end
$enddefinitions $end
#0
$dumpvars
bx *
0)
b10001 (
z'
bz &
z%
z$
1#
x"
1!
$end
#1
0"
#2
b10000 (
bx0 *
0!
#4
1!
#6
b1111 (
bx01 *
0!
1"
#8
1!
#10
b1110 (
bx011 *
0!
#12
1!
#14
b1101 (
bx0111 *
0!
#15
0"
#16
1!
#18
b1100 (
bx01110 *
0!
#20
1!
#22
b1011 (
bx011100 *
0!
#24
1!
#26
b1010 (
bx0111000 *
0!
#28
1!
1"
#30
b1001 (
bx01110001 *
0!
#32
1!
#34
b1000 (
bx011100011 *
0!
#36
1!
0"
#38
b111 (
bx0111000110 *
0!
#40
1!
#42
b110 (
bx01110001100 *
0!
#44
1!
#46
b101 (
bx011100011000 *
0!
#48
1!
#50
b100 (
bx0111000110000 *
0!
#52
1!
#54
b11 (
bx01110001100000 *
0!
#56
1!
#58
b10 (
bx011100011000000 *
0!
#60
1!
#62
b1 (
bx0111000110000000 *
0!
#64
1!
#66
b0 (
bx01110001100000000 *
0!
#68
1!
#70
b111111111111111111 (
b11100011000000000 *
0!
#72
1!
#74
1)
0!
#76
1!
#78
b1 (
0!
1"
#80
1!
#82
b0 (
b111000110000000001 *
0!
#84
1!
#86
b111111111111111111 (
b110001100000000011 *
0!
#88
1!
#90
b1 (
0!
#92
1!
#94
b0 (
b100011000000000111 *
0!
#96
1!
#98
b111111111111111111 (
b110000000001111 *
0!
#100
1!
#102
b1 (
0!
#104
1!
#105
0"
#106
b0 (
b1100000000011110 *
0!
#108
1!
#110
b111111111111111111 (
b11000000000111100 *
0!
#112
1!
#114
0!
#116
1!
#118
0!
#120
1!
#122
0!
#124
1!
#126
0!
#128
1!
#130
0!
#132
1!
#134
0!
#136
1!
1"
#138
b1 (
0!
#140
1!
#142
b0 (
b110000000001111001 *
0!
#144
1!
#146
b111111111111111111 (
b100000000011110011 *
0!
#148
1!
#150
b1 (
0!
#152
1!
#153
0"
#154
b0 (
b111100110 *
0!
#156
1!
#158
b111111111111111111 (
b1111001100 *
0!
