HW/RTL/06PCM-AUDIO-MICROFONO/Version_01/02 verilog/Microfono/div_freq.v
module div_freq #(
              parameter   fi     = 50000000 ,           
              parameter   fs	= 10000000        
  )(input clk, output reg clkout,input reset);





reg [15:0] count;

always @(posedge  clk)
begin
	if (reset) begin
		count <= fi/fs;
		clkout <=0;
	end
	else begin
		count <=count-1;
		if (count==0)begin
			clkout <=~clkout;
			count <= fi/fs;
		end	
	end	
end


endmodule

HW/RTL/06PCM-AUDIO-MICROFONO/Version_01/02 verilog/Microfono/microfono.v
module microfono
(
	input		enable,
	input		clk,
	output reg 	[17:0]  sdata,
	output		mclk,
	output		ws,
	input		dataint,
	input		reset,
	output		done

);

reg [0:31] count=
0;
reg [17:0] sregt;
reg done=0;
reg ws=0;


div_freq df(.clk(clk), .reset(reset),.clkout(mclk));

always @(negedge  mclk, posedge enable)

	if (enable) 
	begin	
		if (count<=17)
			begin
			sregt<= {sregt[17:0],dataint};
			count<=count+1;
			end		
			else if(dataint<=1'b0 && count<=30)
			begin		
			sdata<= sregt[17:0];
			count<=count+1;
			end
			else 
			begin
			count<=0;				
			ws=!ws;	
			end
	end	
	else
	done=1;


endmodule

HW/RTL/06PCM-AUDIO-MICROFONO/Version_01/02 verilog/Microfono/microfono_TB.v
module microfono_TB;

reg dataint;
reg clk;
reg enable;
reg mclk;
reg ws;
reg done;
reg reset;
microfono uut(.enable(enable),.reset(reset),.dataint(dataint),.clk(clk));

always
begin

clk =1'b1;
#2;
clk=1'b0;
#2;
end

initial
begin
reset =1'b1;
#10;
reset =1'b0;
end

initial begin
enable=0;
#2 enable=1;
end 
initial begin
dataint = 1'b0;
#4 dataint = 1'b1;
#4 dataint = 1'b0;
#4 dataint = 1'b1;
#4 dataint = 1'b0;
#4 dataint = 1'b0;
#4 dataint = 1'b1;
#4 dataint = 1'b0;
#4 dataint = 1'b1;
#4 dataint = 1'b0;
#4 dataint = 1'b1;
#4 dataint = 1'b0;
#4 dataint = 1'b1;
#4 dataint = 1'b1;
#4 dataint = 1'b0;
#4 dataint = 1'b0;
#70 dataint = 1'b1;
#4 dataint = 1'b1;
#4 dataint = 1'b1;
#4 dataint = 1'b0;
#4 dataint = 1'b1;
#4 dataint = 1'b1;
#4 dataint = 1'b1;
#4 dataint = 1'b0;
#4 dataint = 1'b1;
#4 dataint = 1'b0;
#4 dataint = 1'b1;
#4 dataint = 1'b0;
#4 dataint = 1'b1;
#4 dataint = 1'b1;
#4 dataint = 1'b0;
#4 dataint = 1'b0;
end
	
initial begin: TEST_CASE
     $dumpfile("microfono_TB.vcd");
     $dumpvars(-1, uut);
     #(300) $finish;
   end

endmodule //

HW/RTL/06PCM-AUDIO-MICROFONO/Version_01/02 verilog/Microfono/simulation/microfono_TB.vcd
$date
	Wed Oct  4 11:43:40 2017
$end
$version
	Icarus Verilog
$end
$timescale
	1s
$end
$scope module microfono_TB $end
$scope module uut $end
$var wire 1 ! clk $end
$var wire 1 " dataint $end
$var wire 1 # enable $end
$var wire 1 $ reset $end
$var wire 1 % mclk $end
$var reg 32 & count [0:31] $end
$var reg 1 ' done $end
$var reg 18 ( sdata [17:0] $end
$var reg 18 ) sregt [17:0] $end
$var reg 1 * ws $end
$scope module df $end
$var wire 1 ! clk $end
$var wire 1 $ reset $end
$var reg 1 % clkout $end
$var reg 16 + count [15:0] $end
$upscope $end
$upscope $end
$upscope $end
$enddefinitions $end
#0
$dumpvars
b101 +
0*
bx )
bx (
1'
b0 &
0%
1$
0#
0"
1!
$end
#2
b1 &
bx0 )
1#
0!
#4
1!
1"
#6
0!
#8
1!
0"
#10
0!
0$
#12
b100 +
1!
1"
#14
0!
#16
b11 +
1!
0"
#18
0!
#20
b10 +
1!
#22
0!
#24
b1 +
1!
1"
#26
0!
#28
b0 +
1!
0"
#30
0!
#32
1%
b101 +
1!
1"
#34
0!
#36
b100 +
1!
0"
#38
0!
#40
b11 +
1!
1"
#42
0!
#44
b10 +
1!
0"
#46
0!
#48
b1 +
1!
1"
#50
0!
#52
b0 +
1!
#54
0!
#56
b10 &
bx00 )
0%
b101 +
1!
0"
#58
0!
#60
b100 +
1!
#62
0!
#64
b11 +
1!
#66
0!
#68
b10 +
1!
#70
0!
#72
b1 +
1!
#74
0!
#76
b0 +
1!
#78
0!
#80
1%
b101 +
1!
#82
0!
#84
b100 +
1!
#86
0!
#88
b11 +
1!
#90
0!
#92
b10 +
1!
#94
0!
#96
b1 +
1!
#98
0!
#100
b0 +
1!
#102
0!
#104
b11 &
bx000 )
0%
b101 +
1!
#106
0!
#108
b100 +
1!
#110
0!
#112
b11 +
1!
#114
0!
#116
b10 +
1!
#118
0!
#120
b1 +
1!
#122
0!
#124
b0 +
1!
#126
0!
#128
1%
b101 +
1!
#130
0!
1"
#132
b100 +
1!
#134
0!
#136
b11 +
1!
#138
0!
#140
b10 +
1!
#142
0!
0"
#144
b1 +
1!
#146
0!
1"
#148
b0 +
1!
#150
0!
#152
b100 &
bx0001 )
0%
b101 +
1!
#154
0!
#156
b100 +
1!
#158
0!
0"
#160
b11 +
1!
#162
0!
1"
#164
b10 +
1!
#166
0!
0"
#168
b1 +
1!
#170
0!
1"
#172
b0 +
1!
#174
0!
0"
#176
1%
b101 +
1!
#178
0!
1"
#180
b100 +
1!
#182
0!
#184
b11 +
1!
#186
0!
0"
#188
b10 +
1!
#190
0!
#192
b1 +
1!
#194
0!
#196
b0 +
1!
#198
0!
#200
b101 &
bx00010 )
0%
b101 +
1!
#202
0!
#204
b100 +
1!
#206
0!
#208
b11 +
1!
#210
0!
#212
b10 +
1!
#214
0!
#216
b1 +
1!
#218
0!
#220
b0 +
1!
#222
0!
#224
1%
b101 +
1!
#226
0!
#228
b100 +
1!
#230
0!
#232
b11 +
1!
#234
0!
#236
b10 +
1!
#238
0!
#240
b1 +
1!
#242
0!
#244
b0 +
1!
#246
0!
#248
b110 &
bx000100 )
0%
b101 +
1!
#250
0!
#252
b100 +
1!
#254
0!
#256
b11 +
1!
#258
0!
#260
b10 +
1!
#262
0!
#264
b1 +
1!
#266
0!
#268
b0 +
1!
#270
0!
#272
1%
b101 +
1!
#274
0!
#276
b100 +
1!
#278
0!
#280
b11 +
1!
#282
0!
#284
b10 +
1!
#286
0!
#288
b1 +
1!
#290
0!
#292
b0 +
1!
#294
0!
#296
b111 &
bx0001000 )
0%
b101 +
1!
#298
0!
#300
b100 +
1!
