HW/RTL/06PCM-AUDIO-MICROFONO/Version_01/02 verilog/Prueba1/div_freq.v
module div_freq #(
              parameter   fi     = 50000000,        //<- fFPGA/2=fi  
              parameter   fs	 = 3125000        //<- flckout=fs
  )(input clk, output reg clkout,input reset, output reg led);



initial led=0;

reg [31:0] count;

always @(posedge  clk)
begin
	if (reset) begin
	led=1;
		count <=count-1;
		if (count==0)begin
			clkout <=~clkout;
			count <= fi/fs;
		end	

	end
	else begin
	led=0;
		count <= fi/fs;
		clkout <=0;
	end	
end


endmodule

HW/RTL/06PCM-AUDIO-MICROFONO/Version_01/02 verilog/Prueba5/pwm.v
module pwm
(
	input 		reset,	
	output 		ledres,
	input		clk,
	output		mclk,
        input           micData,    
        output    reg   ampPWM,
        output    reg	ampSD,
	input     [7:0] dout
 

);


reg [3:0] count;
initial ampSD <= 1;


always @(posedge  mclk)
begin
count<=0;
	if (reset)
		begin
     		ampPWM<=0;
    		end 
	else 
		begin
		if (count<=7)
			begin
			ampPWM<=dout[count];
			count<=count+1;
			end
		else
			begin
			count<=0;
			end
		end
	
	
end

endmodule

HW/RTL/06PCM-AUDIO-MICROFONO/Version_01/02 verilog/Prueba5/fifo.v
module fifo # (parameter abits = 1, dbits = 8)(
    input  reset, clock,
    input  rd, wr,
    input  [dbits-1:0] din,
    output [dbits-1:0] dout,
    output empty,
    output full
    //output reg ledres
    );



wire db_wr, db_rd;
reg dffw1, dffw2, dffr1, dffr2;
reg [dbits-1:0] out;
//initial ledres = 0;

always @ (posedge clock) dffw1 <= wr; 
always @ (posedge clock) dffw2 <= dffw1;
 
assign db_wr = ~dffw1 & dffw2; //monostable multivibrator to detect only one pulse of the button
 
always @ (posedge clock) dffr1 <= rd;
always @ (posedge clock) dffr2 <= dffr1;
 
assign db_rd = ~dffr1 & dffr2; //monostable multivibrator to detect only one pulse of the button
 
 
reg [dbits-1:0] regarray[2**abits-1:0]; //number of words in fifo = 2^(number of address bits)
reg [abits-1:0] wr_reg, wr_next, wr_succ; //points to the register that needs to be written to
reg [abits-1:0] rd_reg, rd_next, rd_succ; //points to the register that needs to be read from
reg full_reg, empty_reg, full_next, empty_next;
 
assign wr_en = db_wr & ~full; //only write if write signal is high and fifo is not full
 
//always block for write operation
always @ (posedge clock)
 begin
  if(wr_en)
   regarray[wr_reg] <= din;  //at wr_reg location of regarray store what is given at din
 
 end
  
//always block for read operation
always @ (posedge clock)
 begin
  if(db_rd)
   out <= regarray[rd_reg];
 end

always @ (posedge clock or posedge reset)
 begin
  if (reset)
   begin
   
   wr_reg <= 0;
   rd_reg <= 0;
   full_reg <= 1'b0;
   empty_reg <= 1'b1;
  // ledres=0;
   end
   
  else
   begin
   wr_reg <= wr_next; //created the next registers to avoid the error of mixing blocking and non blocking assignment to the same signal
   rd_reg <= rd_next;
   full_reg <= full_next;
   empty_reg <= empty_next;
   //ledres=1;
   end
 end
  
always @(*)
 begin
  wr_succ = wr_reg + 1; //assigned to new value as wr_next cannot be tested for in same always block
  rd_succ = rd_reg + 1; //assigned to new value as rd_next cannot be tested for in same always block
  wr_next = wr_reg;  //defaults state stays the same
  rd_next = rd_reg;  //defaults state stays the same
  full_next = full_reg;  //defaults state stays the same
  empty_next = empty_reg;  //defaults state stays the same
   
   case({db_wr,db_rd})
    //2'b00: do nothing LOL..
     
    2'b01: //read
     begin
      if(~empty) //if fifo is not empty continue
       begin
        rd_next = rd_succ;
        full_next = 1'b0;
       if(rd_succ == wr_reg) //all data has been read
         empty_next = 1'b1;  //its empty again
       end
     end
2'b10: //write
     begin
       
      if(~full) //if fifo is not full continue
       begin
        wr_next = wr_succ;
        empty_next = 1'b0;
        if(wr_succ == (2**abits-1)) //all registers have been written to
         full_next = 1'b1;   //its full now
       end
     end
      
    2'b11: //read and write
     begin
      wr_next = wr_succ;
      rd_next = rd_succ;
     end
     //no empty or full flag will be checked for or asserted in this state since data is being written to and read from together it can  not get full in this state.
    endcase
    
 
 end
 
assign full = full_reg;
assign empty = empty_reg;
assign dout = out;
endmodule

HW/RTL/06PCM-AUDIO-MICROFONO/Version_01/02 verilog/Prueba5/microfono.v
module microfono
(
	input 		reset,	
	output 		ledres,
	input		clk,
	output		mclk,
	output    reg   micLRSel,
        input           micData,    
        output          ampPWM,
        output          ampSD,
	input		rd,wr,
	output		empty,
	output		full,
	output reg	done
	//output 	  [7:0] dout,
	 

);

wire [7:0] dout;
wire [7:0] dout1;
wire mclk1;
wire mclk2;
assign mclk3=mclk2;
assign mclk2=mclk1;
assign mclk=mclk1;
reg [7:0] sregt1;

reg [7:0] sregt;

fifo fi(.reset(reset),.din(sregt1),.dout(dout),.clock(done),.rd(rd),.wr(wr),.empty(empty),.full(full));
pwm pw(.ampSD(ampSD), .reset(reset),.mclk(mclk2),.ampPWM(ampPWM),.clk(clk),.dout(dout1));
div_freq df(.clk(clk), .reset(reset),.clkout(mclk1),.led(ledres));


reg [7:0] count;


assign dout1=dout;

initial micLRSel <= 0;
initial count <= 0;
initial sregt <= 0;
initial sregt1 <= 0;

always @(posedge  mclk)
begin

	if (reset)
		begin
     		sregt<=0;
    		end 
	else 
		begin
		if(count<=7)
			begin
			sregt<= {sregt[7:0],micData};	
			count<=count+1;	
			done<=0;
			end
			else		
			begin
			count<=0;
			done<=1;
			sregt1<=sregt;
			end
		end
	
	
end

endmodule

HW/RTL/06PCM-AUDIO-MICROFONO/Version_01/02 verilog/Prueba5/microfono_TB.v

module microfono_TB;

reg reset, clk, micData,rd,wr;  
   

microfono uut(.reset(reset),.micData(micData),.clk(clk),.rd(rd),.wr(wr));

always
begin

clk =1'b1;
#2;
clk=1'b0;
#2;
end

initial
begin
reset =1'b1;
#10;
reset =1'b0;
end

initial
begin
rd = 1'b0;
wr = 1'b0;
#100 wr = 1'b1;
#150 wr = 1'b0;
#150 wr = 1'b1;
#150 wr = 1'b0;
#150 wr = 1'b1;
#150 wr = 1'b0;
#150 wr = 1'b1;
#150 wr = 1'b0;
#150 wr = 1'b1;
#150 wr = 1'b0;
#150 wr = 1'b1;
#150 wr = 1'b0;
#150 wr = 1'b1;
#150 wr = 1'b0;
#150 wr = 1'b1;
#150 wr = 1'b0;
#150 wr = 1'b1;
#150 wr = 1'b0;
#150 wr = 1'b1;
#150 wr = 1'b0;
#150 wr = 1'b1;
#150 wr = 1'b0;
#150 wr = 1'b1;
#150 wr = 1'b0;
#150 wr = 1'b1;
#150 wr = 1'b0;
#150 wr = 1'b1;
#150 wr = 1'b0;
#150 wr = 1'b1;
#150 wr = 1'b0;



#150 rd = 1'b1;
#150 rd = 1'b0;
#150 rd = 1'b1;
#150 rd = 1'b0;
#150 rd = 1'b1;
#150 rd = 1'b0;
#150 rd = 1'b1;
#150 rd = 1'b0;
#150 rd = 1'b1;
#150 rd = 1'b0;
#150 rd = 1'b1;
#150 rd = 1'b0;
#150 rd = 1'b1;
#150 rd = 1'b0;
#150 rd = 1'b1;
#150 rd = 1'b0;
#150 rd = 1'b1;
#150 rd = 1'b0;
#150 rd = 1'b1;
#150 rd = 1'b0;
#150 rd = 1'b1;
#150 rd = 1'b0;
#150 rd = 1'b1;
#150 rd = 1'b0;
#150 rd = 1'b1;
#150 rd = 1'b0;
#150 rd = 1'b1;
#150 rd = 1'b0;
#150 rd = 1'b1;
#150 rd = 1'b0;
#150 rd = 1'b1;
#150 rd = 1'b0;
#150 rd = 1'b1;
#150 rd = 1'b0;
#150 rd = 1'b1;
end


initial begin
micData = 1'b0;
#100 micData = 1'b1;
#150 micData = 1'b0;
#150 micData = 1'b1;
#150 micData = 1'b0;
#150 micData = 1'b0;
#150 micData = 1'b1;
#150 micData = 1'b0;
#150 micData = 1'b1;
#150 micData = 1'b0;
#150 micData = 1'b1;
#150 micData = 1'b0;
#150 micData = 1'b0;
#150 micData = 1'b1;
#150 micData = 1'b0;
#150 micData = 1'b1;
#150 micData = 1'b0;
#150 micData = 1'b1;
#150 micData = 1'b0;
#150 micData = 1'b0;
#150 micData = 1'b1;
#150 micData = 1'b0;
#150 micData = 1'b1;
end
	
initial begin: TEST_CASE
     $dumpfile("microfono_TB.vcd");
     $dumpvars(-1, uut);
     #(10000) $finish;
   end

endmodule //

HW/RTL/06PCM-AUDIO-MICROFONO/Version_01/02 verilog/Prueba5/simulation/microfono_TB.vcd
$date
	Wed Nov 22 02:06:00 2017
$end
$version
	Icarus Verilog
$end
$timescale
	1s
$end
$scope module microfono_TB $end
$scope module uut $end
$var wire 1 ! clk $end
$var wire 8 " dout1 [7:0] $end
$var wire 1 # mclk $end
$var wire 1 $ mclk2 $end
$var wire 1 % mclk3 $end
$var wire 1 & micData $end
$var wire 1 ' rd $end
$var wire 1 ( reset $end
$var wire 1 ) wr $end
$var wire 1 * mclk1 $end
$var wire 1 + ledres $end
$var wire 1 , full $end
$var wire 1 - empty $end
$var wire 8 . dout [7:0] $end
$var wire 1 / ampSD $end
$var wire 1 0 ampPWM $end
$var reg 8 1 count [7:0] $end
$var reg 1 2 done $end
$var reg 1 3 micLRSel $end
$var reg 8 4 sregt [7:0] $end
$var reg 8 5 sregt1 [7:0] $end
$scope module df $end
$var wire 1 ! clk $end
$var wire 1 ( reset $end
$var reg 1 * clkout $end
$var reg 32 6 count [31:0] $end
$var reg 1 + led $end
$upscope $end
$scope module fi $end
$var wire 1 2 clock $end
$var wire 1 7 db_rd $end
$var wire 1 8 db_wr $end
$var wire 8 9 din [7:0] $end
$var wire 1 - empty $end
$var wire 1 ' rd $end
$var wire 1 ( reset $end
$var wire 1 ) wr $end
$var wire 1 : wr_en $end
$var wire 1 , full $end
$var wire 8 ; dout [7:0] $end
$var reg 1 < dffr1 $end
$var reg 1 = dffr2 $end
$var reg 1 > dffw1 $end
$var reg 1 ? dffw2 $end
$var reg 1 @ empty_next $end
$var reg 1 A empty_reg $end
$var reg 1 B full_next $end
$var reg 1 , full_reg $end
$var reg 8 C out [7:0] $end
$var reg 6 D rd_next [5:0] $end
$var reg 6 E rd_reg [5:0] $end
$var reg 6 F rd_succ [5:0] $end
$var reg 6 G wr_next [5:0] $end
$var reg 6 H wr_reg [5:0] $end
$var reg 6 I wr_succ [5:0] $end
$upscope $end
$scope module pw $end
$var wire 1 ! clk $end
$var wire 8 J dout [7:0] $end
$var wire 1 K ledres $end
$var wire 1 $ mclk $end
$var wire 1 L micData $end
$var wire 1 ( reset $end
$var reg 1 0 ampPWM $end
$var reg 1 / ampSD $end
$var reg 4 M count [3:0] $end
$upscope $end
$upscope $end
$upscope $end
$enddefinitions $end
#0
$dumpvars
bx M
zL
zK
bx J
b1 I
b0 H
b0 G
b1 F
b0 E
b0 D
bx C
0B
1A
1@
x?
x>
x=
x<
bx ;
x:
b0 9
x8
x7
b10000 6
b0 5
b0 4
03
x2
b0 1
x0
1/
bx .
1-
0,
0+
0*
0)
1(
0'
0&
0%
0$
0#
bx "
1!
$end
#2
0!
#4
1!
#6
0!
#8
1!
#10
0!
0(
#12
b1111 6
1+
1!
#14
0!
#16
b1110 6
1!
#18
0!
#20
b1101 6
1!
#22
0!
#24
b1100 6
1!
#26
0!
#28
b1011 6
1!
#30
0!
#32
b1010 6
1!
#34
0!
#36
b1001 6
1!
#38
0!
#40
b1000 6
1!
#42
0!
#44
b111 6
1!
#46
0!
#48
b110 6
1!
#50
0!
#52
b101 6
1!
#54
0!
#56
b100 6
1!
#58
0!
#60
b11 6
1!
#62
0!
#64
b10 6
1!
1&
#66
0!
#68
b1 6
1!
#70
0!
#72
b0 6
1!
#74
0!
#76
02
b1 1
b1 4
b0 M
b10000 6
1#
1%
1$
1*
1!
#78
0!
#80
b1111 6
1!
#82
0!
#84
b1110 6
1!
#86
0!
#88
b1101 6
1!
#90
0!
#92
b1100 6
1!
#94
0!
#96
b1011 6
1!
#98
0!
#100
b1010 6
1!
#102
0!
#104
b1001 6
1!
#106
0!
#108
b1000 6
1!
#110
0!
#112
b111 6
1!
#114
0!
#116
b110 6
1!
#118
0!
#120
b101 6
1!
#122
0!
#124
b100 6
1!
#126
0!
#128
b11 6
1!
#130
0!
#132
b10 6
1!
#134
0!
#136
b1 6
1!
#138
0!
#140
b0 6
1!
#142
0!
#144
b10000 6
0#
0%
0$
0*
1!
0&
#146
0!
#148
b1111 6
1!
#150
0!
#152
b1110 6
1!
#154
0!
#156
b1101 6
1!
#158
0!
#160
b1100 6
1!
#162
0!
#164
b1011 6
1!
#166
0!
#168
b1010 6
1!
#170
0!
#172
b1001 6
1!
#174
0!
#176
b1000 6
1!
#178
0!
#180
b111 6
1!
#182
0!
#184
b110 6
1!
#186
0!
#188
b101 6
1!
#190
0!
#192
b100 6
1!
#194
0!
#196
b11 6
1!
#198
0!
#200
b10 6
1!
#202
0!
#204
b1 6
1!
#206
0!
#208
b0 6
1!
#210
0!
#212
b10 1
b10 4
b1 M
b10000 6
1#
1%
1$
1*
1!
#214
0!
#216
b1111 6
1!
#218
0!
#219
1&
#220
b1110 6
1!
#222
0!
#224
b1101 6
1!
#226
0!
#228
b1100 6
1!
#230
0!
#232
b1011 6
1!
#234
0!
#236
b1010 6
1!
#238
0!
#240
b1001 6
1!
#242
0!
#244
b1000 6
1!
#246
0!
#248
b111 6
1!
#250
0!
#252
b110 6
1!
#253
0&
#254
0!
#256
b101 6
1!
#258
0!
#260
b100 6
1!
#262
0!
#264
b11 6
1!
#266
0!
#268
b10 6
1!
#270
0!
#272
b1 6
1!
#274
0!
#276
b0 6
1!
#278
0!
#280
b10000 6
0#
0%
0$
0*
1!
#282
0!
#284
b1111 6
1!
#286
0!
#288
b1110 6
1!
#290
0!
#292
b1101 6
1!
#294
0!
#296
b1100 6
1!
#298
0!
#300
b1011 6
1!
#302
0!
#304
b1010 6
1!
#306
0!
#308
b1001 6
1!
#310
0!
#312
b1000 6
1!
#314
0!
#316
b111 6
1!
#318
0!
#320
b110 6
1!
#322
0!
#324
b101 6
1!
#326
0!
#328
b100 6
1!
1&
#330
0!
#332
b11 6
1!
#334
0!
#336
b10 6
1!
#338
0!
#340
b1 6
1!
#342
0!
#344
b0 6
1!
#346
0!
#348
b11 1
b101 4
b10 M
b10000 6
1#
1%
1$
1*
1!
#350
0!
#352
b1111 6
1!
#354
0!
#356
b1110 6
1!
#358
0!
#360
b1101 6
1!
#362
0!
#364
b1100 6
1!
#366
0!
#368
b1011 6
1!
#370
0!
#372
b1010 6
1!
#374
0!
#376
b1001 6
1!
#378
0!
#380
b1000 6
1!
#382
0!
#384
b111 6
1!
#386
0!
#388
b110 6
1!
#390
0!
#392
b101 6
1!
#394
0!
#396
b100 6
1!
#398
0!
#400
b11 6
1!
#402
0!
#404
b10 6
1!
#406
0!
#408
b1 6
1!
0&
#410
0!
#412
b0 6
1!
#414
0!
#416
b10000 6
0#
0%
0$
0*
1!
#418
0!
#420
b1111 6
1!
#422
0!
#424
b1110 6
1!
#426
0!
#428
b1101 6
1!
#430
0!
#432
b1100 6
1!
#434
0!
#436
b1011 6
1!
#438
0!
#440
b1010 6
1!
#442
0!
#444
b1001 6
1!
#446
0!
#448
b1000 6
1!
#450
0!
#452
b111 6
1!
#454
0!
#456
b110 6
1!
#458
0!
#460
b101 6
1!
#462
0!
#464
b100 6
1!
#466
0!
#468
b11 6
1!
#470
0!
#472
b10 6
1!
#474
0!
#476
b1 6
1!
#478
0!
#480
b0 6
1!
#482
0!
#484
b100 1
b1010 4
b11 M
b10000 6
1#
1%
1$
1*
1!
#486
0!
#488
b1111 6
1!
#490
0!
#492
b1110 6
1!
#494
0!
#496
b1101 6
1!
#498
0!
#500
b1100 6
1!
#502
0!
#504
b1011 6
1!
#506
0!
#508
b1010 6
1!
#510
0!
#512
b1001 6
1!
#514
0!
#516
b1000 6
1!
#518
0!
#520
b111 6
1!
#522
0!
#524
b110 6
1!
#526
0!
#528
b101 6
1!
#530
0!
#532
b100 6
1!
#534
0!
#536
b11 6
1!
#538
0!
#540
b10 6
1!
#542
0!
#544
b1 6
1!
#546
0!
#548
b0 6
1!
#550
0!
#552
b10000 6
0#
0%
0$
0*
1!
#554
0!
#556
b1111 6
1!
#558
0!
#560
b1110 6
1!
#562
0!
#564
b1101 6
1!
#566
0!
#568
b1100 6
1!
#570
0!
#572
b1011 6
1!
#574
0!
#576
b1010 6
1!
#578
0!
#580
b1001 6
1!
#582
0!
#584
b1000 6
1!
#586
0!
#588
b111 6
1!
#590
0!
#592
b110 6
1!
#594
0!
#596
b101 6
1!
#598
0!
#600
b100 6
1!
#602
0!
#604
b11 6
1!
#606
0!
#608
b10 6
1!
#610
0!
#612
b1 6
1!
#614
0!
#616
b0 6
1!
#618
0!
#620
b101 1
b10100 4
b100 M
b10000 6
1#
1%
1$
1*
1!
#622
0!
#624
b1111 6
1!
#626
0!
#628
b1110 6
1!
#630
0!
#632
b1101 6
1!
#634
0!
#636
b1100 6
1!
#638
0!
#640
b1011 6
1!
#642
0!
#644
b1010 6
1!
#646
0!
#648
b1001 6
1!
#650
0!
#652
b1000 6
1!
#654
0!
#656
b111 6
1!
#658
0!
#660
b110 6
1!
#662
0!
#664
b101 6
1!
#666
0!
#668
b100 6
1!
#670
0!
#672
b11 6
1!
#674
0!
#676
b10 6
1!
#678
0!
#680
b1 6
1!
#682
0!
#684
b0 6
1!
#686
0!
#688
b10000 6
0#
0%
0$
0*
1!
#690
0!
#692
b1111 6
1!
#694
0!
#696
b1110 6
1!
#698
0!
#700
b1101 6
1!
#702
0!
#704
b1100 6
1!
#706
0!
#708
b1011 6
1!
#710
0!
#712
b1010 6
1!
#714
0!
#716
b1001 6
1!
#718
0!
#720
b1000 6
1!
#722
0!
#724
b111 6
1!
#726
0!
#728
b110 6
1!
#730
0!
#732
b101 6
1!
#734
0!
#736
b100 6
1!
#738
0!
#740
b11 6
1!
#742
0!
#744
b10 6
1!
#746
0!
#748
b1 6
1!
#750
0!
#752
b0 6
1!
#754
0!
#756
b110 1
b101000 4
b101 M
b10000 6
1#
1%
1$
1*
1!
#758
0!
#760
b1111 6
1!
#762
0!
#764
b1110 6
1!
#766
0!
#768
b1101 6
1!
#770
0!
#772
b1100 6
1!
#774
0!
#776
b1011 6
1!
#778
0!
#780
b1010 6
1!
#782
0!
#784
b1001 6
1!
#786
0!
#788
b1000 6
1!
#790
0!
#792
b111 6
1!
#794
0!
#796
b110 6
1!
#798
0!
#800
b101 6
1!
#802
0!
#804
b100 6
1!
#806
0!
#808
b11 6
1!
#810
0!
#812
b10 6
1!
#814
0!
#816
b1 6
1!
#818
0!
#820
b0 6
1!
#822
0!
#824
b10000 6
0#
0%
0$
0*
1!
#826
0!
#828
b1111 6
1!
#830
0!
#832
b1110 6
1!
#834
0!
#836
b1101 6
1!
#838
0!
#840
b1100 6
1!
#842
0!
#844
b1011 6
1!
#846
0!
#848
b1010 6
1!
#850
0!
#852
b1001 6
1!
#854
0!
#856
b1000 6
1!
#858
0!
#860
b111 6
1!
#862
0!
#864
b110 6
1!
#866
0!
#868
b101 6
1!
#870
0!
#872
b100 6
1!
#874
0!
#876
b11 6
1!
#878
0!
#880
b10 6
1!
#882
0!
#884
b1 6
1!
#886
0!
#888
b0 6
1!
#890
0!
#892
b111 1
b1010000 4
b110 M
b10000 6
1#
1%
1$
1*
1!
#894
0!
#896
b1111 6
1!
#898
0!
#900
b1110 6
1!
#902
0!
#904
b1101 6
1!
#906
0!
#908
b1100 6
1!
#910
0!
#912
b1011 6
1!
#914
0!
#916
b1010 6
1!
#918
0!
#920
b1001 6
1!
#922
0!
#924
b1000 6
1!
#926
0!
#928
b111 6
1!
#930
0!
#932
b110 6
1!
#933
1&
#934
0!
#936
b101 6
1!
#938
0!
#940
b100 6
1!
#942
0!
#944
b11 6
1!
#946
0!
#948
b10 6
1!
#950
0!
#952
b1 6
1!
#954
0!
#956
b0 6
1!
#958
0!
#960
b10000 6
0#
0%
0$
0*
1!
#962
0!
#964
b1111 6
1!
#966
0!
#968
b1110 6
1!
#970
0!
#972
b1101 6
1!
#974
0!
#976
b1100 6
1!
#978
0!
#980
b1011 6
1!
#982
0!
#984
b1010 6
1!
#986
0!
#988
b1001 6
1!
#990
0!
#992
b1000 6
1!
#994
0!
#996
b111 6
1!
#998
0!
#1000
b110 6
1!
1)
#1002
0!
#1004
b101 6
1!
#1006
0!
#1008
b100 6
1!
#1010
0!
#1012
b11 6
1!
#1014
0!
#1016
b10 6
1!
#1018
0!
#1020
b1 6
1!
#1022
0!
#1024
b0 6
1!
#1026
0!
#1028
b1000 1
b10100001 4
b111 M
b10000 6
1#
1%
1$
1*
1!
#1030
0!
#1032
b1111 6
1!
#1033
0&
#1034
0!
#1036
b1110 6
1!
#1038
0!
#1040
b1101 6
1!
#1042
0!
#1044
b1100 6
1!
#1046
0!
#1048
b1011 6
1!
#1050
0!
#1052
b1010 6
1!
#1054
0!
#1056
b1001 6
1!
#1058
0!
#1060
b1000 6
1!
#1062
0!
#1064
b111 6
1!
#1066
0!
#1068
b110 6
1!
#1070
0!
#1072
b101 6
1!
#1074
0!
#1076
b100 6
1!
#1078
0!
#1080
b11 6
1!
#1082
0!
#1084
b10 6
1!
#1086
0!
#1088
b1 6
1!
#1090
0!
#1092
b0 6
1!
#1094
0!
#1096
b10000 6
0#
0%
0$
0*
1!
#1097
1&
#1098
0!
#1100
b1111 6
1!
#1102
0!
#1104
b1110 6
1!
#1106
0!
#1108
b1101 6
1!
#1110
0!
#1112
b1100 6
1!
#1114
0!
#1116
b1011 6
1!
#1118
0!
#1120
b1010 6
1!
#1122
0!
#1124
b1001 6
1!
#1126
0!
#1128
b1000 6
1!
#1130
0!
#1132
b111 6
1!
#1134
0!
#1136
b110 6
1!
#1138
0!
#1140
b101 6
1!
#1142
0!
#1144
b100 6
1!
#1146
0!
#1148
b11 6
1!
#1150
0!
#1152
b10 6
1!
#1154
0!
#1156
b1 6
1!
#1158
0!
#1160
b0 6
1!
#1162
0!
#1164
0:
08
1>
0<
b10100001 5
b10100001 9
12
b0 1
b1000 M
b10000 6
1#
1%
1$
1*
1!
#1166
0!
#1168
b1111 6
1!
#1170
0!
#1172
b1110 6
1!
#1174
0!
#1176
b1101 6
1!
#1177
0&
#1178
0!
#1180
b1100 6
1!
#1182
0!
#1184
b1011 6
1!
#1186
0!
#1188
b1010 6
1!
#1190
0!
#1192
b1001 6
1!
#1194
0!
#1196
b1000 6
1!
#1198
0!
#1200
b111 6
1!
#1202
0!
#1204
b110 6
1!
#1206
0!
#1208
b101 6
1!
#1210
0!
#1212
b100 6
1!
#1214
0!
#1216
b11 6
1!
#1218
0!
#1220
b10 6
1!
#1222
0!
#1224
b1 6
1!
#1226
0!
#1228
b0 6
1!
#1230
0!
#1232
b10000 6
0#
0%
0$
0*
1!
#1234
0!
#1236
b1111 6
1!
#1238
0!
#1240
b1110 6
1!
#1242
0!
#1244
b1101 6
1!
#1246
0!
#1248
b1100 6
1!
#1250
0!
#1252
b1011 6
1!
1&
#1254
0!
#1256
b1010 6
1!
#1258
0!
#1260
b1001 6
1!
#1262
0!
#1264
b1000 6
1!
#1266
0!
#1268
b111 6
1!
#1270
0!
#1272
b110 6
1!
#1274
0!
#1276
b101 6
1!
#1278
0!
#1280
b100 6
1!
#1282
0!
#1284
b11 6
1!
#1286
0!
0&
#1288
b10 6
1!
#1290
0!
#1292
b1 6
1!
#1294
0!
#1296
b0 6
1!
#1298
0!
#1300
02
b1 1
b1000010 4
b0 M
b10000 6
1#
1%
1$
1*
1!
#1302
0!
#1304
b1111 6
1!
#1306
0!
#1308
b1110 6
1!
#1310
0!
#1312
b1101 6
1!
#1314
0!
#1316
b1100 6
1!
#1318
0!
#1320
b1011 6
1!
#1322
0!
#1324
b1010 6
1!
#1326
0!
#1328
b1001 6
1!
#1330
0!
#1332
b1000 6
1!
#1334
0!
#1336
b111 6
1!
#1338
0!
#1340
b110 6
1!
#1342
0!
#1344
b101 6
1!
#1346
0!
#1348
b100 6
1!
#1350
0!
#1352
b11 6
1!
#1354
0!
#1356
b10 6
1!
#1358
0!
#1360
b1 6
1!
#1361
1&
#1362
0!
#1364
b0 6
1!
#1366
0!
#1368
b10000 6
0#
0%
0$
0*
1!
#1370
0!
#1372
b1111 6
1!
#1374
0!
#1376
b1110 6
1!
#1378
0!
#1380
b1101 6
1!
#1382
0!
#1384
b1100 6
1!
#1386
0!
#1388
b1011 6
1!
#1390
0!
#1392
b1010 6
1!
#1394
0!
#1396
b1001 6
1!
#1398
0!
#1400
b1000 6
1!
#1402
0!
#1404
b111 6
1!
#1406
0!
#1408
b110 6
1!
#1410
0!
#1412
b101 6
1!
#1414
0!
#1416
b100 6
1!
#1418
0!
#1420
b11 6
1!
#1422
0!
#1424
b10 6
1!
#1426
0!
#1428
b1 6
1!
#1430
0!
#1432
b0 6
1!
#1434
0!
#1436
b10 1
b10000101 4
b1 M
b10000 6
1#
1%
1$
1*
1!
#1438
0!
#1440
b1111 6
1!
#1441
0&
#1442
0!
#1444
b1110 6
1!
#1446
0!
#1448
b1101 6
1!
#1450
0!
#1452
b1100 6
1!
#1454
0!
#1456
b1011 6
1!
#1458
0!
#1460
b1010 6
1!
#1462
0!
#1464
b1001 6
1!
#1466
0!
#1468
b1000 6
1!
#1470
0!
#1472
b111 6
1!
#1474
0!
#1476
b110 6
1!
#1478
0!
#1480
b101 6
1!
#1482
0!
#1484
b100 6
1!
#1486
0!
#1488
b11 6
1!
#1490
0!
#1492
b10 6
1!
#1494
0!
#1496
b1 6
1!
#1498
0!
#1500
b0 6
1!
#1502
0!
#1504
b10000 6
0#
0%
0$
0*
1!
#1506
0!
#1508
b1111 6
1!
#1510
0!
#1512
b1110 6
1!
#1514
0!
#1516
b1101 6
1!
#1518
0!
#1520
b1100 6
1!
#1522
0!
#1524
b1011 6
1!
#1526
0!
#1528
b1010 6
1!
#1530
0!
#1532
b1001 6
1!
#1534
0!
#1536
b1000 6
1!
#1538
0!
#1540
b111 6
1!
#1542
0!
#1544
b110 6
1!
#1546
0!
#1548
b101 6
1!
#1550
0!
#1552
b100 6
1!
#1554
0!
#1556
b11 6
1!
#1558
0!
#1560
b10 6
1!
#1562
0!
#1564
b1 6
1!
#1566
0!
#1568
b0 6
1!
#1570
0!
#1572
b11 1
b1010 4
b10 M
b10000 6
1#
1%
1$
1*
1!
#1574
0!
#1576
b1111 6
1!
#1578
0!
#1580
b1110 6
1!
#1582
0!
#1584
b1101 6
1!
#1586
0!
#1588
b1100 6
1!
#1590
0!
#1592
b1011 6
1!
#1594
0!
#1596
b1010 6
1!
#1598
0!
#1600
b1001 6
1!
#1602
0!
#1604
b1000 6
1!
#1606
0!
#1608
b111 6
1!
#1610
0!
#1612
b110 6
1!
#1614
0!
#1616
b101 6
1!
#1618
0!
#1620
b100 6
1!
#1622
0!
#1624
b11 6
1!
#1626
0!
#1628
b10 6
1!
#1630
0!
#1632
b1 6
1!
#1634
0!
#1636
b0 6
1!
#1638
0!
#1640
b10000 6
0#
0%
0$
0*
1!
#1642
0!
#1644
b1111 6
1!
#1646
0!
#1648
b1110 6
1!
#1650
0!
#1652
b1101 6
1!
#1654
0!
#1656
b1100 6
1!
#1658
0!
#1660
b1011 6
1!
#1662
0!
#1664
b1010 6
1!
#1666
0!
#1668
b1001 6
1!
#1670
0!
#1672
b1000 6
1!
#1674
0!
#1676
b111 6
1!
#1678
0!
#1680
b110 6
1!
#1682
0!
#1684
b101 6
1!
#1686
0!
#1688
b100 6
1!
#1690
0!
#1692
b11 6
1!
#1694
0!
#1696
b10 6
1!
#1698
0!
#1700
b1 6
1!
#1702
0!
#1704
b0 6
1!
#1706
0!
#1708
b100 1
b10100 4
b11 M
b10000 6
1#
1%
1$
1*
1!
#1710
0!
#1712
b1111 6
1!
#1714
0!
#1716
b1110 6
1!
#1718
0!
#1720
b1101 6
1!
#1722
0!
#1724
b1100 6
1!
#1726
0!
#1728
b1011 6
1!
#1730
0!
#1732
b1010 6
1!
#1734
0!
#1736
b1001 6
1!
#1738
0!
#1740
b1000 6
1!
#1742
0!
#1744
b111 6
1!
#1746
0!
#1748
b110 6
1!
#1750
0!
#1752
b101 6
1!
#1754
0!
#1756
b100 6
1!
#1758
0!
#1760
b11 6
1!
#1762
0!
#1764
b10 6
1!
#1766
0!
#1768
b1 6
1!
#1770
0!
#1772
b0 6
1!
#1774
0!
#1776
b10000 6
0#
0%
0$
0*
1!
#1778
0!
#1780
b1111 6
1!
#1782
0!
#1784
b1110 6
1!
#1786
0!
#1788
b1101 6
1!
#1790
0!
#1792
b1100 6
1!
#1794
0!
#1796
b1011 6
1!
#1798
0!
#1800
b1010 6
1!
#1802
0!
#1804
b1001 6
1!
#1806
0!
#1808
b1000 6
1!
#1810
0!
#1812
b111 6
1!
#1814
0!
#1816
b110 6
1!
#1818
0!
#1820
b101 6
1!
#1822
0!
#1824
b100 6
1!
#1826
0!
#1828
b11 6
1!
#1830
0!
#1832
b10 6
1!
#1834
0!
#1836
b1 6
1!
#1838
0!
#1840
b0 6
1!
#1842
0!
#1844
b101 1
b101000 4
b100 M
b10000 6
1#
1%
1$
1*
1!
#1846
0!
#1848
b1111 6
1!
#1850
0!
#1852
b1110 6
1!
#1854
0!
#1856
b1101 6
1!
#1858
0!
#1860
b1100 6
1!
#1862
0!
#1864
b1011 6
1!
#1866
0!
#1868
b1010 6
1!
#1870
0!
#1872
b1001 6
1!
#1874
0!
#1876
b1000 6
1!
#1878
0!
#1880
b111 6
1!
#1882
0!
#1884
b110 6
1!
#1886
0!
#1888
b101 6
1!
#1890
0!
#1892
b100 6
1!
#1894
0!
#1896
b11 6
1!
#1898
0!
#1900
b10 6
1!
#1902
0!
#1904
b1 6
1!
#1906
0!
#1908
b0 6
1!
#1910
0!
#1912
b10000 6
0#
0%
0$
0*
1!
#1914
0!
#1916
b1111 6
1!
#1918
0!
