HW/RTL/06PCM-AUDIO-MICROFONO/Version_01/02 verilog/MicNexys4/div_freq.v
module div_freq #(
              parameter   fi     = 100000000,           
              parameter   fs	 = 2000000        //flckout=((2.48*fs)/500000)KHZ
  )(input clk, output reg clkout,input reset, output reg led);



initial led=0;

reg [31:0] count;

always @(posedge  clk)
begin
	if (reset) begin
	led=0;
		count <= fi/fs;
		clkout <=0;
	end
	else begin
		led=1;
		count <=count-1;
		if (count==0)begin
			clkout <=~clkout;
			count <= fi/fs;
		end	
	end	
end


endmodule

HW/RTL/06PCM-AUDIO-MICROFONO/Version_01/02 verilog/MicNexys4/microfono.v
module microfono
(
	output reg	ledlr,
	output 		ledres,
	output 	reg	ledc,
	input		clk,
	output		mclk,
	input		lr,
	input		dataint,
	input		reset,
	output reg [5:0] sregt//sregtl
	//output reg [5:0] sregtr


);
reg [0:127] count1=0;
reg [127:0] sregtc;

div_freq df(.clk(clk), .reset(reset),.clkout(mclk),.led(ledres));

always @(posedge  mclk)
begin

	if (reset)
	begin
		if(lr)
		begin
		ledlr=1;
			if (count1<=5)  /* guarda 5 bits */
			begin
		
			ledc=1;
			sregt<= {sregt[4:0],dataint};
			sregtc<= {sregtc[126:0],dataint};
			count1<=count1+1;
			end
		
			else 
			begin
				if(count1<=127)
				begin
				ledc=0;
				sregtc<= {sregtc[126:0],dataint};
				count1<=count1+1;
				end
				else
				begin
				count1<=0;
				end
			end
		end
		else
		begin
		ledlr=0;
		end
	end
	 
	
end
 
endmodule

HW/RTL/06PCM-AUDIO-MICROFONO/Version_01/02 verilog/MicNexys4/pwm.v
module pwm(clk_in, x_in, PWM_out);

input clk_in; //clock for counter
input [5:0] x_in; //control value that
//defines pulse width
output reg PWM_out = 1; //PWM signal out

reg [5:0] counter = 0;

microfono mic(.mclk(clk_in), .sregt(x_in));


always@ (posedge clk_in )

begin
if ( counter < x_in )
PWM_out <= 1;
else
PWM_out <= 0;
counter <= counter+1;
end
endmodule

HW/RTL/06PCM-AUDIO-MICROFONO/Version_01/02 verilog/prueba pwm/controlador_TB.v
module controlador_TB;

reg dataint;
reg clk;
reg mclk;
reg ws;
reg reset;
reg lr;

microfono uut(.reset(reset),.dataint(dataint),.clk(clk),.lr(lr));
pwm pw(.PWM_out(PWM_out));
always
begin

clk =1'b1;
#2;
clk=1'b0;
#2;
end

initial
begin
reset =1'b0;
#10;
reset =1'b1;

end

initial
begin
lr =1'b0;
#10;
lr =1'b1;
#2000;
lr =1'b0;
#2000;
lr =1'b1;
end

initial begin
dataint = 1'b0;
#100 dataint = 1'b1;
#150 dataint = 1'b0;
#150 dataint = 1'b1;
#150 dataint = 1'b0;
#150 dataint = 1'b0;
#150 dataint = 1'b1;
#150 dataint = 1'b0;
#150 dataint = 1'b1;
end
	
initial begin: TEST_CASE
     $dumpfile("controlador_TB.vcd");
     $dumpvars(-1, uut, pw);
     #(100000) $finish;
   end

endmodule //

HW/RTL/06PCM-AUDIO-MICROFONO/Version_01/02 verilog/MicNexys4/simulation/controlador_TB.vcd
$date
	Tue Oct 31 15:42:52 2017
$end
$version
	Icarus Verilog
$end
$timescale
	1s
$end
$scope module controlador_TB $end
$scope module uut $end
$var wire 1 ! clk $end
$var wire 1 " dataint $end
$var wire 1 # lr $end
$var wire 1 $ reset $end
$var wire 1 % mclk $end
$var wire 1 & ledres $end
$var reg 128 ' count1 [0:127] $end
$var reg 1 ( ledc $end
$var reg 1 ) ledlr $end
$var reg 6 * sregt [5:0] $end
$var reg 128 + sregtc [127:0] $end
$scope module df $end
$var wire 1 ! clk $end
$var wire 1 $ reset $end
$var reg 1 % clkout $end
$var reg 32 , count [31:0] $end
$var reg 1 & led $end
$upscope $end
$upscope $end
$upscope $end
$scope module controlador_TB $end
$scope module pw $end
$var wire 6 - x_in [5:0] $end
$var wire 1 . clk_in $end
$var reg 1 / PWM_out $end
$var reg 6 0 counter [5:0] $end
$scope module mic $end
$var wire 1 1 clk $end
$var wire 1 2 dataint $end
$var wire 1 3 lr $end
$var wire 1 4 reset $end
$var wire 1 . mclk $end
$var wire 1 5 ledres $end
$var reg 128 6 count1 [0:127] $end
$var reg 1 7 ledc $end
$var reg 1 8 ledlr $end
$var reg 6 9 sregt [5:0] $end
$var reg 128 : sregtc [127:0] $end
$scope module df $end
$var wire 1 1 clk $end
$var wire 1 4 reset $end
$var reg 1 . clkout $end
$var reg 32 ; count [31:0] $end
$var reg 1 5 led $end
$upscope $end
$upscope $end
$upscope $end
$upscope $end
$enddefinitions $end
#0
$dumpvars
bx ;
bx :
bx 9
x8
x7
b0 6
05
z4
z3
z2
z1
b0 0
1/
x.
bx -
b10100 ,
bx +
bx *
x)
x(
b0 '
0&
0%
0$
0#
0"
1!
$end
#2
0!
#4
1!
#6
0!
#8
1!
#10
0!
1#
1$
#12
b10011 ,
1&
1!
#14
0!
#16
b10010 ,
1!
#18
0!
#20
b10001 ,
1!
#22
0!
#24
b10000 ,
1!
#26
0!
#28
b1111 ,
1!
#30
0!
#32
b1110 ,
1!
#34
0!
#36
b1101 ,
1!
#38
0!
#40
b1100 ,
1!
#42
0!
#44
b1011 ,
1!
#46
0!
#48
b1010 ,
1!
#50
0!
#52
b1001 ,
1!
#54
0!
#56
b1000 ,
1!
#58
0!
#60
b111 ,
1!
#62
0!
#64
b110 ,
1!
#66
0!
#68
b101 ,
1!
#70
0!
#72
b100 ,
1!
#74
0!
#76
b11 ,
1!
#78
0!
#80
b10 ,
1!
#82
0!
#84
b1 ,
1!
#86
0!
#88
b0 ,
1!
#90
0!
#92
b1 '
bx0 +
bx0 *
1(
1)
1%
b10100 ,
1!
#94
0!
#96
b10011 ,
1!
#98
0!
#100
b10010 ,
1!
1"
#102
0!
#104
b10001 ,
1!
#106
0!
#108
b10000 ,
1!
#110
0!
#112
b1111 ,
1!
#114
0!
#116
b1110 ,
1!
#118
0!
#120
b1101 ,
1!
#122
0!
#124
b1100 ,
1!
#126
0!
#128
b1011 ,
1!
#130
0!
#132
b1010 ,
1!
#134
0!
#136
b1001 ,
1!
#138
0!
#140
b1000 ,
1!
#142
0!
#144
b111 ,
1!
#146
0!
#148
b110 ,
1!
#150
0!
#152
b101 ,
1!
#154
0!
#156
b100 ,
1!
#158
0!
#160
b11 ,
1!
#162
0!
#164
b10 ,
1!
#166
0!
#168
b1 ,
1!
#170
0!
#172
b0 ,
1!
#174
0!
#176
0%
b10100 ,
1!
#178
0!
#180
b10011 ,
1!
#182
0!
#184
b10010 ,
1!
#186
0!
#188
b10001 ,
1!
#190
0!
#192
b10000 ,
1!
#194
0!
#196
b1111 ,
1!
#198
0!
#200
b1110 ,
1!
#202
0!
#204
b1101 ,
1!
#206
0!
#208
b1100 ,
1!
#210
0!
#212
b1011 ,
1!
#214
0!
#216
b1010 ,
1!
#218
0!
#220
b1001 ,
1!
#222
0!
#224
b1000 ,
1!
#226
0!
#228
b111 ,
1!
#230
0!
#232
b110 ,
1!
#234
0!
#236
b101 ,
1!
#238
0!
#240
b100 ,
1!
#242
0!
#244
b11 ,
1!
#246
0!
#248
b10 ,
1!
#250
0!
0"
#252
b1 ,
1!
#254
0!
#256
b0 ,
1!
#258
0!
#260
b10 '
bx00 +
bx00 *
1%
b10100 ,
1!
#262
0!
#264
b10011 ,
1!
#266
0!
#268
b10010 ,
1!
#270
0!
#272
b10001 ,
1!
#274
0!
#276
b10000 ,
1!
#278
0!
#280
b1111 ,
1!
#282
0!
#284
b1110 ,
1!
#286
0!
#288
b1101 ,
1!
#290
0!
#292
b1100 ,
1!
#294
0!
#296
b1011 ,
1!
#298
0!
#300
b1010 ,
1!
#302
0!
#304
b1001 ,
1!
#306
0!
#308
b1000 ,
1!
#310
0!
#312
b111 ,
1!
#314
0!
#316
b110 ,
1!
#318
0!
#320
b101 ,
1!
#322
0!
#324
b100 ,
1!
#326
0!
#328
b11 ,
1!
#330
0!
#332
b10 ,
1!
#334
0!
#336
b1 ,
1!
#338
0!
#340
b0 ,
1!
#342
0!
#344
0%
b10100 ,
1!
#346
0!
#348
b10011 ,
1!
#350
0!
#352
b10010 ,
1!
#354
0!
#356
b10001 ,
1!
#358
0!
#360
b10000 ,
1!
#362
0!
#364
b1111 ,
1!
#366
0!
#368
b1110 ,
1!
#370
0!
#372
b1101 ,
1!
#374
0!
#376
b1100 ,
1!
#378
0!
#380
b1011 ,
1!
#382
0!
#384
b1010 ,
1!
#386
0!
#388
b1001 ,
1!
#390
0!
#392
b1000 ,
1!
#394
0!
#396
b111 ,
1!
#398
0!
#400
b110 ,
1!
1"
#402
0!
#404
b101 ,
1!
#406
0!
#408
b100 ,
1!
#410
0!
#412
b11 ,
1!
#414
0!
#416
b10 ,
1!
#418
0!
#420
b1 ,
1!
#422
0!
#424
b0 ,
1!
#426
0!
#428
b11 '
bx001 +
bx001 *
1%
b10100 ,
1!
#430
0!
#432
b10011 ,
1!
#434
0!
#436
b10010 ,
1!
#438
0!
#440
b10001 ,
1!
#442
0!
#444
b10000 ,
1!
#446
0!
#448
b1111 ,
1!
#450
0!
#452
b1110 ,
1!
#454
0!
#456
b1101 ,
1!
#458
0!
#460
b1100 ,
1!
#462
0!
#464
b1011 ,
1!
#466
0!
#468
b1010 ,
1!
#470
0!
#472
b1001 ,
1!
#474
0!
#476
b1000 ,
1!
#478
0!
#480
b111 ,
1!
#482
0!
#484
b110 ,
1!
#486
0!
#488
b101 ,
1!
#490
0!
#492
b100 ,
1!
#494
0!
#496
b11 ,
1!
#498
0!
#500
b10 ,
1!
#502
0!
#504
b1 ,
1!
#506
0!
#508
b0 ,
1!
#510
0!
#512
0%
b10100 ,
1!
#514
0!
#516
b10011 ,
1!
#518
0!
#520
b10010 ,
1!
#522
0!
#524
b10001 ,
1!
#526
0!
#528
b10000 ,
1!
#530
0!
#532
b1111 ,
1!
#534
0!
#536
b1110 ,
1!
#538
0!
#540
b1101 ,
1!
#542
0!
#544
b1100 ,
1!
#546
0!
#548
b1011 ,
1!
#550
0!
0"
#552
b1010 ,
1!
#554
0!
#556
b1001 ,
1!
#558
0!
#560
b1000 ,
1!
#562
0!
#564
b111 ,
1!
#566
0!
#568
b110 ,
1!
#570
0!
#572
b101 ,
1!
#574
0!
#576
b100 ,
1!
#578
0!
#580
b11 ,
1!
#582
0!
#584
b10 ,
1!
#586
0!
#588
b1 ,
1!
#590
0!
#592
b0 ,
1!
#594
0!
#596
b100 '
bx0010 +
bx0010 *
1%
b10100 ,
1!
#598
0!
#600
b10011 ,
1!
#602
0!
#604
b10010 ,
1!
#606
0!
#608
b10001 ,
1!
#610
0!
#612
b10000 ,
1!
#614
0!
#616
b1111 ,
1!
#618
0!
#620
b1110 ,
1!
#622
0!
#624
b1101 ,
1!
#626
0!
#628
b1100 ,
1!
#630
0!
#632
b1011 ,
1!
#634
0!
#636
b1010 ,
1!
#638
0!
#640
b1001 ,
1!
#642
0!
#644
b1000 ,
1!
#646
0!
#648
b111 ,
1!
#650
0!
#652
b110 ,
1!
#654
0!
#656
b101 ,
1!
#658
0!
#660
b100 ,
1!
#662
0!
#664
b11 ,
1!
#666
0!
#668
b10 ,
1!
#670
0!
#672
b1 ,
1!
#674
0!
#676
b0 ,
1!
#678
0!
#680
0%
b10100 ,
1!
#682
0!
#684
b10011 ,
1!
#686
0!
#688
b10010 ,
1!
#690
0!
#692
b10001 ,
1!
#694
0!
#696
b10000 ,
1!
#698
0!
#700
b1111 ,
1!
#702
0!
#704
b1110 ,
1!
#706
0!
#708
b1101 ,
1!
#710
0!
#712
b1100 ,
1!
#714
0!
#716
b1011 ,
1!
#718
0!
#720
b1010 ,
1!
#722
0!
#724
b1001 ,
1!
#726
0!
#728
b1000 ,
1!
#730
0!
#732
b111 ,
1!
#734
0!
#736
b110 ,
1!
#738
0!
#740
b101 ,
1!
#742
0!
#744
b100 ,
1!
#746
0!
#748
b11 ,
1!
#750
0!
#752
b10 ,
1!
#754
0!
#756
b1 ,
1!
#758
0!
#760
b0 ,
1!
#762
0!
#764
b101 '
bx00100 +
bx00100 *
1%
b10100 ,
1!
#766
0!
#768
b10011 ,
1!
#770
0!
#772
b10010 ,
1!
#774
0!
#776
b10001 ,
1!
#778
0!
#780
b10000 ,
1!
#782
0!
#784
b1111 ,
1!
#786
0!
#788
b1110 ,
1!
#790
0!
#792
b1101 ,
1!
#794
0!
#796
b1100 ,
1!
#798
0!
#800
b1011 ,
1!
#802
0!
#804
b1010 ,
1!
#806
0!
#808
b1001 ,
1!
#810
0!
#812
b1000 ,
1!
#814
0!
#816
b111 ,
1!
#818
0!
#820
b110 ,
1!
#822
0!
#824
b101 ,
1!
#826
0!
#828
b100 ,
1!
#830
0!
#832
b11 ,
1!
#834
0!
#836
b10 ,
1!
#838
0!
#840
b1 ,
1!
#842
0!
#844
b0 ,
1!
#846
0!
#848
0%
b10100 ,
1!
#850
0!
1"
#852
b10011 ,
1!
#854
0!
#856
b10010 ,
1!
#858
0!
#860
b10001 ,
1!
#862
0!
#864
b10000 ,
1!
#866
0!
#868
b1111 ,
1!
#870
0!
#872
b1110 ,
1!
#874
0!
#876
b1101 ,
1!
#878
0!
#880
b1100 ,
1!
#882
0!
#884
b1011 ,
1!
#886
0!
#888
b1010 ,
1!
#890
0!
#892
b1001 ,
1!
#894
0!
#896
b1000 ,
1!
#898
0!
#900
b111 ,
1!
#902
0!
#904
b110 ,
1!
#906
0!
#908
b101 ,
1!
#910
0!
#912
b100 ,
1!
#914
0!
#916
b11 ,
1!
#918
0!
#920
b10 ,
1!
#922
0!
#924
b1 ,
1!
#926
0!
#928
b0 ,
1!
#930
0!
#932
b110 '
bx001001 +
b1001 *
1%
b10100 ,
1!
#934
0!
#936
b10011 ,
1!
#938
0!
#940
b10010 ,
1!
#942
0!
#944
b10001 ,
1!
#946
0!
#948
b10000 ,
1!
#950
0!
#952
b1111 ,
1!
#954
0!
#956
b1110 ,
1!
#958
0!
#960
b1101 ,
1!
#962
0!
#964
b1100 ,
1!
#966
0!
#968
b1011 ,
1!
#970
0!
#972
b1010 ,
1!
#974
0!
#976
b1001 ,
1!
#978
0!
#980
b1000 ,
1!
#982
0!
#984
b111 ,
1!
#986
0!
#988
b110 ,
1!
#990
0!
#992
b101 ,
1!
#994
0!
#996
b100 ,
1!
#998
0!
#1000
b11 ,
1!
0"
#1002
0!
#1004
b10 ,
1!
#1006
0!
#1008
b1 ,
1!
#1010
0!
#1012
b0 ,
1!
#1014
0!
#1016
0%
b10100 ,
1!
#1018
0!
#1020
b10011 ,
1!
#1022
0!
#1024
b10010 ,
1!
#1026
0!
#1028
b10001 ,
1!
#1030
0!
#1032
b10000 ,
1!
#1034
0!
#1036
b1111 ,
1!
#1038
0!
#1040
b1110 ,
1!
#1042
0!
#1044
b1101 ,
1!
#1046
0!
#1048
b1100 ,
1!
#1050
0!
#1052
b1011 ,
1!
#1054
0!
#1056
b1010 ,
1!
#1058
0!
#1060
b1001 ,
1!
#1062
0!
#1064
b1000 ,
1!
#1066
0!
#1068
b111 ,
1!
#1070
0!
#1072
b110 ,
1!
#1074
0!
#1076
b101 ,
1!
#1078
0!
#1080
b100 ,
1!
#1082
0!
#1084
b11 ,
1!
#1086
0!
#1088
b10 ,
1!
#1090
0!
#1092
b1 ,
1!
#1094
0!
#1096
b0 ,
1!
#1098
0!
#1100
b111 '
bx0010010 +
0(
1%
b10100 ,
1!
#1102
0!
#1104
b10011 ,
1!
#1106
0!
#1108
b10010 ,
1!
#1110
0!
#1112
b10001 ,
1!
#1114
0!
#1116
b10000 ,
1!
#1118
0!
#1120
b1111 ,
1!
#1122
0!
#1124
b1110 ,
1!
#1126
0!
#1128
b1101 ,
1!
#1130
0!
#1132
b1100 ,
1!
#1134
0!
#1136
b1011 ,
1!
#1138
0!
#1140
b1010 ,
1!
#1142
0!
#1144
b1001 ,
1!
#1146
0!
#1148
b1000 ,
1!
#1150
0!
1"
#1152
b111 ,
1!
#1154
0!
#1156
b110 ,
1!
#1158
0!
#1160
b101 ,
1!
#1162
0!
#1164
b100 ,
1!
#1166
0!
#1168
b11 ,
1!
#1170
0!
#1172
b10 ,
1!
#1174
0!
#1176
b1 ,
1!
#1178
0!
#1180
b0 ,
1!
#1182
0!
#1184
0%
b10100 ,
1!
#1186
0!
#1188
b10011 ,
1!
#1190
0!
#1192
b10010 ,
1!
#1194
0!
#1196
b10001 ,
1!
#1198
0!
#1200
b10000 ,
1!
#1202
0!
#1204
b1111 ,
1!
#1206
0!
#1208
b1110 ,
1!
#1210
0!
#1212
b1101 ,
1!
#1214
0!
#1216
b1100 ,
1!
#1218
0!
#1220
b1011 ,
1!
#1222
0!
#1224
b1010 ,
1!
#1226
0!
#1228
b1001 ,
1!
#1230
0!
#1232
b1000 ,
1!
#1234
0!
#1236
b111 ,
1!
#1238
0!
#1240
b110 ,
1!
#1242
0!
#1244
b101 ,
1!
#1246
0!
#1248
b100 ,
1!
#1250
0!
#1252
b11 ,
1!
#1254
0!
#1256
b10 ,
1!
#1258
0!
#1260
b1 ,
1!
#1262
0!
#1264
b0 ,
1!
#1266
0!
#1268
b1000 '
bx00100101 +
1%
b10100 ,
1!
#1270
0!
#1272
b10011 ,
1!
#1274
0!
#1276
b10010 ,
1!
#1278
0!
#1280
b10001 ,
1!
#1282
0!
#1284
b10000 ,
1!
#1286
0!
#1288
b1111 ,
1!
#1290
0!
#1292
b1110 ,
1!
#1294
0!
#1296
b1101 ,
1!
#1298
0!
#1300
b1100 ,
1!
#1302
0!
#1304
b1011 ,
1!
#1306
0!
#1308
b1010 ,
1!
#1310
0!
#1312
b1001 ,
1!
#1314
0!
#1316
b1000 ,
1!
#1318
0!
#1320
b111 ,
1!
#1322
0!
#1324
b110 ,
1!
#1326
0!
#1328
b101 ,
1!
#1330
0!
#1332
b100 ,
1!
#1334
0!
#1336
b11 ,
1!
#1338
0!
#1340
b10 ,
1!
#1342
0!
#1344
b1 ,
1!
#1346
0!
#1348
b0 ,
1!
#1350
0!
#1352
0%
b10100 ,
1!
#1354
0!
#1356
b10011 ,
1!
#1358
0!
#1360
b10010 ,
1!
#1362
0!
#1364
b10001 ,
1!
#1366
0!
#1368
b10000 ,
1!
#1370
0!
#1372
b1111 ,
1!
#1374
0!
#1376
b1110 ,
1!
#1378
0!
#1380
b1101 ,
1!
#1382
0!
#1384
b1100 ,
1!
#1386
0!
#1388
b1011 ,
1!
#1390
0!
#1392
b1010 ,
1!
#1394
0!
#1396
b1001 ,
1!
#1398
0!
#1400
b1000 ,
1!
#1402
0!
#1404
b111 ,
1!
#1406
0!
#1408
b110 ,
1!
#1410
0!
#1412
b101 ,
1!
#1414
0!
#1416
b100 ,
1!
#1418
0!
#1420
b11 ,
1!
#1422
0!
#1424
b10 ,
1!
#1426
0!
#1428
b1 ,
1!
#1430
0!
#1432
b0 ,
1!
#1434
0!
#1436
b1001 '
bx001001011 +
1%
b10100 ,
1!
#1438
0!
#1440
b10011 ,
1!
#1442
0!
#1444
b10010 ,
1!
#1446
0!
#1448
b10001 ,
1!
#1450
0!
#1452
b10000 ,
1!
#1454
0!
#1456
b1111 ,
1!
#1458
0!
#1460
b1110 ,
1!
#1462
0!
#1464
b1101 ,
1!
#1466
0!
#1468
b1100 ,
1!
#1470
0!
#1472
b1011 ,
1!
#1474
0!
#1476
b1010 ,
1!
#1478
0!
#1480
b1001 ,
1!
#1482
0!
#1484
b1000 ,
1!
#1486
0!
#1488
b111 ,
1!
#1490
0!
#1492
b110 ,
1!
#1494
0!
#1496
b101 ,
1!
#1498
0!
#1500
b100 ,
1!
#1502
0!
#1504
b11 ,
1!
#1506
0!
#1508
b10 ,
1!
#1510
0!
#1512
b1 ,
1!
#1514
0!
#1516
b0 ,
1!
#1518
0!
#1520
0%
b10100 ,
1!
#1522
0!
#1524
b10011 ,
1!
#1526
0!
#1528
b10010 ,
1!
#1530
0!
#1532
b10001 ,
1!
#1534
0!
#1536
b10000 ,
1!
#1538
0!
#1540
b1111 ,
1!
#1542
0!
#1544
b1110 ,
1!
#1546
0!
#1548
b1101 ,
1!
#1550
0!
#1552
b1100 ,
1!
#1554
0!
#1556
b1011 ,
1!
#1558
0!
#1560
b1010 ,
1!
#1562
0!
#1564
b1001 ,
1!
#1566
0!
#1568
b1000 ,
1!
#1570
0!
#1572
b111 ,
1!
#1574
0!
#1576
b110 ,
1!
#1578
0!
#1580
b101 ,
1!
#1582
0!
#1584
b100 ,
1!
#1586
0!
#1588
b11 ,
1!
#1590
0!
#1592
b10 ,
1!
#1594
0!
#1596
b1 ,
1!
#1598
0!
#1600
b0 ,
1!
#1602
0!
#1604
b1010 '
bx0010010111 +
1%
b10100 ,
1!
#1606
0!
#1608
b10011 ,
1!
#1610
0!
#1612
b10010 ,
1!
#1614
0!
#1616
b10001 ,
1!
#1618
0!
#1620
b10000 ,
1!
#1622
0!
#1624
b1111 ,
1!
#1626
0!
#1628
b1110 ,
1!
#1630
0!
#1632
b1101 ,
1!
#1634
0!
#1636
b1100 ,
1!
#1638
0!
#1640
b1011 ,
1!
#1642
0!
#1644
b1010 ,
1!
#1646
0!
#1648
b1001 ,
1!
#1650
0!
#1652
b1000 ,
1!
#1654
0!
#1656
b111 ,
1!
#1658
0!
#1660
b110 ,
1!
#1662
0!
#1664
b101 ,
1!
#1666
0!
#1668
b100 ,
1!
#1670
0!
#1672
b11 ,
1!
#1674
0!
#1676
b10 ,
1!
#1678
0!
#1680
b1 ,
1!
#1682
0!
#1684
b0 ,
1!
#1686
0!
#1688
0%
b10100 ,
1!
#1690
0!
#1692
b10011 ,
1!
#1694
0!
#1696
b10010 ,
1!
#1698
0!
#1700
b10001 ,
1!
#1702
0!
#1704
b10000 ,
1!
#1706
0!
#1708
b1111 ,
1!
#1710
0!
#1712
b1110 ,
1!
#1714
0!
#1716
b1101 ,
1!
#1718
0!
#1720
b1100 ,
1!
#1722
0!
#1724
b1011 ,
1!
#1726
0!
#1728
b1010 ,
1!
#1730
0!
#1732
b1001 ,
1!
#1734
0!
#1736
b1000 ,
1!
#1738
0!
#1740
b111 ,
1!
#1742
0!
#1744
b110 ,
1!
#1746
0!
#1748
b101 ,
1!
#1750
0!
#1752
b100 ,
1!
#1754
0!
#1756
b11 ,
1!
#1758
0!
#1760
b10 ,
1!
#1762
0!
#1764
b1 ,
1!
#1766
0!
#1768
b0 ,
1!
#1770
0!
#1772
b1011 '
bx00100101111 +
1%
b10100 ,
1!
#1774
0!
#1776
b10011 ,
1!
#1778
0!
#1780
b10010 ,
1!
#1782
0!
#1784
b10001 ,
1!
#1786
0!
#1788
b10000 ,
1!
#1790
0!
#1792
b1111 ,
1!
#1794
0!
#1796
b1110 ,
1!
#1798
0!
#1800
b1101 ,
1!
#1802
0!
#1804
b1100 ,
1!
#1806
0!
#1808
b1011 ,
1!
#1810
0!
#1812
b1010 ,
1!
#1814
0!
#1816
b1001 ,
1!
#1818
0!
#1820
b1000 ,
1!
#1822
0!
#1824
b111 ,
1!
#1826
0!
#1828
b110 ,
1!
#1830
0!
#1832
b101 ,
1!
#1834
0!
#1836
b100 ,
1!
#1838
0!
#1840
b11 ,
1!
#1842
0!
#1844
b10 ,
1!
#1846
0!
#1848
b1 ,
1!
#1850
0!
#1852
b0 ,
1!
#1854
0!
#1856
0%
b10100 ,
1!
#1858
0!
#1860
b10011 ,
1!
#1862
0!
#1864
b10010 ,
1!
#1866
0!
#1868
b10001 ,
1!
#1870
0!
#1872
b10000 ,
1!
#1874
0!
#1876
b1111 ,
1!
#1878
0!
#1880
b1110 ,
1!
#1882
0!
#1884
b1101 ,
1!
#1886
0!
#1888
b1100 ,
1!
#1890
0!
#1892
b1011 ,
1!
#1894
0!
#1896
b1010 ,
1!
#1898
0!
#1900
b1001 ,
1!
#1902
0!
#1904
b1000 ,
1!
#1906
0!
#1908
b111 ,
1!
#1910
0!
#1912
b110 ,
1!
#1914
0!
#1916
b101 ,
1!
#1918
0!
#1920
b100 ,
1!
#1922
0!
#1924
b11 ,
1!
#1926
0!
#1928
b10 ,
1!
#1930
0!
#1932
b1 ,
1!
#1934
0!
#1936
b0 ,
1!
#1938
0!
#1940
b1100 '
bx001001011111 +
1%
b10100 ,
1!
#1942
0!
#1944
b10011 ,
1!
#1946
0!
#1948
b10010 ,
1!
#1950
0!
#1952
b10001 ,
1!
#1954
0!
#1956
b10000 ,
1!
#1958
0!
#1960
b1111 ,
1!
#1962
0!
#1964
b1110 ,
1!
#1966
0!
#1968
b1101 ,
1!
#1970
0!
#1972
b1100 ,
1!
#1974
0!
#1976
b1011 ,
1!
#1978
0!
#1980
b1010 ,
1!
#1982
0!
#1984
b1001 ,
1!
#1986
0!
#1988
b1000 ,
1!
#1990
0!
#1992
b111 ,
1!
#1994
0!
#1996
b110 ,
1!
#1998
0!
#2000
b101 ,
1!
#2002
0!
#2004
b100 ,
1!
#2006
0!
#2008
b11 ,
1!
#2010
0!
0#
#2012
b10 ,
1!
#2014
0!
#2016
b1 ,
1!
#2018
0!
#2020
b0 ,
1!
#2022
0!
#2024
0%
b10100 ,
1!
#2026
0!
#2028
b10011 ,
1!
#2030
0!
#2032
b10010 ,
1!
#2034
0!
#2036
b10001 ,
1!
#2038
0!
#2040
b10000 ,
1!
#2042
0!
#2044
b1111 ,
1!
#2046
0!
#2048
b1110 ,
1!
#2050
0!
#2052
b1101 ,
1!
#2054
0!
#2056
b1100 ,
1!
#2058
0!
#2060
b1011 ,
1!
#2062
0!
#2064
b1010 ,
1!
#2066
0!
#2068
b1001 ,
1!
#2070
0!
#2072
b1000 ,
1!
#2074
0!
#2076
b111 ,
1!
#2078
0!
#2080
b110 ,
1!
#2082
0!
#2084
b101 ,
1!
#2086
0!
#2088
b100 ,
1!
#2090
0!
#2092
b11 ,
1!
#2094
0!
#2096
b10 ,
1!
#2098
0!
#2100
b1 ,
1!
#2102
0!
#2104
b0 ,
1!
#2106
0!
#2108
0)
1%
b10100 ,
1!
#2110
0!
#2112
b10011 ,
1!
#2114
0!
#2116
b10010 ,
1!
#2118
0!
#2120
b10001 ,
1!
#2122
0!
#2124
b10000 ,
1!
#2126
0!
#2128
b1111 ,
1!
#2130
0!
#2132
b1110 ,
1!
#2134
0!
#2136
b1101 ,
1!
#2138
0!
#2140
b1100 ,
1!
#2142
0!
#2144
b1011 ,
1!
#2146
0!
#2148
b1010 ,
1!
#2150
0!
#2152
b1001 ,
1!
#2154
0!
#2156
b1000 ,
1!
#2158
0!
#2160
b111 ,
1!
#2162
0!
#2164
b110 ,
1!
#2166
0!
#2168
b101 ,
1!
#2170
0!
#2172
b100 ,
1!
#2174
0!
#2176
b11 ,
1!
#2178
0!
#2180
b10 ,
1!
#2182
0!
#2184
b1 ,
1!
#2186
0!
#2188
b0 ,
1!
#2190
0!
#2192
0%
b10100 ,
1!
#2194
0!
#2196
b10011 ,
1!
#2198
0!
#2200
b10010 ,
1!
#2202
0!
#2204
b10001 ,
1!
#2206
0!
#2208
b10000 ,
1!
#2210
0!
#2212
b1111 ,
1!
#2214
0!
#2216
b1110 ,
1!
#2218
0!
#2220
b1101 ,
1!
#2222
0!
#2224
b1100 ,
1!
#2226
0!
#2228
b1011 ,
1!
#2230
0!
#2232
b1010 ,
1!
#2234
0!
#2236
b1001 ,
1!
#2238
0!
#2240
b1000 ,
1!
#2242
0!
#2244
b111 ,
1!
#2246
0!
#2248
b110 ,
1!
#2250
0!
#2252
b101 ,
1!
#2254
0!
#2256
b100 ,
1!
#2258
0!
#2260
b11 ,
1!
#2262
0!
#2264
b10 ,
1!
#2266
0!
#2268
b1 ,
1!
#2270
0!
#2272
b0 ,
1!
#2274
0!
#2276
1%
b10100 ,
1!
#2278
0!
#2280
b10011 ,
1!
#2282
0!
#2284
b10010 ,
1!
#2286
0!
#2288
b10001 ,
1!
#2290
0!
#2292
b10000 ,
1!
#2294
0!
#2296
b1111 ,
1!
#2298
0!
#2300
b1110 ,
1!
#2302
0!
#2304
b1101 ,
1!
#2306
0!
#2308
b1100 ,
1!
#2310
0!
#2312
b1011 ,
1!
#2314
0!
#2316
b1010 ,
1!
#2318
0!
#2320
b1001 ,
1!
#2322
0!
#2324
b1000 ,
1!
#2326
0!
#2328
b111 ,
1!
#2330
0!
#2332
b110 ,
1!
#2334
0!
#2336
b101 ,
1!
#2338
0!
#2340
b100 ,
1!
#2342
0!
#2344
b11 ,
1!
#2346
0!
#2348
b10 ,
1!
#2350
0!
#2352
b1 ,
1!
#2354
0!
#2356
b0 ,
1!
#2358
0!
#2360
0%
b10100 ,
1!
#2362
0!
#2364
b10011 ,
1!
#2366
0!
#2368
b10010 ,
1!
#2370
0!
#2372
b10001 ,
1!
#2374
0!
#2376
b10000 ,
1!
#2378
0!
#2380
b1111 ,
1!
#2382
0!
#2384
b1110 ,
1!
#2386
0!
#2388
b1101 ,
1!
#2390
0!
#2392
b1100 ,
1!
#2394
0!
#2396
b1011 ,
1!
#2398
0!
#2400
b1010 ,
1!
#2402
0!
#2404
b1001 ,
1!
#2406
0!
#2408
b1000 ,
1!
#2410
0!
#2412
b111 ,
1!
#2414
0!
#2416
b110 ,
1!
#2418
0!
#2420
b101 ,
1!
#2422
0!
#2424
b100 ,
1!
#2426
0!
#2428
b11 ,
1!
#2430
0!
#2432
b10 ,
1!
#2434
0!
#2436
b1 ,
1!
#2438
0!
#2440
b0 ,
1!
#2442
0!
#2444
1%
b10100 ,
1!
#2446
0!
#2448
b10011 ,
1!
#2450
0!
#2452
b10010 ,
1!
#2454
0!
#2456
b10001 ,
1!
#2458
0!
#2460
b10000 ,
1!
#2462
0!
#2464
b1111 ,
1!
#2466
0!
#2468
b1110 ,
1!
#2470
0!
#2472
b1101 ,
1!
#2474
0!
#2476
b1100 ,
1!
#2478
0!
#2480
b1011 ,
1!
#2482
0!
